Workbook

Sheet Input-Unit
C2: Unit economics of the project | F2: Made by | G2: https://feofinance.com/
C4: Input parameters
B6: 1. | C6: Cells that can be changed | D6: ххх
B7: 2. | C7: Cells that can't be changed (they contain a formula) | D7: =D6 -> ххх
B9: 3. | C9: Name of the project | D9: StepUP
B12: 1. | C12: Number of customers (subscribers) and conversions
B14: № | C14: Name | D14: Value | E14: Unit. | H14: SDR Velocity
B15: 1. | C15: Number of visits (clicks) (UA) | D15: 1000 | E15: units/month | H15: Working hours | I15: 8
B16: 2. | C16: Conversion to Registration (C1) | D16: 0.08 | E16: % | H16: Days | I16: 20
B17: 3. | C17: Total number of registrations (leads) | D17: =D15*D16 -> 80 | E17: units/month | H17: Call duration hours | I17: 0.5
B18: 4. | C18: Conversion from registration to payment (C2) | D18: 0.3 | E18: % | H18: Schedule fullfillment | I18: 0.8
B19: 5. | C19: Total number of paying users (B) | D19: =D18*D17 -> 24 | E19: units/month | H19: Calls done /month | I19: =I15*I16*I17*I18 -> 64
B20: 6. | C20: Final conversion from click to purchase (C3) | D20: =D16*D18 -> 0.024 | E20: % | H20: SDR HC | I20: =D17/I19 -> 1.25
B23: 2. | C23: Lifetime value (LTV)
G24: Смотрим модель с вариантами ARPPU
B25: № | C25: Name | D25: =D14 -> Value | E25: =E14 -> Unit. | G25: 200 | H25: 1
B26: 1. | C26: Average revenue per paying customer (ARPPU) | D26: 400 | E26: $ / month | G26: 400 | H26: 2
B27: 2. | C27: Customer Lifetime (CL) | D27: 27 | E27: months | G27: 1500 | H27: 3
B28: 3. | C28: Lifetime value (LTV) | D28: =sum('Results-Unit'!D35:O35)*D26/D19 -> 3822.2222 | E28: $
B29: 4. | C29: Churn rate | D29: =1/D27 -> 0.037037037 | E29: %
B32: 3. | C32: Customer Acquisition Cost (CAC)
B34: 3.1. | C34: Advertising costs
B36: =B$25 -> № | C36: =C$25 -> Name | D36: =D$25 -> Value | E36: =E$25 -> Unit.
B37: 1. | C37: Cost of 1 visit (click) | D37: 5 | E37: $
B38: 2. | C38: Number of visits (clicks) | D38: =$D$15 -> 1000 | E38: $ / unit
C39: Total advertising expenses | D39: =D37*D38 -> 5000 | E39: $ / month
B42: 3.2. | C42: Salary (not all staff, but only for marketing and advertising departments)
B44: =B$25 -> № | C44: =C$25 -> Name | D44: =D$25 -> Value | E44: =E$25 -> Unit.
B45: 1. | C45: Sales Development Representative | D45: =F45*I20 -> 2500 | E45: $ / month | F45: 2000
B46: 2. | C46: Product Manager | D46: 3000 | E46: $ / month
B47: 3. | C47: Founder | D47: 3000 | E47: $ / month
B48: 4. | E48: $ / month
B49: 5. | E49: $ / month
B50: 6. | E50: $ / month
B51: 7. | E51: $ / month
B52: 8. | E52: $ / month
B53: 9. | E53: $ / month
B54: 10. | E54: $ / month
C55: Total salary | D55: =SUM(D45:D54) -> 8500 | E55: $ / month
B58: 3.3. | C58: Other marketing and advertising expenses
B60: =B$25 -> № | C60: =C$25 -> Name | D60: =D$25 -> Value | E60: =E$25 -> Unit.
B61: 1. | D61: 0 | E61: $ / month
B62: 2. | E62: $ / month
B63: 3. | D63: 0 | E63: $ / month
B64: 4. | D64: 0 | E64: $ / month
B65: 5. | D65: 0 | E65: $ / month
C66: Total other marketing and advertising expenses | D66: =SUM(D61:D65) -> 0 | E66: $ / month
B69: 3.4. | C69: Total cost of customer acquisition
B71: № | C71: Total expenses: | D71: =D39+D55+D66 -> 13500 | E71: $ / month
B72: 1. | C72: per 1 potential client (per 1 click) | D72: =D$71/D15 -> 13.5 | E72: $
B73: 2. | C73: per 1 lead (per 1 registration) | D73: =D$71/D17 -> 168.75 | E73: $
B74: 3. | C74: per 1 paying user - CAC | D74: =D$71/D19 -> 562.5 | E74: $

Sheet Results-Unit
D2: Unit-econimics — Results | L2: Made by | M2: https://feofinance.com/
D3: ='Input-Unit'!D9 -> StepUP
C6: 1. | D6: Number of clients and conversions
C8: № | D8: =D20 -> Name | H8: =H20 -> Value | I8: =I20 -> Unit.
C9: 1. | D9: ='Input-Unit'!C15 -> Number of visits (clicks) (UA) | H9: ='Input-Unit'!D15 -> 1000 | I9: ='Input-Unit'!E15 -> units/month | J9: =D9 -> Number of visits (clicks) (UA) | K9: =H9 -> 1000
C10: 2. | D10: ='Input-Unit'!C16 -> Conversion to Registration (C1) | H10: ='Input-Unit'!D16 -> 0.08 | I10: ='Input-Unit'!E16 -> % | J10: =D11 -> Total number of registrations (leads) | K10: =H11 -> 80
C11: 3. | D11: ='Input-Unit'!C17 -> Total number of registrations (leads) | H11: ='Input-Unit'!D17 -> 80 | I11: ='Input-Unit'!E17 -> units/month | J11: =D13 -> Total number of paying users (B) | K11: =H13 -> 24
C12: 4. | D12: ='Input-Unit'!C18 -> Conversion from registration to payment (C2) | H12: ='Input-Unit'!D18 -> 0.3 | I12: ='Input-Unit'!E18 -> %
C13: 5. | D13: ='Input-Unit'!C19 -> Total number of paying users (B) | H13: ='Input-Unit'!D19 -> 24 | I13: ='Input-Unit'!E19 -> units/month
C14: 6. | D14: ='Input-Unit'!C20 -> Final conversion from click to purchase (C3) | H14: ='Input-Unit'!D20 -> 0.024 | I14: ='Input-Unit'!E20 -> %
C15: 7. | D15: Churn rate | H15: ='Results-Unit'!H25 -> 0.037037037 | I15: %
C18: 2. | D18: The ratio of LTV to CAC
C20: № | D20: ='Input-Unit'!C36 -> Name | H20: ='Input-Unit'!D36 -> Value | I20: ='Input-Unit'!E36 -> Unit.
C21: 1. | D21: Customer Acquisition Cost (CAC) | H21: ='Input-Unit'!D74 -> 562.5 | I21: $ | J21: =D22 -> Lifetime value per customer (LTV) | K21: =H22 -> 3822.2222
C22: 2. | D22: Lifetime value per customer (LTV) | H22: ='Input-Unit'!D28 -> 3822.2222 | I22: $ | J22: =D21 -> Customer Acquisition Cost (CAC) | K22: =H21 -> 562.5
C23: 3. | D23: Difference between LTV and CAC (LTV – CAC) | H23: =H22-H21 -> 3259.7222 | I23: $ | J23: =D23 -> Difference between LTV and CAC (LTV – CAC) | K23: =H23 -> 3259.7222
C24: 4. | D24: LTV/CAC ratio | H24: =H22/H21 -> 6.7950617 | I24: k
C25: 5. | D25: Churn rate | H25: =1/'Input-Unit'!D27 -> 0.037037037 | I25: %
C29: 3. | D29: Cohort analysis | K29: =CONCATENATE("LTV / CAC = ",TEXT(H24,"# ##0.0")) -> LTV / CAC = 6.8
C31: Number of clients (new + old)
D33: Month
D34: 1 | E34: =D34+1 -> 2 | F34: =E34+1 -> 3 | G34: =F34+1 -> 4 | H34: =G34+1 -> 5 | I34: =H34+1 -> 6 | J34: =I34+1 -> 7 | K34: =J34+1 -> 8 | L34: =K34+1 -> 9 | ... O34: =N34+1 -> 12
A35: =$H$15 -> 0.037037037 | B35: Month | C35: 1 | D35: =$H$13 -> 24 | E35: =IF(D35-$D35*$H15<0,0,IF(ROUND(D35-$D35*$H15,2)=0,0,D35-$D35*$H15)) -> 23.111111 | F35: =IF(E35-$D35*$H15<0,0,IF(ROUND(E35-$D35*$H15,2)=0,0,E35-$D35*$H15)) -> 22.222222 | G35: =IF(F35-$D35*$H15<0,0,IF(ROUND(F35-$D35*$H15,2)=0,0,F35-$D35*$H15)) -> 21.333333 | H35: =IF(G35-$D35*$H15<0,0,IF(ROUND(G35-$D35*$H15,2)=0,0,G35-$D35*$H15)) -> 20.444444 | I35: =IF(H35-$D35*$H15<0,0,IF(ROUND(H35-$D35*$H15,2)=0,0,H35-$D35*$H15)) -> 19.555556 | J35: =IF(I35-$D35*$H15<0,0,IF(ROUND(I35-$D35*$H15,2)=0,0,I35-$D35*$H15)) -> 18.666667 | K35: =IF(J35-$D35*$H15<0,0,IF(ROUND(J35-$D35*$H15,2)=0,0,J35-$D35*$H15)) -> 17.777778 | L35: =IF(K35-$D35*$H15<0,0,IF(ROUND(K35-$D35*$H15,2)=0,0,K35-$D35*$H15)) -> 16.888889 | ... O35: =IF(N35-$D35*$H15<0,0,IF(ROUND(N35-$D35*$H15,2)=0,0,N35-$D35*$H15)) -> 14.222222
A36: =$H$15 -> 0.037037037 | C36: =C35+1 -> 2 | E36: =$H$13 -> 24 | F36: =IF(E36-$E36*$A36<0,0,IF(ROUND(E36-$E36*$A36,2)=0,0,E36-$E36*$A36)) -> 23.111111 | G36: =IF(F36-$E36*$A36<0,0,IF(ROUND(F36-$E36*$A36,2)=0,0,F36-$E36*$A36)) -> 22.222222 | H36: =IF(G36-$E36*$A36<0,0,IF(ROUND(G36-$E36*$A36,2)=0,0,G36-$E36*$A36)) -> 21.333333 | I36: =IF(H36-$E36*$A36<0,0,IF(ROUND(H36-$E36*$A36,2)=0,0,H36-$E36*$A36)) -> 20.444444 | J36: =IF(I36-$E36*$A36<0,0,IF(ROUND(I36-$E36*$A36,2)=0,0,I36-$E36*$A36)) -> 19.555556 | K36: =IF(J36-$E36*$A36<0,0,IF(ROUND(J36-$E36*$A36,2)=0,0,J36-$E36*$A36)) -> 18.666667 | L36: =IF(K36-$E36*$A36<0,0,IF(ROUND(K36-$E36*$A36,2)=0,0,K36-$E36*$A36)) -> 17.777778 | M36: =IF(L36-$E36*$A36<0,0,IF(ROUND(L36-$E36*$A36,2)=0,0,L36-$E36*$A36)) -> 16.888889 | ... O36: =IF(N36-$E36*$A36<0,0,IF(ROUND(N36-$E36*$A36,2)=0,0,N36-$E36*$A36)) -> 15.111111
A37: =$H$15 -> 0.037037037 | C37: =C36+1 -> 3 | F37: =$H$13 -> 24 | G37: =IF(F37-$F37*$A37<0,0,IF(ROUND(F37-$F37*$A37,2)=0,0,F37-$F37*$A37)) -> 23.111111 | H37: =IF(G37-$F37*$A37<0,0,IF(ROUND(G37-$F37*$A37,2)=0,0,G37-$F37*$A37)) -> 22.222222 | I37: =IF(H37-$F37*$A37<0,0,IF(ROUND(H37-$F37*$A37,2)=0,0,H37-$F37*$A37)) -> 21.333333 | J37: =IF(I37-$F37*$A37<0,0,IF(ROUND(I37-$F37*$A37,2)=0,0,I37-$F37*$A37)) -> 20.444444 | K37: =IF(J37-$F37*$A37<0,0,IF(ROUND(J37-$F37*$A37,2)=0,0,J37-$F37*$A37)) -> 19.555556 | L37: =IF(K37-$F37*$A37<0,0,IF(ROUND(K37-$F37*$A37,2)=0,0,K37-$F37*$A37)) -> 18.666667 | M37: =IF(L37-$F37*$A37<0,0,IF(ROUND(L37-$F37*$A37,2)=0,0,L37-$F37*$A37)) -> 17.777778 | N37: =IF(M37-$F37*$A37<0,0,IF(ROUND(M37-$F37*$A37,2)=0,0,M37-$F37*$A37)) -> 16.888889 | O37: =IF(N37-$F37*$A37<0,0,IF(ROUND(N37-$F37*$A37,2)=0,0,N37-$F37*$A37)) -> 16
A38: =$H$15 -> 0.037037037 | C38: =C37+1 -> 4 | G38: =$H$13 -> 24 | H38: =IF(G38-$G38*$A38<0,0,IF(ROUND(G38-$G38*$A38,2)=0,0,G38-$G38*$A38)) -> 23.111111 | I38: =IF(H38-$G38*$A38<0,0,IF(ROUND(H38-$G38*$A38,2)=0,0,H38-$G38*$A38)) -> 22.222222 | J38: =IF(I38-$G38*$A38<0,0,IF(ROUND(I38-$G38*$A38,2)=0,0,I38-$G38*$A38)) -> 21.333333 | K38: =IF(J38-$G38*$A38<0,0,IF(ROUND(J38-$G38*$A38,2)=0,0,J38-$G38*$A38)) -> 20.444444 | L38: =IF(K38-$G38*$A38<0,0,IF(ROUND(K38-$G38*$A38,2)=0,0,K38-$G38*$A38)) -> 19.555556 | M38: =IF(L38-$G38*$A38<0,0,IF(ROUND(L38-$G38*$A38,2)=0,0,L38-$G38*$A38)) -> 18.666667 | N38: =IF(M38-$G38*$A38<0,0,IF(ROUND(M38-$G38*$A38,2)=0,0,M38-$G38*$A38)) -> 17.777778 | O38: =IF(N38-$G38*$A38<0,0,IF(ROUND(N38-$G38*$A38,2)=0,0,N38-$G38*$A38)) -> 16.888889
A39: =$H$15 -> 0.037037037 | C39: =C38+1 -> 5 | H39: =$H$13 -> 24 | I39: =IF(H39-$H39*$A39<0,0,IF(ROUND(H39-$H39*$A39,2)=0,0,H39-$H39*$A39)) -> 23.111111 | J39: =IF(I39-$H39*$A39<0,0,IF(ROUND(I39-$H39*$A39,2)=0,0,I39-$H39*$A39)) -> 22.222222 | K39: =IF(J39-$H39*$A39<0,0,IF(ROUND(J39-$H39*$A39,2)=0,0,J39-$H39*$A39)) -> 21.333333 | L39: =IF(K39-$H39*$A39<0,0,IF(ROUND(K39-$H39*$A39,2)=0,0,K39-$H39*$A39)) -> 20.444444 | M39: =IF(L39-$H39*$A39<0,0,IF(ROUND(L39-$H39*$A39,2)=0,0,L39-$H39*$A39)) -> 19.555556 | N39: =IF(M39-$H39*$A39<0,0,IF(ROUND(M39-$H39*$A39,2)=0,0,M39-$H39*$A39)) -> 18.666667 | O39: =IF(N39-$H39*$A39<0,0,IF(ROUND(N39-$H39*$A39,2)=0,0,N39-$H39*$A39)) -> 17.777778
A40: =$H$15 -> 0.037037037 | C40: =C39+1 -> 6 | I40: =$H$13 -> 24 | J40: =IF(I40-$I40*$A40<0,0,IF(ROUND(I40-$I40*$A40,2)=0,0,I40-$I40*$A40)) -> 23.111111 | K40: =IF(J40-$I40*$A40<0,0,IF(ROUND(J40-$I40*$A40,2)=0,0,J40-$I40*$A40)) -> 22.222222 | L40: =IF(K40-$I40*$A40<0,0,IF(ROUND(K40-$I40*$A40,2)=0,0,K40-$I40*$A40)) -> 21.333333 | M40: =IF(L40-$I40*$A40<0,0,IF(ROUND(L40-$I40*$A40,2)=0,0,L40-$I40*$A40)) -> 20.444444 | N40: =IF(M40-$I40*$A40<0,0,IF(ROUND(M40-$I40*$A40,2)=0,0,M40-$I40*$A40)) -> 19.555556 | O40: =IF(N40-$I40*$A40<0,0,IF(ROUND(N40-$I40*$A40,2)=0,0,N40-$I40*$A40)) -> 18.666667
A41: =$H$15 -> 0.037037037 | C41: =C40+1 -> 7 | J41: =$H$13 -> 24 | K41: =IF(J41-$J41*$A41<0,0,IF(ROUND(J41-$J41*$A41,2)=0,0,J41-$J41*$A41)) -> 23.111111 | L41: =IF(K41-$J41*$A41<0,0,IF(ROUND(K41-$J41*$A41,2)=0,0,K41-$J41*$A41)) -> 22.222222 | M41: =IF(L41-$J41*$A41<0,0,IF(ROUND(L41-$J41*$A41,2)=0,0,L41-$J41*$A41)) -> 21.333333 | N41: =IF(M41-$J41*$A41<0,0,IF(ROUND(M41-$J41*$A41,2)=0,0,M41-$J41*$A41)) -> 20.444444 | O41: =IF(N41-$J41*$A41<0,0,IF(ROUND(N41-$J41*$A41,2)=0,0,N41-$J41*$A41)) -> 19.555556
A42: =$H$15 -> 0.037037037 | C42: =C41+1 -> 8 | K42: =$H$13 -> 24 | L42: =IF(K42-$K42*$A42<0,0,IF(ROUND(K42-$K42*$A42,2)=0,0,K42-$K42*$A42)) -> 23.111111 | M42: =IF(L42-$K42*$A42<0,0,IF(ROUND(L42-$K42*$A42,2)=0,0,L42-$K42*$A42)) -> 22.222222 | N42: =IF(M42-$K42*$A42<0,0,IF(ROUND(M42-$K42*$A42,2)=0,0,M42-$K42*$A42)) -> 21.333333 | O42: =IF(N42-$K42*$A42<0,0,IF(ROUND(N42-$K42*$A42,2)=0,0,N42-$K42*$A42)) -> 20.444444
A43: =$H$15 -> 0.037037037 | C43: =C42+1 -> 9 | L43: =$H$13 -> 24 | M43: =IF(L43-$L43*$A43<0,0,IF(ROUND(L43-$L43*$A43,2)=0,0,L43-$L43*$A43)) -> 23.111111 | N43: =IF(M43-$L43*$A43<0,0,IF(ROUND(M43-$L43*$A43,2)=0,0,M43-$L43*$A43)) -> 22.222222 | O43: =IF(N43-$L43*$A43<0,0,IF(ROUND(N43-$L43*$A43,2)=0,0,N43-$L43*$A43)) -> 21.333333
A44: =$H$15 -> 0.037037037 | C44: =C43+1 -> 10 | M44: =$H$13 -> 24 | N44: =IF(M44-$M44*$A44<0,0,IF(ROUND(M44-$M44*$A44,2)=0,0,M44-$M44*$A44)) -> 23.111111 | O44: =IF(N44-$M44*$A44<0,0,IF(ROUND(N44-$M44*$A44,2)=0,0,N44-$M44*$A44)) -> 22.222222
A45: =$H$15 -> 0.037037037 | C45: =C44+1 -> 11 | N45: =$H$13 -> 24 | O45: =IF(N45-$N45*$A45<0,0,IF(ROUND(N45-$N45*$A45,2)=0,0,N45-$N45*$A45)) -> 23.111111
A46: =$H$15 -> 0.037037037 | C46: =C45+1 -> 12 | O46: =$H$13 -> 24
C47: Total | D47: =SUM(D35:D46) -> 24 | E47: =SUM(E35:E46) -> 47.111111 | F47: =SUM(F35:F46) -> 69.333333 | G47: =SUM(G35:G46) -> 90.666667 | H47: =SUM(H35:H46) -> 111.11111 | I47: =SUM(I35:I46) -> 130.66667 | J47: =SUM(J35:J46) -> 149.33333 | K47: =SUM(K35:K46) -> 167.11111 | ... O47: =SUM(O35:O46) -> 229.33333
C48: New | D48: =$H$13 -> 24 | E48: =$H$13 -> 24 | F48: =$H$13 -> 24 | G48: =$H$13 -> 24 | H48: =$H$13 -> 24 | I48: =$H$13 -> 24 | J48: =$H$13 -> 24 | K48: =$H$13 -> 24 | ... O48: =$H$13 -> 24
C49: Churn | D49: =-(-D50) -> 0 | E49: =-(D47-E50) -> -0.88888889 | F49: =-(E47-F50) -> -1.7777778 | G49: =-(F47-G50) -> -2.6666667 | H49: =-(G47-H50) -> -3.5555556 | I49: =-(H47-I50) -> -4.4444444 | J49: =-(I47-J50) -> -5.3333333 | K49: =-(J47-K50) -> -6.2222222 | L49: =-(K47-L50) -> -7.1111111 | ... O49: =-(N47-O50) -> -9.7777778
C50: Old | D50: =D47-D48 -> 0 | E50: =E47-E48 -> 23.111111 | F50: =F47-F48 -> 45.333333 | G50: =G47-G48 -> 66.666667 | H50: =H47-H48 -> 87.111111 | I50: =I47-I48 -> 106.66667 | J50: =J47-J48 -> 125.33333 | K50: =K47-K48 -> 143.11111 | ... O50: =O47-O48 -> 205.33333
C54: 4. | D54: Cash flow by month
C56: Name | G56: 1 | H56: =G56+1 -> 2 | I56: =H56+1 -> 3 | J56: =I56+1 -> 4 | K56: =J56+1 -> 5 | L56: =K56+1 -> 6 | M56: =L56+1 -> 7 | N56: =M56+1 -> 8 | O56: =N56+1 -> 9 | ... R56: =Q56+1 -> 12
C57: Revenue | G57: =G58*G60 -> 9600 | H57: =H58*H60 -> 18844.444 | I57: =I58*I60 -> 27733.333 | J57: =J58*J60 -> 36266.667 | K57: =K58*K60 -> 44444.444 | L57: =L58*L60 -> 52266.667 | M57: =M58*M60 -> 59733.333 | N57: =N58*N60 -> 66844.444 | ... R57: =R58*R60 -> 91733.333
C58: =D13 -> Total number of paying users (B) | G58: =D47 -> 24 | H58: =E47 -> 47.111111 | I58: =F47 -> 69.333333 | J58: =G47 -> 90.666667 | K58: =H47 -> 111.11111 | L58: =I47 -> 130.66667 | M58: =J47 -> 149.33333 | N58: =K47 -> 167.11111 | ... R58: =O47 -> 229.33333
G59: х | H59: х | I59: х | J59: х | K59: х | L59: х | M59: х | N59: х | O59: х | P59: х | Q59: х | R59: х
C60: ='Input-Unit'!C26 -> Average revenue per paying customer (ARPPU) | G60: ='Input-Unit'!$D$26 -> 400 | H60: ='Input-Unit'!$D$26 -> 400 | I60: ='Input-Unit'!$D$26 -> 400 | J60: ='Input-Unit'!$D$26 -> 400 | K60: ='Input-Unit'!$D$26 -> 400 | L60: ='Input-Unit'!$D$26 -> 400 | M60: ='Input-Unit'!$D$26 -> 400 | N60: ='Input-Unit'!$D$26 -> 400 | ... R60: ='Input-Unit'!$D$26 -> 400
C61: Cost of attracting customers | G61: =G62+G66+G77 -> -13000 | H61: =H62+H66+H77 -> -13000 | I61: =I62+I66+I77 -> -13000 | J61: =J62+J66+J77 -> -13000 | K61: =K62+K66+K77 -> -13000 | L61: =L62+L66+L77 -> -13000 | M61: =M62+M66+M77 -> -13000 | N61: =N62+N66+N77 -> -13000 | ... R61: =R62+R66+R77 -> -13000
C62: Advertising and marketing expenses | G62: =-G63*G65 -> -5000 | H62: =-H63*H65 -> -5000 | I62: =-I63*I65 -> -5000 | J62: =-J63*J65 -> -5000 | K62: =-K63*K65 -> -5000 | L62: =-L63*L65 -> -5000 | M62: =-M63*M65 -> -5000 | N62: =-N63*N65 -> -5000 | ... R62: =-R63*R65 -> -5000
C63: ='Input-Unit'!C38 -> Number of visits (clicks) | G63: =$H$9 -> 1000 | H63: =$H$9 -> 1000 | I63: =$H$9 -> 1000 | J63: =$H$9 -> 1000 | K63: =$H$9 -> 1000 | L63: =$H$9 -> 1000 | M63: =$H$9 -> 1000 | N63: =$H$9 -> 1000 | ... R63: =$H$9 -> 1000
G64: х | H64: х | I64: х | J64: х | K64: х | L64: х | M64: х | N64: х | O64: х | P64: х | Q64: х | R64: х
C65: ='Input-Unit'!C37 -> Cost of 1 visit (click) | G65: ='Input-Unit'!$D$37 -> 5 | H65: ='Input-Unit'!$D$37 -> 5 | I65: ='Input-Unit'!$D$37 -> 5 | J65: ='Input-Unit'!$D$37 -> 5 | K65: ='Input-Unit'!$D$37 -> 5 | L65: ='Input-Unit'!$D$37 -> 5 | M65: ='Input-Unit'!$D$37 -> 5 | N65: ='Input-Unit'!$D$37 -> 5 | ... R65: ='Input-Unit'!$D$37 -> 5
C66: Salary | G66: =SUM(G67:G76) -> -8000 | H66: =SUM(H67:H76) -> -8000 | I66: =SUM(I67:I76) -> -8000 | J66: =SUM(J67:J76) -> -8000 | K66: =SUM(K67:K76) -> -8000 | L66: =SUM(L67:L76) -> -8000 | M66: =SUM(M67:M76) -> -8000 | N66: =SUM(N67:N76) -> -8000 | ... R66: =SUM(R67:R76) -> -8000
C67: ='Input-Unit'!C45 -> Sales Development Representative | G67: =-'Input-Unit'!$F45 -> -2000 | H67: =-'Input-Unit'!$F45 -> -2000 | I67: =-'Input-Unit'!$F45 -> -2000 | J67: =-'Input-Unit'!$F45 -> -2000 | K67: =-'Input-Unit'!$F45 -> -2000 | L67: =-'Input-Unit'!$F45 -> -2000 | M67: =-'Input-Unit'!$F45 -> -2000 | N67: =-'Input-Unit'!$F45 -> -2000 | ... R67: =-'Input-Unit'!$F45 -> -2000
C68: ='Input-Unit'!C46 -> Product Manager | G68: =-'Input-Unit'!$D46 -> -3000 | H68: =-'Input-Unit'!$D46 -> -3000 | I68: =-'Input-Unit'!$D46 -> -3000 | J68: =-'Input-Unit'!$D46 -> -3000 | K68: =-'Input-Unit'!$D46 -> -3000 | L68: =-'Input-Unit'!$D46 -> -3000 | M68: =-'Input-Unit'!$D46 -> -3000 | N68: =-'Input-Unit'!$D46 -> -3000 | ... R68: =-'Input-Unit'!$D46 -> -3000
C69: ='Input-Unit'!C47 -> Founder | G69: =-'Input-Unit'!$D47 -> -3000 | H69: =-'Input-Unit'!$D47 -> -3000 | I69: =-'Input-Unit'!$D47 -> -3000 | J69: =-'Input-Unit'!$D47 -> -3000 | K69: =-'Input-Unit'!$D47 -> -3000 | L69: =-'Input-Unit'!$D47 -> -3000 | M69: =-'Input-Unit'!$D47 -> -3000 | N69: =-'Input-Unit'!$D47 -> -3000 | ... R69: =-'Input-Unit'!$D47 -> -3000
C70: ='Input-Unit'!C48 | G70: =-'Input-Unit'!$D48 -> 0 | H70: =-'Input-Unit'!$D48 -> 0 | I70: =-'Input-Unit'!$D48 -> 0 | J70: =-'Input-Unit'!$D48 -> 0 | K70: =-'Input-Unit'!$D48 -> 0 | L70: =-'Input-Unit'!$D48 -> 0 | M70: =-'Input-Unit'!$D48 -> 0 | N70: =-'Input-Unit'!$D48 -> 0 | ... R70: =-'Input-Unit'!$D48 -> 0
C71: ='Input-Unit'!C49 | G71: =-'Input-Unit'!$D49 -> 0 | H71: =-'Input-Unit'!$D49 -> 0 | I71: =-'Input-Unit'!$D49 -> 0 | J71: =-'Input-Unit'!$D49 -> 0 | K71: =-'Input-Unit'!$D49 -> 0 | L71: =-'Input-Unit'!$D49 -> 0 | M71: =-'Input-Unit'!$D49 -> 0 | N71: =-'Input-Unit'!$D49 -> 0 | ... R71: =-'Input-Unit'!$D49 -> 0
C72: ='Input-Unit'!C50 | G72: =-'Input-Unit'!$D50 -> 0 | H72: =-'Input-Unit'!$D50 -> 0 | I72: =-'Input-Unit'!$D50 -> 0 | J72: =-'Input-Unit'!$D50 -> 0 | K72: =-'Input-Unit'!$D50 -> 0 | L72: =-'Input-Unit'!$D50 -> 0 | M72: =-'Input-Unit'!$D50 -> 0 | N72: =-'Input-Unit'!$D50 -> 0 | ... R72: =-'Input-Unit'!$D50 -> 0
C73: ='Input-Unit'!C51 | G73: =-'Input-Unit'!$D51 -> 0 | H73: =-'Input-Unit'!$D51 -> 0 | I73: =-'Input-Unit'!$D51 -> 0 | J73: =-'Input-Unit'!$D51 -> 0 | K73: =-'Input-Unit'!$D51 -> 0 | L73: =-'Input-Unit'!$D51 -> 0 | M73: =-'Input-Unit'!$D51 -> 0 | N73: =-'Input-Unit'!$D51 -> 0 | ... R73: =-'Input-Unit'!$D51 -> 0
C74: ='Input-Unit'!C52 | G74: =-'Input-Unit'!$D52 -> 0 | H74: =-'Input-Unit'!$D52 -> 0 | I74: =-'Input-Unit'!$D52 -> 0 | J74: =-'Input-Unit'!$D52 -> 0 | K74: =-'Input-Unit'!$D52 -> 0 | L74: =-'Input-Unit'!$D52 -> 0 | M74: =-'Input-Unit'!$D52 -> 0 | N74: =-'Input-Unit'!$D52 -> 0 | ... R74: =-'Input-Unit'!$D52 -> 0
C75: ='Input-Unit'!C53 | G75: =-'Input-Unit'!$D53 -> 0 | H75: =-'Input-Unit'!$D53 -> 0 | I75: =-'Input-Unit'!$D53 -> 0 | J75: =-'Input-Unit'!$D53 -> 0 | K75: =-'Input-Unit'!$D53 -> 0 | L75: =-'Input-Unit'!$D53 -> 0 | M75: =-'Input-Unit'!$D53 -> 0 | N75: =-'Input-Unit'!$D53 -> 0 | ... R75: =-'Input-Unit'!$D53 -> 0
C76: ='Input-Unit'!C54 | G76: =-'Input-Unit'!$D54 -> 0 | H76: =-'Input-Unit'!$D54 -> 0 | I76: =-'Input-Unit'!$D54 -> 0 | J76: =-'Input-Unit'!$D54 -> 0 | K76: =-'Input-Unit'!$D54 -> 0 | L76: =-'Input-Unit'!$D54 -> 0 | M76: =-'Input-Unit'!$D54 -> 0 | N76: =-'Input-Unit'!$D54 -> 0 | ... R76: =-'Input-Unit'!$D54 -> 0
C77: Other marketing and advertising expenses | G77: =SUM(G78:G82) -> 0 | H77: =SUM(H78:H82) -> 0 | I77: =SUM(I78:I82) -> 0 | J77: =SUM(J78:J82) -> 0 | K77: =SUM(K78:K82) -> 0 | L77: =SUM(L78:L82) -> 0 | M77: =SUM(M78:M82) -> 0 | N77: =SUM(N78:N82) -> 0 | ... R77: =SUM(R78:R82) -> 0
C78: ='Input-Unit'!C61 | G78: =-'Input-Unit'!$D61 -> 0 | H78: =-'Input-Unit'!$D61 -> 0 | I78: =-'Input-Unit'!$D61 -> 0 | J78: =-'Input-Unit'!$D61 -> 0 | K78: =-'Input-Unit'!$D61 -> 0 | L78: =-'Input-Unit'!$D61 -> 0 | M78: =-'Input-Unit'!$D61 -> 0 | N78: =-'Input-Unit'!$D61 -> 0 | ... R78: =-'Input-Unit'!$D61 -> 0
C79: ='Input-Unit'!C62 | G79: =-'Input-Unit'!$D62 -> 0 | H79: =-'Input-Unit'!$D62 -> 0 | I79: =-'Input-Unit'!$D62 -> 0 | J79: =-'Input-Unit'!$D62 -> 0 | K79: =-'Input-Unit'!$D62 -> 0 | L79: =-'Input-Unit'!$D62 -> 0 | M79: =-'Input-Unit'!$D62 -> 0 | N79: =-'Input-Unit'!$D62 -> 0 | ... R79: =-'Input-Unit'!$D62 -> 0
C80: ='Input-Unit'!C63 | G80: =-'Input-Unit'!$D63 -> 0 | H80: =-'Input-Unit'!$D63 -> 0 | I80: =-'Input-Unit'!$D63 -> 0 | J80: =-'Input-Unit'!$D63 -> 0 | K80: =-'Input-Unit'!$D63 -> 0 | L80: =-'Input-Unit'!$D63 -> 0 | M80: =-'Input-Unit'!$D63 -> 0 | N80: =-'Input-Unit'!$D63 -> 0 | ... R80: =-'Input-Unit'!$D63 -> 0
C81: ='Input-Unit'!C64 | G81: =-'Input-Unit'!$D64 -> 0 | H81: =-'Input-Unit'!$D64 -> 0 | I81: =-'Input-Unit'!$D64 -> 0 | J81: =-'Input-Unit'!$D64 -> 0 | K81: =-'Input-Unit'!$D64 -> 0 | L81: =-'Input-Unit'!$D64 -> 0 | M81: =-'Input-Unit'!$D64 -> 0 | N81: =-'Input-Unit'!$D64 -> 0 | ... R81: =-'Input-Unit'!$D64 -> 0
C82: ='Input-Unit'!C65 | G82: =-'Input-Unit'!$D65 -> 0 | H82: =-'Input-Unit'!$D65 -> 0 | I82: =-'Input-Unit'!$D65 -> 0 | J82: =-'Input-Unit'!$D65 -> 0 | K82: =-'Input-Unit'!$D65 -> 0 | L82: =-'Input-Unit'!$D65 -> 0 | M82: =-'Input-Unit'!$D65 -> 0 | N82: =-'Input-Unit'!$D65 -> 0 | ... R82: =-'Input-Unit'!$D65 -> 0
C83: Gross profit * | G83: =G57+G61 -> -3400 | H83: =H57+H61 -> 5844.4444 | I83: =I57+I61 -> 14733.333 | J83: =J57+J61 -> 23266.667 | K83: =K57+K61 -> 31444.444 | L83: =L57+L61 -> 39266.667 | M83: =M57+M61 -> 46733.333 | N83: =N57+N61 -> 53844.444 | ... R83: =R57+R61 -> 78733.333
C85: *Gross profit includes direct marketing and advertising costs only
C122: Data for graphs
D124: =D34 -> 1 | E124: =E34 -> 2 | F124: =F34 -> 3 | G124: =G34 -> 4 | H124: =H34 -> 5 | I124: =I34 -> 6 | J124: =J34 -> 7 | K124: =K34 -> 8 | ... O124: =O34 -> 12
C125: =C47 -> Total | D125: =D47 -> 24 | E125: =E47 -> 47.111111 | F125: =F47 -> 69.333333 | G125: =G47 -> 90.666667 | H125: =H47 -> 111.11111 | I125: =I47 -> 130.66667 | J125: =J47 -> 149.33333 | ... O125: =O47 -> 229.33333
C126: =C48 -> New | D126: =D48 -> 24 | E126: =E48 -> 24 | F126: =F48 -> 24 | G126: =G48 -> 24 | H126: =H48 -> 24 | I126: =I48 -> 24 | J126: =J48 -> 24 | ... O126: =O48 -> 24
C127: =C50 -> Old | D127: =D50 -> 0 | E127: =E50 -> 23.111111 | F127: =F50 -> 45.333333 | G127: =G50 -> 66.666667 | H127: =H50 -> 87.111111 | I127: =I50 -> 106.66667 | J127: =J50 -> 125.33333 | ... O127: =O50 -> 205.33333
D132: =D124 -> 1 | E132: =E124 -> 2 | F132: =F124 -> 3 | G132: =G124 -> 4 | H132: =H124 -> 5 | I132: =I124 -> 6 | J132: =J124 -> 7 | K132: =K124 -> 8 | ... O132: =O124 -> 12
C133: =C57 -> Revenue | D133: =G57 -> 9600 | E133: =H57 -> 18844.444 | F133: =I57 -> 27733.333 | G133: =J57 -> 36266.667 | H133: =K57 -> 44444.444 | I133: =L57 -> 52266.667 | J133: =M57 -> 59733.333 | K133: =N57 -> 66844.444 | ... O133: =R57 -> 91733.333
C134: =C61 -> Cost of attracting customers | D134: =-G61 -> 13000 | E134: =-H61 -> 13000 | F134: =-I61 -> 13000 | G134: =-J61 -> 13000 | H134: =-K61 -> 13000 | I134: =-L61 -> 13000 | J134: =-M61 -> 13000 | K134: =-N61 -> 13000 | ... O134: =-R61 -> 13000
C135: =C83 -> Gross profit * | D135: =G83 -> -3400 | E135: =H83 -> 5844.4444 | F135: =I83 -> 14733.333 | G135: =J83 -> 23266.667 | H135: =K83 -> 31444.444 | I135: =L83 -> 39266.667 | J135: =M83 -> 46733.333 | K135: =N83 -> 53844.444 | ... O135: =R83 -> 78733.333

Sheet Input
A1: =BS!A1 -> Ok
C3: Financial Model — Input | G3: Made by | H3: https://feofinance.com/
C4: ='Input-Unit'!D9 -> StepUP
C6: v 1.0
C10: Input Parameters | D10: Go to Results
B12: I | C12: Settings
B14: 1. | C14: Cells that can be changed | D14: ххх
B15: 2. | C15: Cells that can't be changed (they contain a formula) | D15: =D14 -> ххх
B18: № | C18: Name | D18: Date
B19: 1. | C19: Model start date | D19: 46023
B20: 2. | C20: Model validity period, years | D20: =(D21-D19)/365.25 -> 6.9979466
B21: 3. | C21: Model end date | D21: =EOMONTH(CF!CN1,0) -> 48579
B25: II | C25: Capital Expenditures
B27: № | C27: Name | D27: Depreciation period, year | E27: Total, $ | F27: =CF!I1 -> 46023 | G27: =CF!J1 -> 46054 | H27: =CF!K1 -> 46082 | I27: =CF!L1 -> 46113 | J27: =CF!M1 -> 46143 | K27: =CF!N1 -> 46174 | L27: =CF!O1 -> 46204 | M27: =CF!P1 -> 46235 | ... CK27: =CF!CN1 -> 48549
B28: 1. | C28: Platform development | D28: 5 | E28: =SUM(F28:CK28) -> 20000 | F28: 5000 | G28: 5000 | H28: 5000 | I28: 5000 | J28: 0 | K28: 0 | L28: 0 | M28: 0 | N28: 0 | O28: 0 | P28: 0 | Q28: 0 | R28: 0 | S28: 0 | T28: 0 | U28: 0 | V28: 0 | W28: 0 | X28: 0 | Y28: 0 | Z28: 0 | AA28: 0 | AB28: 0 | AC28: 0 | AD28: 0 | AE28: 0 | AF28: 0 | AG28: 0 | AH28: 0 | AI28: 0 | AJ28: 0 | AK28: 0 | AL28: 0 | AM28: 0 | AN28: 0 | AO28: 0 | AP28: 0 | AQ28: 0 | AR28: 0 | AS28: 0 | AT28: 0 | AU28: 0 | AV28: 0 | AW28: 0 | AX28: 0 | AY28: 0 | AZ28: 0 | BA28: 0 | BB28: 0 | BC28: 0 | BD28: 0 | BE28: 0 | BF28: 0 | BG28: 0 | BH28: 0 | BI28: 0 | BJ28: 0 | BK28: 0 | BL28: 0 | BM28: 0 | BN28: 0 | BO28: 0 | BP28: 0 | BQ28: 0 | BR28: 0 | BS28: 0 | BT28: 0 | BU28: 0 | BV28: 0 | BW28: 0 | BX28: 0 | BY28: 0 | BZ28: 0 | CA28: 0 | CB28: 0 | CC28: 0 | CD28: 0 | CE28: 0 | CF28: 0 | CG28: 0 | CH28: 0 | CI28: 0 | CJ28: 0 | CK28: 0
B29: 2. | C29: Infrastructure setup | D29: 5 | E29: =SUM(F29:CK29) -> 4400 | H29: 0 | I29: 0 | J29: 4400 | K29: 0 | L29: 0 | M29: 0 | N29: 0 | O29: 0 | P29: 0 | Q29: 0 | R29: 0 | S29: 0 | T29: 0 | U29: 0 | V29: 0 | W29: 0 | X29: 0 | Y29: 0 | Z29: 0 | AA29: 0 | AB29: 0 | AC29: 0 | AD29: 0 | AE29: 0 | AF29: 0 | AG29: 0 | AH29: 0 | AI29: 0 | AJ29: 0 | AK29: 0 | AL29: 0 | AM29: 0 | AN29: 0 | AO29: 0 | AP29: 0 | AQ29: 0 | AR29: 0 | AS29: 0 | AT29: 0 | AU29: 0 | AV29: 0 | AW29: 0 | AX29: 0 | AY29: 0 | AZ29: 0 | BA29: 0 | BB29: 0 | BC29: 0 | BD29: 0 | BE29: 0 | BF29: 0 | BG29: 0 | BH29: 0 | BI29: 0 | BJ29: 0 | BK29: 0 | BL29: 0 | BM29: 0 | BN29: 0 | BO29: 0 | BP29: 0 | BQ29: 0 | BR29: 0 | BS29: 0 | BT29: 0 | BU29: 0 | BV29: 0 | BW29: 0 | BX29: 0 | BY29: 0 | BZ29: 0 | CA29: 0 | CB29: 0 | CC29: 0 | CD29: 0 | CE29: 0 | CF29: 0 | CG29: 0 | CH29: 0 | CI29: 0 | CJ29: 0 | CK29: 0
B30: 3. | D30: 5 | H30: 0 | I30: 0 | J30: 0 | K30: 0 | L30: 0 | M30: 0 | N30: 0 | O30: 0 | P30: 0 | Q30: 0 | R30: 0 | S30: 0 | T30: 0 | U30: 0 | V30: 0 | W30: 0 | X30: 0 | Y30: 0 | Z30: 0 | AA30: 0 | AB30: 0 | AC30: 0 | AD30: 0 | AE30: 0 | AF30: 0 | AG30: 0 | AH30: 0 | AI30: 0 | AJ30: 0 | AK30: 0 | AL30: 0 | AM30: 0 | AN30: 0 | AO30: 0 | AP30: 0 | AQ30: 0 | AR30: 0 | AS30: 0 | AT30: 0 | AU30: 0 | AV30: 0 | AW30: 0 | AX30: 0 | AY30: 0 | AZ30: 0 | BA30: 0 | BB30: 0 | BC30: 0 | BD30: 0 | BE30: 0 | BF30: 0 | BG30: 0 | BH30: 0 | BI30: 0 | BJ30: 0 | BK30: 0 | BL30: 0 | BM30: 0 | BN30: 0 | BO30: 0 | BP30: 0 | BQ30: 0 | BR30: 0 | BS30: 0 | BT30: 0 | BU30: 0 | BV30: 0 | BW30: 0 | BX30: 0 | BY30: 0 | BZ30: 0 | CA30: 0 | CB30: 0 | CC30: 0 | CD30: 0 | CE30: 0 | CF30: 0 | CG30: 0 | CH30: 0 | CI30: 0 | CJ30: 0 | CK30: 0
B31: 4. | D31: 5 | H31: 0 | I31: 0 | J31: 0 | K31: 0 | L31: 0 | M31: 0 | N31: 0 | O31: 0 | P31: 0 | Q31: 0 | R31: 0 | S31: 0 | T31: 0 | U31: 0 | V31: 0 | W31: 0 | X31: 0 | Y31: 0 | Z31: 0 | AA31: 0 | AB31: 0 | AC31: 0 | AD31: 0 | AE31: 0 | AF31: 0 | AG31: 0 | AH31: 0 | AI31: 0 | AJ31: 0 | AK31: 0 | AL31: 0 | AM31: 0 | AN31: 0 | AO31: 0 | AP31: 0 | AQ31: 0 | AR31: 0 | AS31: 0 | AT31: 0 | AU31: 0 | AV31: 0 | AW31: 0 | AX31: 0 | AY31: 0 | AZ31: 0 | BA31: 0 | BB31: 0 | BC31: 0 | BD31: 0 | BE31: 0 | BF31: 0 | BG31: 0 | BH31: 0 | BI31: 0 | BJ31: 0 | BK31: 0 | BL31: 0 | BM31: 0 | BN31: 0 | BO31: 0 | BP31: 0 | BQ31: 0 | BR31: 0 | BS31: 0 | BT31: 0 | BU31: 0 | BV31: 0 | BW31: 0 | BX31: 0 | BY31: 0 | BZ31: 0 | CA31: 0 | CB31: 0 | CC31: 0 | CD31: 0 | CE31: 0 | CF31: 0 | CG31: 0 | CH31: 0 | CI31: 0 | CJ31: 0 | CK31: 0
B32: 5. | D32: 5 | E32: =SUM(F32:CK32) -> 0 | F32: 0 | G32: 0 | H32: 0 | I32: 0 | J32: 0 | K32: 0 | L32: 0 | M32: 0 | N32: 0 | O32: 0 | P32: 0 | Q32: 0 | R32: 0 | S32: 0 | T32: 0 | U32: 0 | V32: 0 | W32: 0 | X32: 0 | Y32: 0 | Z32: 0 | AA32: 0 | AB32: 0 | AC32: 0 | AD32: 0 | AE32: 0 | AF32: 0 | AG32: 0 | AH32: 0 | AI32: 0 | AJ32: 0 | AK32: 0 | AL32: 0 | AM32: 0 | AN32: 0 | AO32: 0 | AP32: 0 | AQ32: 0 | AR32: 0 | AS32: 0 | AT32: 0 | AU32: 0 | AV32: 0 | AW32: 0 | AX32: 0 | AY32: 0 | AZ32: 0 | BA32: 0 | BB32: 0 | BC32: 0 | BD32: 0 | BE32: 0 | BF32: 0 | BG32: 0 | BH32: 0 | BI32: 0 | BJ32: 0 | BK32: 0 | BL32: 0 | BM32: 0 | BN32: 0 | BO32: 0 | BP32: 0 | BQ32: 0 | BR32: 0 | BS32: 0 | BT32: 0 | BU32: 0 | BV32: 0 | BW32: 0 | BX32: 0 | BY32: 0 | BZ32: 0 | CA32: 0 | CB32: 0 | CC32: 0 | CD32: 0 | CE32: 0 | CF32: 0 | CG32: 0 | CH32: 0 | CI32: 0 | CJ32: 0 | CK32: 0
C33: Total | E33: =SUM(E28:E32) -> 24400 | F33: =SUM(F28:F32) -> 5000 | G33: =SUM(G28:G32) -> 5000 | H33: =SUM(H28:H32) -> 5000 | I33: =SUM(I28:I32) -> 5000 | J33: =SUM(J28:J32) -> 4400 | K33: =SUM(K28:K32) -> 0 | L33: =SUM(L28:L32) -> 0 | ... CK33: =SUM(CK28:CK32) -> 0
B37: III | C37: Sales volume and direct costs
B39: 1. | C39: Main settings | D39: See sheet "Input-Unit"
B40: 2. | C40: Sales start date | D40: 45413 | F40: =round((D40-D19)/30.5,0) -> -20
B43: IV | C43: Other Expenses
B45: 1 | C45: Salary (without marketing and sales)
B47: № | C47: Job title | D47: Salary, Gross, $ per year | E47: Salary, Gross, $ per month | F47: Employment date | G47: Date of dismissal
B48: 1. | C48: CEO | D48: 36000 | E48: =D48/12 -> 3000 | F48: 45292 | G48: =$D$21 -> 48579
B49: 2. | C49: CPO | D49: 36000 | E49: =D49/12 -> 3000 | F49: 45292 | G49: =$D$21 -> 48579
B50: 3. | C50: DevOps | D50: 13200 | E50: =D50/12 -> 1100 | F50: 46174 | G50: =$D$21 -> 48579
B51: 4. | C51: Senior Fullstack Engineer | D51: 42000 | E51: =D51/12 -> 3500 | F51: 45323 | G51: 31/12/2024
B52: 5.
B53: 6.
B54: 7.
B55: 8.
B56: 9.
B57: 10.
C58: Total | D58: =SUM(D48:D57) -> 127200 | E58: =SUM(E48:E57) -> 10600
B61: 2 | C61: Fixed Expenses
B63: № | C63: Name | D63: Value, $ per month | E63: Start date | F63: Expiration date
B64: 1. | C64: Servers | D64: 1200 | E64: 45294 | F64: =$D$21 -> 48579
B65: 2. | C65: App analytics service | D65: 150 | E65: 45292 | F65: =$D$21 -> 48579
B66: 3. | E66: 45352 | F66: =$D$21 -> 48579
B67: 4. | E67: 45352 | F67: =$D$21 -> 48579
B68: 5. | E68: 45352 | F68: =$D$21 -> 48579
B69: 6. | E69: 45352 | F69: =$D$21 -> 48579
B70: 7. | E70: 45352 | F70: =$D$21 -> 48579
B71: 8. | E71: 45352 | F71: =$D$21 -> 48579
B72: 9. | E72: 45352 | F72: =$D$21 -> 48579
B73: 10. | E73: 45352 | F73: =$D$21 -> 48579
C74: Total | D74: =SUM(D64:D73) -> 1350
B77: 3 | C77: Other Variable Expenses
B79: № | C79: Name | D79: Value | E79: Accrual base
B80: 1. | C80: Stores Commission | D80: 0 | E80: % of revenue | G80: =VLOOKUP(E80,$H$80:$I$81,2,FALSE) -> 1 | H80: % of revenue | I80: 1
B81: 2. | C81: Bank's fee | D81: 0.01 | E81: % of revenue | G81: =VLOOKUP(E81,$H$80:$I$81,2,FALSE) -> 1 | H81: $ / 1 paying user | I81: 2
B82: 3. | C82: Other commissions | D82: 0.005 | E82: % of revenue | G82: =VLOOKUP(E82,$H$80:$I$81,2,FALSE) -> 1
B83: 4. | C83: ChatGPT | D83: =1500*0.005 -> 7.5 | E83: $ / 1 paying user | G83: =VLOOKUP(E83,$H$80:$I$81,2,FALSE) -> 2
B84: 5. | C84: Free user service | D84: =50*0.005 -> 0.25 | E84: $ / 1 paying user | G84: =VLOOKUP(E84,$H$80:$I$81,2,FALSE) -> 2
B85: 6. | E85: $ / 1 paying user | G85: =VLOOKUP(E85,$H$80:$I$81,2,FALSE) -> 2
B86: 7. | D86: 0 | E86: $ / 1 paying user | G86: =VLOOKUP(E86,$H$80:$I$81,2,FALSE) -> 2
B89: V | C89: Financing
B91: № | C91: Index | D91: Investor's funds | E91: Founders' funds
B92: 1. | C92: Funding share | D92: 0.4 | E92: =1-D92 -> 0.6
B93: 2. | C93: Share in the authorized capital | D93: 0.2 | E93: =1-D93 -> 0.8
B95: 3. | C95: Investment volume, incl: | D95: =Results!D6 -> 162300 | E95: $ | L95: 1 | M95: DSCR (from cash flow) | P95: 1 | Q95: technique in formula
B96: 3.1. | C96: =Results!D30 -> Founders' funds | D96: =Results!G30 -> 97380 | E96: $
B97: 3.2. | C97: =Results!D31 -> Investor's funds | D97: =Results!G31 -> 64920 | E97: $
B98: 4. | C98: Share in the authorized capital | D98: =D93 -> 0.2 | E98: %
B99: 5. | C99: Company valuation | D99: =D97/D98 -> 324600 | E99: $ | L99: 1 | M99: DSCR (from cash flow) | P99: 1 | Q99: technique in formula
B100: 6. | C100: =Results!D10 -> Investor's profit | D100: =Results!D9 -> 1868791 | E100: $ | L100: 1 | M100: DSCR (from cash flow) | P100: 1 | Q100: technique in formula
B101: 7. | C101: =Results!F10 -> IRR (investor) | D101: =Results!F9 -> 1.17074 | E101: %
B102: 8. | C102: =Results!I10 -> Investor's capital gain | D102: =Results!I9 -> 28.78606 | E102: x
B103: 9. | C103: =Results!L10 -> Payback period (investor) | D103: =if(Results!G234<1,TEXT(round(Results!G234*12,0),"0"),TEXT(Results!G234,"0.0")) -> 2.0 | E103: =if(Results!G234<1,"months","years") -> years
B105: 10. | C105: Dividend payment share | D105: 0.7 | E105: of retained earnings | L105: 1 | M105: DSCR (from cash flow) | P105: 1 | Q105: technique in formula
B109: VI | C109: Macro Indicators
B111: 1. | C111: Taxes
B113: № | C113: Name | D113: Value, %
B114: 1. | C114: Income tax | D114: 0.09
B115: 2. | C115: VAT | D115: 0.05
B116: 3. | C116: Additional taxes and insurance contributions for employees | D116: 0
B119: 2. | C119: Indexing
B121: № | C121: Name | D121: =YEAR(D19) -> 2026 | E121: =D121+1 -> 2027 | F121: =E121+1 -> 2028 | G121: =F121+1 -> 2029 | H121: =G121+1 -> 2030 | I121: =H121+1 -> 2031 | J121: =I121+1 -> 2032 | L121: =D121 -> 2026 | M121: =E121 -> 2027 | N121: =F121 -> 2028 | O121: =G121 -> 2029 | P121: =H121 -> 2030 | Q121: =I121 -> 2031 | R121: =J121 -> 2032
B122: 1. | C122: Indexation of production prices | D122: 0 | E122: 0.05 | F122: 0.05 | G122: 0.05 | H122: 0.05 | I122: 0.05 | J122: 0.05 | L122: =1+D122 -> 1 | M122: =L122*(1+E122) -> 1.05 | N122: =M122*(1+F122) -> 1.1025 | O122: =N122*(1+G122) -> 1.157625 | P122: =O122*(1+H122) -> 1.2155063 | Q122: =P122*(1+I122) -> 1.2762816 | R122: =Q122*(1+J122) -> 1.3400956
B123: 2. | C123: Payroll indexation | D123: 0 | E123: 0.05 | F123: 0.05 | G123: 0.05 | H123: 0.05 | I123: 0.05 | J123: 0.05 | L123: =1+D123 -> 1 | M123: =L123*(1+E123) -> 1.05 | N123: =M123*(1+F123) -> 1.1025 | O123: =N123*(1+G123) -> 1.157625 | P123: =O123*(1+H123) -> 1.2155063 | Q123: =P123*(1+I123) -> 1.2762816 | R123: =Q123*(1+J123) -> 1.3400956
B124: 3. | C124: Indexation of other expenses | D124: 0 | E124: 0.05 | F124: 0.05 | G124: 0.05 | H124: 0.05 | I124: 0.05 | J124: 0.05 | L124: =1+D124 -> 1 | M124: =L124*(1+E124) -> 1.05 | N124: =M124*(1+F124) -> 1.1025 | O124: =N124*(1+G124) -> 1.157625 | P124: =O124*(1+H124) -> 1.2155063 | Q124: =P124*(1+I124) -> 1.2762816 | R124: =Q124*(1+J124) -> 1.3400956
B125: 4. | C125: Sales price indexation | D125: 0 | E125: 0.05 | F125: 0.05 | G125: 0.05 | H125: 0.05 | I125: 0.05 | J125: 0.05 | L125: =1+D125 -> 1 | M125: =L125*(1+E125) -> 1.05 | N125: =M125*(1+F125) -> 1.1025 | O125: =N125*(1+G125) -> 1.157625 | P125: =O125*(1+H125) -> 1.2155063 | Q125: =P125*(1+I125) -> 1.2762816 | R125: =Q125*(1+J125) -> 1.3400956
B128: 3. | C128: Discount Rate
B130: № | C130: Name | D130: Value
B131: 1. | C131: Discount rate | D131: 0.3
B132: 2. | C132: Multiplier - EV/EBITDA (to estimate the value of a business) | D132: 5

Sheet Results
B1: =BS!A1 -> Ok
D2: Financial Model — Results | J2: Made by | K2: https://feofinance.com/
D3: ='Input-Unit'!D9 -> StepUP
D6: =G33 -> 162300 | F6: =G31 -> 64920 | I6: =Input!D99 -> 324600 | L6: =Input!D98 -> 0.2
D7: Investment size (total) | F7: Investment size (investor) | I7: =Input!C99 -> Company valuation | L7: Investor's share
D9: =G225 -> 1868791 | F9: =G231 -> 1.17074 | I9: =-G225/G226 -> 28.78606 | L9: =if(G234<1,CONCATENATE(TEXT(round(G234*12,0),"0")," months"),CONCATENATE(TEXT(G234,"0.0")," years")) -> 2.0 years
D10: Investor's profit | F10: IRR (investor) | I10: Investor's capital gain | L10: Payback period (investor)
C14: I | D14: Project Budget
C16: № | D16: Name | G16: Total, $
C17: =CF!B17 -> 1. | D17: =CF!C17 -> Platform development | G17: =-CF!F17 -> 20000
C18: =CF!B18 -> 2. | D18: =CF!C18 -> Infrastructure setup | G18: =-CF!F18 -> 4400
C19: =CF!B19 -> 3. | D19: =CF!C19 | G19: =-CF!F19 -> 0
C20: =CF!B20 -> 4. | D20: =CF!C20 | G20: =-CF!F20 -> 0
C21: =CF!B21 -> 5. | D21: =CF!C21 | G21: =-CF!F21 -> 0
C22: 6. | D22: Working capital (marketing, payroll and other expenses) | G22: =IF((CF!F66+CF!F69)-SUM(G17:G21)<0,0,(CF!F66+CF!F69)-SUM(G17:G21)) -> 137900
D23: Total | G23: =SUM(G17:G22) -> 162300
C27: II | D27: Sources of Financing
C29: № | D29: Name | G29: =G16 -> Total, $
C30: 1. | D30: =Input!E91 -> Founders' funds | G30: =CF!F66 -> 97380 | Q30: =D30 -> Founders' funds | R30: =G30 -> 97380
C31: 2. | D31: =Input!D91 -> Investor's funds | G31: =CF!F69 -> 64920 | Q31: =D31 -> Investor's funds | R31: =G31 -> 64920
C32: 3. | D32: Project profit | G32: =IF(G23-G30-G31<0,0,G23-G30-G31) -> 0
D33: Total | G33: =G31+G30+G32 -> 162300
C38: III | D38: Unit-Economics
H50: =CONCATENATE("LTV / CAC = ",TEXT('Results-Unit'!H24,"# ##0.0")) -> LTV / CAC = 6.8
C54: IV | D54: =CF!C13 -> Cash Flow Statement (CF) | P54: Факт
P55: План
C56: № | D56: Name | F56: Total, $ | G56: =YEAR(CF!I1) -> 2026 | H56: =G56+1 -> 2027 | I56: =H56+1 -> 2028 | J56: =I56+1 -> 2029 | K56: =J56+1 -> 2030 | L56: =K56+1 -> 2031 | M56: =L56+1 -> 2032 | P56: Факт - далее план
C58: =CF!B15 -> 1. | D58: =CF!C15 -> Investment Phase
D59: =CF!C17 -> Platform development | F59: =SUM(G59:M59) -> -20000 | G59: =SUMIFS(CF!17:17,CF!$3:$3,G$56) -> -20000 | H59: =SUMIFS(CF!17:17,CF!$3:$3,H$56) -> 0 | I59: =SUMIFS(CF!17:17,CF!$3:$3,I$56) -> 0 | J59: =SUMIFS(CF!17:17,CF!$3:$3,J$56) -> 0 | K59: =SUMIFS(CF!17:17,CF!$3:$3,K$56) -> 0 | L59: =SUMIFS(CF!17:17,CF!$3:$3,L$56) -> 0 | M59: =SUMIFS(CF!17:17,CF!$3:$3,M$56) -> 0
D60: =CF!C18 -> Infrastructure setup | F60: =SUM(G60:M60) -> -4400 | G60: =SUMIFS(CF!18:18,CF!$3:$3,G$56) -> -4400 | H60: =SUMIFS(CF!18:18,CF!$3:$3,H$56) -> 0 | I60: =SUMIFS(CF!18:18,CF!$3:$3,I$56) -> 0 | J60: =SUMIFS(CF!18:18,CF!$3:$3,J$56) -> 0 | K60: =SUMIFS(CF!18:18,CF!$3:$3,K$56) -> 0 | L60: =SUMIFS(CF!18:18,CF!$3:$3,L$56) -> 0 | M60: =SUMIFS(CF!18:18,CF!$3:$3,M$56) -> 0
D61: =CF!C19 | F61: =SUM(G61:M61) -> 0 | G61: =SUMIFS(CF!19:19,CF!$3:$3,G$56) -> 0 | H61: =SUMIFS(CF!19:19,CF!$3:$3,H$56) -> 0 | I61: =SUMIFS(CF!19:19,CF!$3:$3,I$56) -> 0 | J61: =SUMIFS(CF!19:19,CF!$3:$3,J$56) -> 0 | K61: =SUMIFS(CF!19:19,CF!$3:$3,K$56) -> 0 | L61: =SUMIFS(CF!19:19,CF!$3:$3,L$56) -> 0 | M61: =SUMIFS(CF!19:19,CF!$3:$3,M$56) -> 0
D62: =CF!C20 | F62: =SUM(G62:M62) -> 0 | G62: =SUMIFS(CF!20:20,CF!$3:$3,G$56) -> 0 | H62: =SUMIFS(CF!20:20,CF!$3:$3,H$56) -> 0 | I62: =SUMIFS(CF!20:20,CF!$3:$3,I$56) -> 0 | J62: =SUMIFS(CF!20:20,CF!$3:$3,J$56) -> 0 | K62: =SUMIFS(CF!20:20,CF!$3:$3,K$56) -> 0 | L62: =SUMIFS(CF!20:20,CF!$3:$3,L$56) -> 0 | M62: =SUMIFS(CF!20:20,CF!$3:$3,M$56) -> 0
D63: =CF!C21 | F63: =SUM(G63:M63) -> 0 | G63: =SUMIFS(CF!21:21,CF!$3:$3,G$56) -> 0 | H63: =SUMIFS(CF!21:21,CF!$3:$3,H$56) -> 0 | I63: =SUMIFS(CF!21:21,CF!$3:$3,I$56) -> 0 | J63: =SUMIFS(CF!21:21,CF!$3:$3,J$56) -> 0 | K63: =SUMIFS(CF!21:21,CF!$3:$3,K$56) -> 0 | L63: =SUMIFS(CF!21:21,CF!$3:$3,L$56) -> 0 | M63: =SUMIFS(CF!21:21,CF!$3:$3,M$56) -> 0
D64: =CF!C22 -> Total investment phase | F64: =SUM(F59:F63) -> -24400 | G64: =SUM(G59:G63) -> -24400 | H64: =SUM(H59:H63) -> 0 | I64: =SUM(I59:I63) -> 0 | J64: =SUM(J59:J63) -> 0 | K64: =SUM(K59:K63) -> 0 | L64: =SUM(L59:L63) -> 0 | M64: =SUM(M59:M63) -> 0
C67: =CF!B25 -> 2. | D67: =CF!C25 -> Operational Phase
C68: =CF!B27 -> 1. | D68: =CF!C27 -> Income | F68: =SUM(G68:M68) -> 7861922.9 | G68: =SUM(G69) -> 0 | H68: =SUM(H69) -> 1155840 | I68: =SUM(I69) -> 1213632 | J68: =SUM(J69) -> 1274313.6 | K68: =SUM(K69) -> 1338029.3 | L68: =SUM(L69) -> 1404930.7 | M68: =SUM(M69) -> 1475177.3
C69: =CF!B28 -> 1.1. | D69: =CF!C28 -> Income — StepUP | F69: =SUM(G69:M69) -> 7861922.9 | G69: =SUMIFS(CF!28:28,CF!$3:$3,G$56) -> 0 | H69: =SUMIFS(CF!28:28,CF!$3:$3,H$56) -> 1155840 | I69: =SUMIFS(CF!28:28,CF!$3:$3,I$56) -> 1213632 | J69: =SUMIFS(CF!28:28,CF!$3:$3,J$56) -> 1274313.6 | K69: =SUMIFS(CF!28:28,CF!$3:$3,K$56) -> 1338029.3 | L69: =SUMIFS(CF!28:28,CF!$3:$3,L$56) -> 1404930.7 | M69: =SUMIFS(CF!28:28,CF!$3:$3,M$56) -> 1475177.3
C70: =CF!B30 -> 2. | D70: =CF!C30 -> Direct costs (marketing and sales) | F70: =SUM(G70:M70) -> -1114153.3 | G70: =SUM(G71:G73) -> 0 | H70: =SUM(H71:H73) -> -163800 | I70: =SUM(I71:I73) -> -171990 | J70: =SUM(J71:J73) -> -180589.5 | K70: =SUM(K71:K73) -> -189618.98 | L70: =SUM(L71:L73) -> -199099.92 | M70: =SUM(M71:M73) -> -209054.92
C71: =CF!B31 -> 2.1. | D71: =CF!C31 -> Advertising and marketing expenses | F71: =SUM(G71:M71) -> -428520.51 | G71: =SUMIFS(CF!31:31,CF!$3:$3,G$56) -> 0 | H71: =SUMIFS(CF!31:31,CF!$3:$3,H$56) -> -63000 | I71: =SUMIFS(CF!31:31,CF!$3:$3,I$56) -> -66150 | J71: =SUMIFS(CF!31:31,CF!$3:$3,J$56) -> -69457.5 | K71: =SUMIFS(CF!31:31,CF!$3:$3,K$56) -> -72930.375 | L71: =SUMIFS(CF!31:31,CF!$3:$3,L$56) -> -76576.894 | M71: =SUMIFS(CF!31:31,CF!$3:$3,M$56) -> -80405.738
C72: =CF!B32 -> 2.2. | D72: =CF!C32 -> Salary (marketing and sales) | F72: =SUM(G72:M72) -> -685632.81 | G72: =SUMIFS(CF!32:32,CF!$3:$3,G$56) -> 0 | H72: =SUMIFS(CF!32:32,CF!$3:$3,H$56) -> -100800 | I72: =SUMIFS(CF!32:32,CF!$3:$3,I$56) -> -105840 | J72: =SUMIFS(CF!32:32,CF!$3:$3,J$56) -> -111132 | K72: =SUMIFS(CF!32:32,CF!$3:$3,K$56) -> -116688.6 | L72: =SUMIFS(CF!32:32,CF!$3:$3,L$56) -> -122523.03 | M72: =SUMIFS(CF!32:32,CF!$3:$3,M$56) -> -128649.18
C73: =CF!B33 -> 2.3. | D73: =CF!C33 -> Other marketing and advertising expenses | F73: =SUM(G73:M73) -> 0 | G73: =SUMIFS(CF!33:33,CF!$3:$3,G$56) -> 0 | H73: =SUMIFS(CF!33:33,CF!$3:$3,H$56) -> 0 | I73: =SUMIFS(CF!33:33,CF!$3:$3,I$56) -> 0 | J73: =SUMIFS(CF!33:33,CF!$3:$3,J$56) -> 0 | K73: =SUMIFS(CF!33:33,CF!$3:$3,K$56) -> 0 | L73: =SUMIFS(CF!33:33,CF!$3:$3,L$56) -> 0 | M73: =SUMIFS(CF!33:33,CF!$3:$3,M$56) -> 0
C74: =CF!B35 -> 3. | D74: =CF!C35 -> Payroll — admin and others | F74: =SUM(F75:F76) -> -1030163.5 | G74: =SUM(G75:G76) -> -121700 | H74: =SUM(H75:H76) -> -133560 | I74: =SUM(I75:I76) -> -140238 | J74: =SUM(J75:J76) -> -147249.9 | K74: =SUM(K75:K76) -> -154612.39 | L74: =SUM(L75:L76) -> -162343.01 | M74: =SUM(M75:M76) -> -170460.17
C75: =CF!B36 -> 3.1. | D75: =CF!C36 -> Salary (Gross) | F75: =SUM(G75:M75) -> -1030163.5 | G75: =SUMIFS(CF!36:36,CF!$3:$3,G$56) -> -121700 | H75: =SUMIFS(CF!36:36,CF!$3:$3,H$56) -> -133560 | I75: =SUMIFS(CF!36:36,CF!$3:$3,I$56) -> -140238 | J75: =SUMIFS(CF!36:36,CF!$3:$3,J$56) -> -147249.9 | K75: =SUMIFS(CF!36:36,CF!$3:$3,K$56) -> -154612.39 | L75: =SUMIFS(CF!36:36,CF!$3:$3,L$56) -> -162343.01 | M75: =SUMIFS(CF!36:36,CF!$3:$3,M$56) -> -170460.17
C76: =CF!B37 -> 3.2. | D76: =CF!C37 -> Additional taxes and insurance contributions for employees | F76: =SUM(G76:M76) -> 0 | G76: =SUMIFS(CF!37:37,CF!$3:$3,G$56) -> 0 | H76: =SUMIFS(CF!37:37,CF!$3:$3,H$56) -> 0 | I76: =SUMIFS(CF!37:37,CF!$3:$3,I$56) -> 0 | J76: =SUMIFS(CF!37:37,CF!$3:$3,J$56) -> 0 | K76: =SUMIFS(CF!37:37,CF!$3:$3,K$56) -> 0 | L76: =SUMIFS(CF!37:37,CF!$3:$3,L$56) -> 0 | M76: =SUMIFS(CF!37:37,CF!$3:$3,M$56) -> 0
C77: =CF!B38 -> 4. | D77: =CF!C38 -> Fixed Expenses | F77: =SUM(F78:F87) -> -131900.54 | G77: =SUM(G78:G87) -> -16200 | H77: =SUM(H78:H87) -> -17010 | I77: =SUM(I78:I87) -> -17860.5 | J77: =SUM(J78:J87) -> -18753.525 | K77: =SUM(K78:K87) -> -19691.201 | L77: =SUM(L78:L87) -> -20675.761 | M77: =SUM(M78:M87) -> -21709.549
C78: =CF!B39 -> 4.1. | D78: =CF!C39 -> Servers | F78: =SUM(G78:M78) -> -117244.92 | G78: =SUMIFS(CF!39:39,CF!$3:$3,G$56) -> -14400 | H78: =SUMIFS(CF!39:39,CF!$3:$3,H$56) -> -15120 | I78: =SUMIFS(CF!39:39,CF!$3:$3,I$56) -> -15876 | J78: =SUMIFS(CF!39:39,CF!$3:$3,J$56) -> -16669.8 | K78: =SUMIFS(CF!39:39,CF!$3:$3,K$56) -> -17503.29 | L78: =SUMIFS(CF!39:39,CF!$3:$3,L$56) -> -18378.454 | M78: =SUMIFS(CF!39:39,CF!$3:$3,M$56) -> -19297.377
C79: =CF!B40 -> 4.2. | D79: =CF!C40 -> App analytics service | F79: =SUM(G79:M79) -> -14655.615 | G79: =SUMIFS(CF!40:40,CF!$3:$3,G$56) -> -1800 | H79: =SUMIFS(CF!40:40,CF!$3:$3,H$56) -> -1890 | I79: =SUMIFS(CF!40:40,CF!$3:$3,I$56) -> -1984.5 | J79: =SUMIFS(CF!40:40,CF!$3:$3,J$56) -> -2083.725 | K79: =SUMIFS(CF!40:40,CF!$3:$3,K$56) -> -2187.9113 | L79: =SUMIFS(CF!40:40,CF!$3:$3,L$56) -> -2297.3068 | M79: =SUMIFS(CF!40:40,CF!$3:$3,M$56) -> -2412.1722
C80: =CF!B41 -> 4.3. | D80: =CF!C41 | F80: =SUM(G80:M80) -> 0 | G80: =SUMIFS(CF!41:41,CF!$3:$3,G$56) -> 0 | H80: =SUMIFS(CF!41:41,CF!$3:$3,H$56) -> 0 | I80: =SUMIFS(CF!41:41,CF!$3:$3,I$56) -> 0 | J80: =SUMIFS(CF!41:41,CF!$3:$3,J$56) -> 0 | K80: =SUMIFS(CF!41:41,CF!$3:$3,K$56) -> 0 | L80: =SUMIFS(CF!41:41,CF!$3:$3,L$56) -> 0 | M80: =SUMIFS(CF!41:41,CF!$3:$3,M$56) -> 0
C81: =CF!B42 -> 4.4. | D81: =CF!C42 | F81: =SUM(G81:M81) -> 0 | G81: =SUMIFS(CF!42:42,CF!$3:$3,G$56) -> 0 | H81: =SUMIFS(CF!42:42,CF!$3:$3,H$56) -> 0 | I81: =SUMIFS(CF!42:42,CF!$3:$3,I$56) -> 0 | J81: =SUMIFS(CF!42:42,CF!$3:$3,J$56) -> 0 | K81: =SUMIFS(CF!42:42,CF!$3:$3,K$56) -> 0 | L81: =SUMIFS(CF!42:42,CF!$3:$3,L$56) -> 0 | M81: =SUMIFS(CF!42:42,CF!$3:$3,M$56) -> 0
C82: =CF!B43 -> 4.5. | D82: =CF!C43 | F82: =SUM(G82:M82) -> 0 | G82: =SUMIFS(CF!43:43,CF!$3:$3,G$56) -> 0 | H82: =SUMIFS(CF!43:43,CF!$3:$3,H$56) -> 0 | I82: =SUMIFS(CF!43:43,CF!$3:$3,I$56) -> 0 | J82: =SUMIFS(CF!43:43,CF!$3:$3,J$56) -> 0 | K82: =SUMIFS(CF!43:43,CF!$3:$3,K$56) -> 0 | L82: =SUMIFS(CF!43:43,CF!$3:$3,L$56) -> 0 | M82: =SUMIFS(CF!43:43,CF!$3:$3,M$56) -> 0
C83: =CF!B44 -> 4.6. | D83: =CF!C44 | F83: =SUM(G83:M83) -> 0 | G83: =SUMIFS(CF!44:44,CF!$3:$3,G$56) -> 0 | H83: =SUMIFS(CF!44:44,CF!$3:$3,H$56) -> 0 | I83: =SUMIFS(CF!44:44,CF!$3:$3,I$56) -> 0 | J83: =SUMIFS(CF!44:44,CF!$3:$3,J$56) -> 0 | K83: =SUMIFS(CF!44:44,CF!$3:$3,K$56) -> 0 | L83: =SUMIFS(CF!44:44,CF!$3:$3,L$56) -> 0 | M83: =SUMIFS(CF!44:44,CF!$3:$3,M$56) -> 0
C84: =CF!B45 -> 4.7. | D84: =CF!C45 | F84: =SUM(G84:M84) -> 0 | G84: =SUMIFS(CF!45:45,CF!$3:$3,G$56) -> 0 | H84: =SUMIFS(CF!45:45,CF!$3:$3,H$56) -> 0 | I84: =SUMIFS(CF!45:45,CF!$3:$3,I$56) -> 0 | J84: =SUMIFS(CF!45:45,CF!$3:$3,J$56) -> 0 | K84: =SUMIFS(CF!45:45,CF!$3:$3,K$56) -> 0 | L84: =SUMIFS(CF!45:45,CF!$3:$3,L$56) -> 0 | M84: =SUMIFS(CF!45:45,CF!$3:$3,M$56) -> 0
C85: =CF!B46 -> 4.8. | D85: =CF!C46 | F85: =SUM(G85:M85) -> 0 | G85: =SUMIFS(CF!46:46,CF!$3:$3,G$56) -> 0 | H85: =SUMIFS(CF!46:46,CF!$3:$3,H$56) -> 0 | I85: =SUMIFS(CF!46:46,CF!$3:$3,I$56) -> 0 | J85: =SUMIFS(CF!46:46,CF!$3:$3,J$56) -> 0 | K85: =SUMIFS(CF!46:46,CF!$3:$3,K$56) -> 0 | L85: =SUMIFS(CF!46:46,CF!$3:$3,L$56) -> 0 | M85: =SUMIFS(CF!46:46,CF!$3:$3,M$56) -> 0
C86: =CF!B47 -> 4.9. | D86: =CF!C47 | F86: =SUM(G86:M86) -> 0 | G86: =SUMIFS(CF!47:47,CF!$3:$3,G$56) -> 0 | H86: =SUMIFS(CF!47:47,CF!$3:$3,H$56) -> 0 | I86: =SUMIFS(CF!47:47,CF!$3:$3,I$56) -> 0 | J86: =SUMIFS(CF!47:47,CF!$3:$3,J$56) -> 0 | K86: =SUMIFS(CF!47:47,CF!$3:$3,K$56) -> 0 | L86: =SUMIFS(CF!47:47,CF!$3:$3,L$56) -> 0 | M86: =SUMIFS(CF!47:47,CF!$3:$3,M$56) -> 0
C87: =CF!B48 -> 4.8. | D87: =CF!C48 | F87: =SUM(G87:M87) -> 0 | G87: =SUMIFS(CF!48:48,CF!$3:$3,G$56) -> 0 | H87: =SUMIFS(CF!48:48,CF!$3:$3,H$56) -> 0 | I87: =SUMIFS(CF!48:48,CF!$3:$3,I$56) -> 0 | J87: =SUMIFS(CF!48:48,CF!$3:$3,J$56) -> 0 | K87: =SUMIFS(CF!48:48,CF!$3:$3,K$56) -> 0 | L87: =SUMIFS(CF!48:48,CF!$3:$3,L$56) -> 0 | M87: =SUMIFS(CF!48:48,CF!$3:$3,M$56) -> 0
C88: =CF!B49 -> 5. | D88: =CF!C49 -> Other Variable Expenses | F88: =SUM(F89:F95) -> -245896.84 | G88: =SUM(G89:G95) -> 0 | H88: =SUM(H89:H95) -> -38665.6 | I88: =SUM(I89:I95) -> -39532.48 | J88: =SUM(J89:J95) -> -40442.704 | K88: =SUM(K89:K95) -> -41398.439 | L88: =SUM(L89:L95) -> -42401.961 | M88: =SUM(M89:M95) -> -43455.659
C89: =CF!B50 -> 5.1. | D89: =CF!C50 -> Stores Commission | F89: =SUM(G89:M89) -> 0 | G89: =SUMIFS(CF!50:50,CF!$3:$3,G$56) -> 0 | H89: =SUMIFS(CF!50:50,CF!$3:$3,H$56) -> 0 | I89: =SUMIFS(CF!50:50,CF!$3:$3,I$56) -> 0 | J89: =SUMIFS(CF!50:50,CF!$3:$3,J$56) -> 0 | K89: =SUMIFS(CF!50:50,CF!$3:$3,K$56) -> 0 | L89: =SUMIFS(CF!50:50,CF!$3:$3,L$56) -> 0 | M89: =SUMIFS(CF!50:50,CF!$3:$3,M$56) -> 0
C90: =CF!B51 -> 5.2. | D90: =CF!C51 -> Bank's fee | F90: =SUM(G90:M90) -> -78619.229 | G90: =SUMIFS(CF!51:51,CF!$3:$3,G$56) -> 0 | H90: =SUMIFS(CF!51:51,CF!$3:$3,H$56) -> -11558.4 | I90: =SUMIFS(CF!51:51,CF!$3:$3,I$56) -> -12136.32 | J90: =SUMIFS(CF!51:51,CF!$3:$3,J$56) -> -12743.136 | K90: =SUMIFS(CF!51:51,CF!$3:$3,K$56) -> -13380.293 | L90: =SUMIFS(CF!51:51,CF!$3:$3,L$56) -> -14049.307 | M90: =SUMIFS(CF!51:51,CF!$3:$3,M$56) -> -14751.773
C91: =CF!B52 -> 5.3. | D91: =CF!C52 -> Other commissions | F91: =SUM(G91:M91) -> -39309.615 | G91: =SUMIFS(CF!52:52,CF!$3:$3,G$56) -> 0 | H91: =SUMIFS(CF!52:52,CF!$3:$3,H$56) -> -5779.2 | I91: =SUMIFS(CF!52:52,CF!$3:$3,I$56) -> -6068.16 | J91: =SUMIFS(CF!52:52,CF!$3:$3,J$56) -> -6371.568 | K91: =SUMIFS(CF!52:52,CF!$3:$3,K$56) -> -6690.1464 | L91: =SUMIFS(CF!52:52,CF!$3:$3,L$56) -> -7024.6537 | M91: =SUMIFS(CF!52:52,CF!$3:$3,M$56) -> -7375.8864
C92: =CF!B53 -> 5.4. | D92: =CF!C53 -> ChatGPT | F92: =SUM(G92:M92) -> -123840 | G92: =SUMIFS(CF!53:53,CF!$3:$3,G$56) -> 0 | H92: =SUMIFS(CF!53:53,CF!$3:$3,H$56) -> -20640 | I92: =SUMIFS(CF!53:53,CF!$3:$3,I$56) -> -20640 | J92: =SUMIFS(CF!53:53,CF!$3:$3,J$56) -> -20640 | K92: =SUMIFS(CF!53:53,CF!$3:$3,K$56) -> -20640 | L92: =SUMIFS(CF!53:53,CF!$3:$3,L$56) -> -20640 | M92: =SUMIFS(CF!53:53,CF!$3:$3,M$56) -> -20640
C93: =CF!B54 -> 5.5. | D93: =CF!C54 -> Free user service | F93: =SUM(G93:M93) -> -4128 | G93: =SUMIFS(CF!54:54,CF!$3:$3,G$56) -> 0 | H93: =SUMIFS(CF!54:54,CF!$3:$3,H$56) -> -688 | I93: =SUMIFS(CF!54:54,CF!$3:$3,I$56) -> -688 | J93: =SUMIFS(CF!54:54,CF!$3:$3,J$56) -> -688 | K93: =SUMIFS(CF!54:54,CF!$3:$3,K$56) -> -688 | L93: =SUMIFS(CF!54:54,CF!$3:$3,L$56) -> -688 | M93: =SUMIFS(CF!54:54,CF!$3:$3,M$56) -> -688
C94: =CF!B55 -> 5.6. | D94: =CF!C55 | F94: =SUM(G94:M94) -> 0 | G94: =SUMIFS(CF!55:55,CF!$3:$3,G$56) -> 0 | H94: =SUMIFS(CF!55:55,CF!$3:$3,H$56) -> 0 | I94: =SUMIFS(CF!55:55,CF!$3:$3,I$56) -> 0 | J94: =SUMIFS(CF!55:55,CF!$3:$3,J$56) -> 0 | K94: =SUMIFS(CF!55:55,CF!$3:$3,K$56) -> 0 | L94: =SUMIFS(CF!55:55,CF!$3:$3,L$56) -> 0 | M94: =SUMIFS(CF!55:55,CF!$3:$3,M$56) -> 0
C95: =CF!B56 -> 5.7. | D95: =CF!C56 | F95: =SUM(G95:M95) -> 0 | G95: =SUMIFS(CF!56:56,CF!$3:$3,G$56) -> 0 | H95: =SUMIFS(CF!56:56,CF!$3:$3,H$56) -> 0 | I95: =SUMIFS(CF!56:56,CF!$3:$3,I$56) -> 0 | J95: =SUMIFS(CF!56:56,CF!$3:$3,J$56) -> 0 | K95: =SUMIFS(CF!56:56,CF!$3:$3,K$56) -> 0 | L95: =SUMIFS(CF!56:56,CF!$3:$3,L$56) -> 0 | M95: =SUMIFS(CF!56:56,CF!$3:$3,M$56) -> 0
C96: =CF!B57 -> 6. | D96: =CF!C57 -> Taxes | F96: =SUM(F97:F98) -> -753361.58 | G96: =SUM(G97:G98) -> 0 | H96: =SUM(H97:H98) -> -97925.853 | I96: =SUM(I97:I98) -> -118193.5 | J96: =SUM(J97:J98) -> -124266.27 | K96: =SUM(K97:K98) -> -130642.69 | L96: =SUM(L97:L98) -> -137547.07 | M96: =SUM(M97:M98) -> -144786.21
C97: =CF!B58 -> 6.1. | D97: =CF!C58 -> Income tax | F97: =SUM(G97:M97) -> -451191.48 | G97: =SUMIFS(CF!58:58,CF!$3:$3,G$56) -> 0 | H97: =SUMIFS(CF!58:58,CF!$3:$3,H$56) -> -55270.406 | I97: =SUMIFS(CF!58:58,CF!$3:$3,I$56) -> -71324.496 | J97: =SUMIFS(CF!58:58,CF!$3:$3,J$56) -> -75003.041 | K97: =SUMIFS(CF!58:58,CF!$3:$3,K$56) -> -78865.513 | L97: =SUMIFS(CF!58:58,CF!$3:$3,L$56) -> -83130.251 | M97: =SUMIFS(CF!58:58,CF!$3:$3,M$56) -> -87597.77
C98: =CF!B59 -> 6.2. | D98: =CF!C59 -> VAT | F98: =SUM(G98:M98) -> -302170.1 | G98: =SUMIFS(CF!59:59,CF!$3:$3,G$56) -> 0 | H98: =SUMIFS(CF!59:59,CF!$3:$3,H$56) -> -42655.448 | I98: =SUMIFS(CF!59:59,CF!$3:$3,I$56) -> -46869.001 | J98: =SUMIFS(CF!59:59,CF!$3:$3,J$56) -> -49263.232 | K98: =SUMIFS(CF!59:59,CF!$3:$3,K$56) -> -51777.175 | L98: =SUMIFS(CF!59:59,CF!$3:$3,L$56) -> -54416.814 | M98: =SUMIFS(CF!59:59,CF!$3:$3,M$56) -> -57188.436
D99: =CF!C60 -> Total operational phase | F99: =SUM(G99:M99) -> 4586447.1 | G99: =G96+G88+G77+G74+G70+G68 -> -137900 | H99: =H96+H88+H77+H74+H70+H68 -> 704878.55 | I99: =I96+I88+I77+I74+I70+I68 -> 725817.52 | J99: =J96+J88+J77+J74+J70+J68 -> 763011.7 | K99: =K96+K88+K77+K74+K70+K68 -> 802065.58 | L99: =L96+L88+L77+L74+L70+L68 -> 842863.02 | M99: =M96+M88+M77+M74+M70+M68 -> 885710.78
C102: =CF!B63 -> 3. | D102: =CF!C63 -> Financial Phase
C103: =CF!B65 -> 3.1. | D103: =CF!C65 -> Founders' funds | F103: =SUM(G103:M103) -> 0 | G103: =G104+G105 -> 97380 | H103: =H104+H105 -> 0 | I103: =I104+I105 -> 0 | J103: =J104+J105 -> 0 | K103: =K104+K105 -> 0 | L103: =L104+L105 -> 0 | M103: =M104+M105 -> -97380
D104: =CF!C66 -> Contribution to the authorized capital | F104: =SUM(G104:M104) -> 97380 | G104: =SUMIFS(CF!66:66,CF!$3:$3,G$56) -> 97380 | H104: =SUMIFS(CF!66:66,CF!$3:$3,H$56) -> 0 | I104: =SUMIFS(CF!66:66,CF!$3:$3,I$56) -> 0 | J104: =SUMIFS(CF!66:66,CF!$3:$3,J$56) -> 0 | K104: =SUMIFS(CF!66:66,CF!$3:$3,K$56) -> 0 | L104: =SUMIFS(CF!66:66,CF!$3:$3,L$56) -> 0 | M104: =SUMIFS(CF!66:66,CF!$3:$3,M$56) -> 0
D105: =CF!C67 -> Sale of share capital (at nominal value) | F105: =SUM(G105:M105) -> -97380 | G105: =SUMIFS(CF!67:67,CF!$3:$3,G$56) -> 0 | H105: =SUMIFS(CF!67:67,CF!$3:$3,H$56) -> 0 | I105: =SUMIFS(CF!67:67,CF!$3:$3,I$56) -> 0 | J105: =SUMIFS(CF!67:67,CF!$3:$3,J$56) -> 0 | K105: =SUMIFS(CF!67:67,CF!$3:$3,K$56) -> 0 | L105: =SUMIFS(CF!67:67,CF!$3:$3,L$56) -> 0 | M105: =SUMIFS(CF!67:67,CF!$3:$3,M$56) -> -97380
C106: =CF!B68 -> 3.2. | D106: =CF!C68 -> Investor's funds | F106: =SUM(G106:M106) -> 0 | G106: =G107+G108 -> 64920 | H106: =H107+H108 -> 0 | I106: =I107+I108 -> 0 | J106: =J107+J108 -> 0 | K106: =K107+K108 -> 0 | L106: =L107+L108 -> 0 | M106: =M107+M108 -> -64920
D107: =CF!C69 -> Contribution to the authorized capital | F107: =SUM(G107:M107) -> 64920 | G107: =SUMIFS(CF!69:69,CF!$3:$3,G$56) -> 64920 | H107: =SUMIFS(CF!69:69,CF!$3:$3,H$56) -> 0 | I107: =SUMIFS(CF!69:69,CF!$3:$3,I$56) -> 0 | J107: =SUMIFS(CF!69:69,CF!$3:$3,J$56) -> 0 | K107: =SUMIFS(CF!69:69,CF!$3:$3,K$56) -> 0 | L107: =SUMIFS(CF!69:69,CF!$3:$3,L$56) -> 0 | M107: =SUMIFS(CF!69:69,CF!$3:$3,M$56) -> 0
D108: =CF!C70 -> Sale of share capital (at nominal value) | F108: =SUM(G108:M108) -> -64920 | G108: =SUMIFS(CF!70:70,CF!$3:$3,G$56) -> 0 | H108: =SUMIFS(CF!70:70,CF!$3:$3,H$56) -> 0 | I108: =SUMIFS(CF!70:70,CF!$3:$3,I$56) -> 0 | J108: =SUMIFS(CF!70:70,CF!$3:$3,J$56) -> 0 | K108: =SUMIFS(CF!70:70,CF!$3:$3,K$56) -> 0 | L108: =SUMIFS(CF!70:70,CF!$3:$3,L$56) -> 0 | M108: =SUMIFS(CF!70:70,CF!$3:$3,M$56) -> -64920
D109: =CF!C71 -> Total financial phase | F109: =SUM(G109:M109) -> 0 | G109: =G106+G103 -> 162300 | H109: =H106+H103 -> 0 | I109: =I106+I103 -> 0 | J109: =J106+J103 -> 0 | K109: =K106+K103 -> 0 | L109: =L106+L103 -> 0 | M109: =M106+M103 -> -162300
D111: =CF!C73 -> Total turnover for the period | F111: =SUM(G111:M111) -> 4562047.1 | G111: =G109+G64+G99 -> 0 | H111: =H109+H64+H99 -> 704878.55 | I111: =I109+I64+I99 -> 725817.52 | J111: =J109+J64+J99 -> 763011.7 | K111: =K109+K64+K99 -> 802065.58 | L111: =L109+L64+L99 -> 842863.02 | M111: =M109+M64+M99 -> 723410.78
D112: =CF!C74 -> Selling a business | F112: =SUM(G112:M112) -> 4781908.1 | G112: =SUMIFS(CF!74:74,CF!$3:$3,G$56) -> 0 | H112: =SUMIFS(CF!74:74,CF!$3:$3,H$56) -> 0 | I112: =SUMIFS(CF!74:74,CF!$3:$3,I$56) -> 0 | J112: =SUMIFS(CF!74:74,CF!$3:$3,J$56) -> 0 | K112: =SUMIFS(CF!74:74,CF!$3:$3,K$56) -> 0 | L112: =SUMIFS(CF!74:74,CF!$3:$3,L$56) -> 0 | M112: =SUMIFS(CF!74:74,CF!$3:$3,M$56) -> 4781908.1
D113: =CF!C75 -> Dividends | F113: =SUM(G113:M113) -> -9343955.2 | G113: =SUMIFS(CF!75:75,CF!$3:$3,G$56) -> 0 | H113: =SUMIFS(CF!75:75,CF!$3:$3,H$56) -> 0 | I113: =SUMIFS(CF!75:75,CF!$3:$3,I$56) -> -433259.89 | J113: =SUMIFS(CF!75:75,CF!$3:$3,J$56) -> -636966.56 | K113: =SUMIFS(CF!75:75,CF!$3:$3,K$56) -> -724222.97 | L113: =SUMIFS(CF!75:75,CF!$3:$3,L$56) -> -777851.51 | M113: =SUMIFS(CF!75:75,CF!$3:$3,M$56) -> -6771654.3
D114: =CF!C76 -> Account balance | F114: =M114 -> 0 | G114: =IF(ROUND(G111+G112+G113,2)=0,0,G111+G112+G113) -> 0 | H114: =IF(ROUND(H111+H112+H113+G114,2)=0,0,H111+H112+H113+G114) -> 704878.55 | I114: =IF(ROUND(I111+I112+I113+H114,2)=0,0,I111+I112+I113+H114) -> 997436.18 | J114: =IF(ROUND(J111+J112+J113+I114,2)=0,0,J111+J112+J113+I114) -> 1123481.3 | K114: =IF(ROUND(K111+K112+K113+J114,2)=0,0,K111+K112+K113+J114) -> 1201323.9 | L114: =IF(ROUND(L111+L112+L113+K114,2)=0,0,L111+L112+L113+K114) -> 1266335.4 | M114: =IF(ROUND(M111+M112+M113+L114,2)=0,0,M111+M112+M113+L114) -> 0
C147: V | D147: =PL!C13 -> Profit and Loss Statement (PL)
C149: № | D149: Name | F149: Total, $ | G149: =G$56 -> 2026 | H149: =H$56 -> 2027 | I149: =I$56 -> 2028 | J149: =J$56 -> 2029 | K149: =K$56 -> 2030 | L149: =L$56 -> 2031 | M149: =M$56 -> 2032
C150: 1. | D150: =PL!C15 -> Revenue | F150: =SUM(G150:M150) -> 7487545.6 | G150: =SUM(G151) -> 0 | H150: =SUM(H151) -> 1100800 | I150: =SUM(I151) -> 1155840 | J150: =SUM(J151) -> 1213632 | K150: =SUM(K151) -> 1274313.6 | L150: =SUM(L151) -> 1338029.3 | M150: =SUM(M151) -> 1404930.7
C151: =PL!B16 -> 1.1. | D151: =PL!C16 -> Income — StepUP | F151: =SUM(G151:M151) -> 7487545.6 | G151: =SUMIFS(PL!16:16,PL!$3:$3,G$56) -> 0 | H151: =SUMIFS(PL!16:16,PL!$3:$3,H$56) -> 1100800 | I151: =SUMIFS(PL!16:16,PL!$3:$3,I$56) -> 1155840 | J151: =SUMIFS(PL!16:16,PL!$3:$3,J$56) -> 1213632 | K151: =SUMIFS(PL!16:16,PL!$3:$3,K$56) -> 1274313.6 | L151: =SUMIFS(PL!16:16,PL!$3:$3,L$56) -> 1338029.3 | M151: =SUMIFS(PL!16:16,PL!$3:$3,M$56) -> 1404930.7
C152: 2. | D152: =PL!C17 -> Direct costs (marketing and sales) | F152: =SUM(G152:M152) -> -1061098.4 | G152: =SUM(G153:G155) -> 0 | H152: =SUM(H153:H155) -> -156000 | I152: =SUM(I153:I155) -> -163800 | J152: =SUM(J153:J155) -> -171990 | K152: =SUM(K153:K155) -> -180589.5 | L152: =SUM(L153:L155) -> -189618.98 | M152: =SUM(M153:M155) -> -199099.92
C153: =PL!B18 -> 2.1. | D153: =PL!C18 -> Advertising and marketing expenses | F153: =SUM(G153:M153) -> -408114.77 | G153: =SUMIFS(PL!18:18,PL!$3:$3,G$56) -> 0 | H153: =SUMIFS(PL!18:18,PL!$3:$3,H$56) -> -60000 | I153: =SUMIFS(PL!18:18,PL!$3:$3,I$56) -> -63000 | J153: =SUMIFS(PL!18:18,PL!$3:$3,J$56) -> -66150 | K153: =SUMIFS(PL!18:18,PL!$3:$3,K$56) -> -69457.5 | L153: =SUMIFS(PL!18:18,PL!$3:$3,L$56) -> -72930.375 | M153: =SUMIFS(PL!18:18,PL!$3:$3,M$56) -> -76576.894
C154: =PL!B19 -> 2.2. | D154: =PL!C19 -> Salary (marketing and sales) | F154: =SUM(G154:M154) -> -652983.63 | G154: =SUMIFS(PL!19:19,PL!$3:$3,G$56) -> 0 | H154: =SUMIFS(PL!19:19,PL!$3:$3,H$56) -> -96000 | I154: =SUMIFS(PL!19:19,PL!$3:$3,I$56) -> -100800 | J154: =SUMIFS(PL!19:19,PL!$3:$3,J$56) -> -105840 | K154: =SUMIFS(PL!19:19,PL!$3:$3,K$56) -> -111132 | L154: =SUMIFS(PL!19:19,PL!$3:$3,L$56) -> -116688.6 | M154: =SUMIFS(PL!19:19,PL!$3:$3,M$56) -> -122523.03
C155: =PL!B20 -> 2.3. | D155: =PL!C20 -> Other marketing and advertising expenses | F155: =SUM(G155:M155) -> 0 | G155: =SUMIFS(PL!20:20,PL!$3:$3,G$56) -> 0 | H155: =SUMIFS(PL!20:20,PL!$3:$3,H$56) -> 0 | I155: =SUMIFS(PL!20:20,PL!$3:$3,I$56) -> 0 | J155: =SUMIFS(PL!20:20,PL!$3:$3,J$56) -> 0 | K155: =SUMIFS(PL!20:20,PL!$3:$3,K$56) -> 0 | L155: =SUMIFS(PL!20:20,PL!$3:$3,L$56) -> 0 | M155: =SUMIFS(PL!20:20,PL!$3:$3,M$56) -> 0
D156: =PL!C21 -> Gross profit | F156: =SUM(G156:M156) -> 6426447.2 | G156: =G150+G152 -> 0 | H156: =H150+H152 -> 944800 | I156: =I150+I152 -> 992040 | J156: =J150+J152 -> 1041642 | K156: =K150+K152 -> 1093724.1 | L156: =L150+L152 -> 1148410.3 | M156: =M150+M152 -> 1205830.8
D157: =PL!C22 -> Return on sales | F157: =IFERROR(F156/F150,0) -> 0.85828488 | G157: =IFERROR(G156/G150,0) -> 0 | H157: =IFERROR(H156/H150,0) -> 0.85828488 | I157: =IFERROR(I156/I150,0) -> 0.85828488 | J157: =IFERROR(J156/J150,0) -> 0.85828488 | K157: =IFERROR(K156/K150,0) -> 0.85828488 | L157: =IFERROR(L156/L150,0) -> 0.85828488 | M157: =IFERROR(M156/M150,0) -> 0.85828488
C158: 3. | D158: =PL!C23 -> Payroll — admin and others | F158: =SUM(G158:M158) -> -1030163.5 | G158: =G159+G160 -> -121700 | H158: =H159+H160 -> -133560 | I158: =I159+I160 -> -140238 | J158: =J159+J160 -> -147249.9 | K158: =K159+K160 -> -154612.39 | L158: =L159+L160 -> -162343.01 | M158: =M159+M160 -> -170460.17
C159: 3.1. | D159: =PL!C24 -> Salary (Gross) | F159: =SUM(G159:M159) -> -1030163.5 | G159: =SUMIFS(PL!24:24,PL!$3:$3,G$56) -> -121700 | H159: =SUMIFS(PL!24:24,PL!$3:$3,H$56) -> -133560 | I159: =SUMIFS(PL!24:24,PL!$3:$3,I$56) -> -140238 | J159: =SUMIFS(PL!24:24,PL!$3:$3,J$56) -> -147249.9 | K159: =SUMIFS(PL!24:24,PL!$3:$3,K$56) -> -154612.39 | L159: =SUMIFS(PL!24:24,PL!$3:$3,L$56) -> -162343.01 | M159: =SUMIFS(PL!24:24,PL!$3:$3,M$56) -> -170460.17
C160: 3.2. | D160: =PL!C25 -> Additional taxes and insurance contributions for employees | F160: =SUM(G160:M160) -> 0 | G160: =SUMIFS(PL!25:25,PL!$3:$3,G$56) -> 0 | H160: =SUMIFS(PL!25:25,PL!$3:$3,H$56) -> 0 | I160: =SUMIFS(PL!25:25,PL!$3:$3,I$56) -> 0 | J160: =SUMIFS(PL!25:25,PL!$3:$3,J$56) -> 0 | K160: =SUMIFS(PL!25:25,PL!$3:$3,K$56) -> 0 | L160: =SUMIFS(PL!25:25,PL!$3:$3,L$56) -> 0 | M160: =SUMIFS(PL!25:25,PL!$3:$3,M$56) -> 0
C161: 4. | D161: =PL!C26 -> Fixed Expenses | F161: =SUM(G161:M161) -> -125619.56 | G161: =SUMIFS(PL!26:26,PL!$3:$3,G$56) -> -15428.571 | H161: =SUMIFS(PL!26:26,PL!$3:$3,H$56) -> -16200 | I161: =SUMIFS(PL!26:26,PL!$3:$3,I$56) -> -17010 | J161: =SUMIFS(PL!26:26,PL!$3:$3,J$56) -> -17860.5 | K161: =SUMIFS(PL!26:26,PL!$3:$3,K$56) -> -18753.525 | L161: =SUMIFS(PL!26:26,PL!$3:$3,L$56) -> -19691.201 | M161: =SUMIFS(PL!26:26,PL!$3:$3,M$56) -> -20675.761
C162: 5. | D162: =PL!C37 -> Other Variable Expenses | F162: =SUM(G162:M162) -> -234187.47 | G162: =SUMIFS(PL!37:37,PL!$3:$3,G$56) -> 0 | H162: =SUMIFS(PL!37:37,PL!$3:$3,H$56) -> -36824.381 | I162: =SUMIFS(PL!37:37,PL!$3:$3,I$56) -> -37649.981 | J162: =SUMIFS(PL!37:37,PL!$3:$3,J$56) -> -38516.861 | K162: =SUMIFS(PL!37:37,PL!$3:$3,K$56) -> -39427.085 | L162: =SUMIFS(PL!37:37,PL!$3:$3,L$56) -> -40382.82 | M162: =SUMIFS(PL!37:37,PL!$3:$3,M$56) -> -41386.342
C163: 6. | D163: =PL!C45 -> EBITDA | F163: =SUM(G163:M163) -> 5036476.7 | G163: =G156+G158+G161+G162 -> -137128.57 | H163: =H156+H158+H161+H162 -> 758215.62 | I163: =I156+I158+I161+I162 -> 797142.02 | J163: =J156+J158+J161+J162 -> 838014.74 | K163: =K156+K158+K161+K162 -> 880931.09 | L163: =L156+L158+L161+L162 -> 925993.27 | M163: =M156+M158+M161+M162 -> 973308.55
D164: =PL!C46 -> EBITDA margin | F164: =IFERROR(F163/F150,0) -> 0.67264722 | G164: =IFERROR(G163/G150,0) -> 0 | H164: =IFERROR(H163/H150,0) -> 0.68878599 | I164: =IFERROR(I163/I150,0) -> 0.68966468 | J164: =IFERROR(J163/J150,0) -> 0.69050152 | K164: =IFERROR(K163/K150,0) -> 0.69129851 | L164: =IFERROR(L163/L150,0) -> 0.69205755 | M164: =IFERROR(M163/M150,0) -> 0.69278045
C165: 6.1. | D165: =PL!C47 -> Depreciation | F165: =SUM(G165:M165) -> -23238.095 | G165: =SUMIFS(PL!47:47,PL!$3:$3,G$56) -> -2323.8095 | H165: =SUMIFS(PL!47:47,PL!$3:$3,H$56) -> -4647.619 | I165: =SUMIFS(PL!47:47,PL!$3:$3,I$56) -> -4647.619 | J165: =SUMIFS(PL!47:47,PL!$3:$3,J$56) -> -4647.619 | K165: =SUMIFS(PL!47:47,PL!$3:$3,K$56) -> -4647.619 | L165: =SUMIFS(PL!47:47,PL!$3:$3,L$56) -> -2323.8095 | M165: =SUMIFS(PL!47:47,PL!$3:$3,M$56) -> 0
C166: 7. | D166: =PL!C48 -> EBIT | F166: =SUM(G166:M166) -> 5013238.6 | G166: =G163+G165 -> -139452.38 | H166: =H163+H165 -> 753568 | I166: =I163+I165 -> 792494.4 | J166: =J163+J165 -> 833367.12 | K166: =K163+K165 -> 876283.48 | L166: =L163+L165 -> 923669.46 | M166: =M163+M165 -> 973308.55
C167: 7.1. | D167: =PL!C49 -> Interest receivable | F167: =SUM(G167:M167) -> 0 | G167: =SUMIFS(PL!49:49,PL!$3:$3,G$56) -> 0 | H167: =SUMIFS(PL!49:49,PL!$3:$3,H$56) -> 0 | I167: =SUMIFS(PL!49:49,PL!$3:$3,I$56) -> 0 | J167: =SUMIFS(PL!49:49,PL!$3:$3,J$56) -> 0 | K167: =SUMIFS(PL!49:49,PL!$3:$3,K$56) -> 0 | L167: =SUMIFS(PL!49:49,PL!$3:$3,L$56) -> 0 | M167: =SUMIFS(PL!49:49,PL!$3:$3,M$56) -> 0
C168: 7.2. | D168: =PL!C50 -> Interest paid | F168: =SUM(G168:M168) -> 0 | G168: =SUMIFS(PL!50:50,PL!$3:$3,G$56) -> 0 | H168: =SUMIFS(PL!50:50,PL!$3:$3,H$56) -> 0 | I168: =SUMIFS(PL!50:50,PL!$3:$3,I$56) -> 0 | J168: =SUMIFS(PL!50:50,PL!$3:$3,J$56) -> 0 | K168: =SUMIFS(PL!50:50,PL!$3:$3,K$56) -> 0 | L168: =SUMIFS(PL!50:50,PL!$3:$3,L$56) -> 0 | M168: =SUMIFS(PL!50:50,PL!$3:$3,M$56) -> 0
...

Sheet CF
A1: =BS!A1 -> Ok | B1: № | C1: Name | E1: Share | F1: Total | G1: Unit | I1: =Input!D19 -> 46023 | J1: =EOMONTH(I1,0)+1 -> 46054 | K1: =EOMONTH(J1,0)+1 -> 46082 | L1: =EOMONTH(K1,0)+1 -> 46113 | M1: =EOMONTH(L1,0)+1 -> 46143 | N1: =EOMONTH(M1,0)+1 -> 46174 | O1: =EOMONTH(N1,0)+1 -> 46204 | P1: =EOMONTH(O1,0)+1 -> 46235 | Q1: =EOMONTH(P1,0)+1 -> 46266 | ... CN1: =EOMONTH(CM1,0)+1 -> 48549
C2: Sales volume, MAU | I2: =if(I5<13,sumifs('Results-Unit'!$58:$58,'Results-Unit'!$56:$56,I$4-Input!$F$40),max('Results-Unit'!$58:$58)) -> 0 | J2: =if(J5<13,sumifs('Results-Unit'!$58:$58,'Results-Unit'!$56:$56,J$4-Input!$F$40),max('Results-Unit'!$58:$58)) -> 0 | K2: =if(K5<13,sumifs('Results-Unit'!$58:$58,'Results-Unit'!$56:$56,K$4-Input!$F$40),max('Results-Unit'!$58:$58)) -> 0 | L2: =if(L5<13,sumifs('Results-Unit'!$58:$58,'Results-Unit'!$56:$56,L$4-Input!$F$40),max('Results-Unit'!$58:$58)) -> 0 | M2: =if(M5<13,sumifs('Results-Unit'!$58:$58,'Results-Unit'!$56:$56,M$4-Input!$F$40),max('Results-Unit'!$58:$58)) -> 0 | N2: =if(N5<13,sumifs('Results-Unit'!$58:$58,'Results-Unit'!$56:$56,N$4-Input!$F$40),max('Results-Unit'!$58:$58)) -> 0 | O2: =if(O5<13,sumifs('Results-Unit'!$58:$58,'Results-Unit'!$56:$56,O$4-Input!$F$40),max('Results-Unit'!$58:$58)) -> 0 | P2: =if(P5<13,sumifs('Results-Unit'!$58:$58,'Results-Unit'!$56:$56,P$4-Input!$F$40),max('Results-Unit'!$58:$58)) -> 0 | ... CN2: =if(CN5<13,sumifs('Results-Unit'!$58:$58,'Results-Unit'!$56:$56,CN$4-Input!$F$40),max('Results-Unit'!$58:$58)) -> 229.33333
C3: Year | I3: =YEAR(I1) -> 2026 | J3: =YEAR(J1) -> 2026 | K3: =YEAR(K1) -> 2026 | L3: =YEAR(L1) -> 2026 | M3: =YEAR(M1) -> 2026 | N3: =YEAR(N1) -> 2026 | O3: =YEAR(O1) -> 2026 | P3: =YEAR(P1) -> 2026 | ... CN3: =YEAR(CN1) -> 2032
C4: Month | I4: =MONTH(I1) -> 1 | J4: =MONTH(J1) -> 2 | K4: =MONTH(K1) -> 3 | L4: =MONTH(L1) -> 4 | M4: =MONTH(M1) -> 5 | N4: =MONTH(N1) -> 6 | O4: =MONTH(O1) -> 7 | P4: =MONTH(P1) -> 8 | ... CN4: =MONTH(CN1) -> 12
C5: Serial number of the period | I5: 1 | J5: =I5+1 -> 2 | K5: =J5+1 -> 3 | L5: =K5+1 -> 4 | M5: =L5+1 -> 5 | N5: =M5+1 -> 6 | O5: =N5+1 -> 7 | P5: =O5+1 -> 8 | Q5: =P5+1 -> 9 | ... CN5: =CM5+1 -> 84
C6: =Input!C122 -> Indexation of production prices | I6: =SUMIFS(Input!$L122:$R122,Input!$L$121:$R$121,I$3) -> 1 | J6: =SUMIFS(Input!$L122:$R122,Input!$L$121:$R$121,J$3) -> 1 | K6: =SUMIFS(Input!$L122:$R122,Input!$L$121:$R$121,K$3) -> 1 | L6: =SUMIFS(Input!$L122:$R122,Input!$L$121:$R$121,L$3) -> 1 | M6: =SUMIFS(Input!$L122:$R122,Input!$L$121:$R$121,M$3) -> 1 | N6: =SUMIFS(Input!$L122:$R122,Input!$L$121:$R$121,N$3) -> 1 | O6: =SUMIFS(Input!$L122:$R122,Input!$L$121:$R$121,O$3) -> 1 | P6: =SUMIFS(Input!$L122:$R122,Input!$L$121:$R$121,P$3) -> 1 | ... CN6: =SUMIFS(Input!$L122:$R122,Input!$L$121:$R$121,CN$3) -> 1.3400956
C7: =Input!C123 -> Payroll indexation | I7: =SUMIFS(Input!$L123:$R123,Input!$L$121:$R$121,I$3) -> 1 | J7: =SUMIFS(Input!$L123:$R123,Input!$L$121:$R$121,J$3) -> 1 | K7: =SUMIFS(Input!$L123:$R123,Input!$L$121:$R$121,K$3) -> 1 | L7: =SUMIFS(Input!$L123:$R123,Input!$L$121:$R$121,L$3) -> 1 | M7: =SUMIFS(Input!$L123:$R123,Input!$L$121:$R$121,M$3) -> 1 | N7: =SUMIFS(Input!$L123:$R123,Input!$L$121:$R$121,N$3) -> 1 | O7: =SUMIFS(Input!$L123:$R123,Input!$L$121:$R$121,O$3) -> 1 | P7: =SUMIFS(Input!$L123:$R123,Input!$L$121:$R$121,P$3) -> 1 | ... CN7: =SUMIFS(Input!$L123:$R123,Input!$L$121:$R$121,CN$3) -> 1.3400956
C8: =Input!C124 -> Indexation of other expenses | I8: =SUMIFS(Input!$L124:$R124,Input!$L$121:$R$121,I$3) -> 1 | J8: =SUMIFS(Input!$L124:$R124,Input!$L$121:$R$121,J$3) -> 1 | K8: =SUMIFS(Input!$L124:$R124,Input!$L$121:$R$121,K$3) -> 1 | L8: =SUMIFS(Input!$L124:$R124,Input!$L$121:$R$121,L$3) -> 1 | M8: =SUMIFS(Input!$L124:$R124,Input!$L$121:$R$121,M$3) -> 1 | N8: =SUMIFS(Input!$L124:$R124,Input!$L$121:$R$121,N$3) -> 1 | O8: =SUMIFS(Input!$L124:$R124,Input!$L$121:$R$121,O$3) -> 1 | P8: =SUMIFS(Input!$L124:$R124,Input!$L$121:$R$121,P$3) -> 1 | ... CN8: =SUMIFS(Input!$L124:$R124,Input!$L$121:$R$121,CN$3) -> 1.3400956
C9: =Input!C125 -> Sales price indexation | I9: =SUMIFS(Input!$L125:$R125,Input!$L$121:$R$121,I$3) -> 1 | J9: =SUMIFS(Input!$L125:$R125,Input!$L$121:$R$121,J$3) -> 1 | K9: =SUMIFS(Input!$L125:$R125,Input!$L$121:$R$121,K$3) -> 1 | L9: =SUMIFS(Input!$L125:$R125,Input!$L$121:$R$121,L$3) -> 1 | M9: =SUMIFS(Input!$L125:$R125,Input!$L$121:$R$121,M$3) -> 1 | N9: =SUMIFS(Input!$L125:$R125,Input!$L$121:$R$121,N$3) -> 1 | O9: =SUMIFS(Input!$L125:$R125,Input!$L$121:$R$121,O$3) -> 1 | P9: =SUMIFS(Input!$L125:$R125,Input!$L$121:$R$121,P$3) -> 1 | ... CN9: =SUMIFS(Input!$L125:$R125,Input!$L$121:$R$121,CN$3) -> 1.3400956
C13: Cash Flow Statement (CF)
B15: 1. | C15: Investment Phase
B17: =Other!B15 -> 1. | C17: =Other!C15 -> Platform development | E17: =IFERROR(F17/$F$22,0) -> 0.81967213 | F17: =SUM(I17:CN17) -> -20000 | G17: $ | I17: =Other!I15 -> -5000 | J17: =Other!J15 -> -5000 | K17: =Other!K15 -> -5000 | L17: =Other!L15 -> -5000 | M17: =Other!M15 -> 0 | N17: =Other!N15 -> 0 | O17: =Other!O15 -> 0 | P17: =Other!P15 -> 0 | ... CN17: =Other!CN15 -> 0
B18: =Other!B16 -> 2. | C18: =Other!C16 -> Infrastructure setup | E18: =IFERROR(F18/$F$22,0) -> 0.18032787 | F18: =SUM(I18:CN18) -> -4400 | G18: $ | I18: =Other!I16 -> 0 | J18: =Other!J16 -> 0 | K18: =Other!K16 -> 0 | L18: =Other!L16 -> 0 | M18: =Other!M16 -> -4400 | N18: =Other!N16 -> 0 | O18: =Other!O16 -> 0 | P18: =Other!P16 -> 0 | ... CN18: =Other!CN16 -> 0
B19: =Other!B17 -> 3. | C19: =Other!C17 | E19: =IFERROR(F19/$F$22,0) -> 0 | F19: =SUM(I19:CN19) -> 0 | G19: $ | I19: =Other!I17 -> 0 | J19: =Other!J17 -> 0 | K19: =Other!K17 -> 0 | L19: =Other!L17 -> 0 | M19: =Other!M17 -> 0 | N19: =Other!N17 -> 0 | O19: =Other!O17 -> 0 | P19: =Other!P17 -> 0 | ... CN19: =Other!CN17 -> 0
B20: =Other!B18 -> 4. | C20: =Other!C18 | E20: =IFERROR(F20/$F$22,0) -> 0 | F20: =SUM(I20:CN20) -> 0 | G20: $ | I20: =Other!I18 -> 0 | J20: =Other!J18 -> 0 | K20: =Other!K18 -> 0 | L20: =Other!L18 -> 0 | M20: =Other!M18 -> 0 | N20: =Other!N18 -> 0 | O20: =Other!O18 -> 0 | P20: =Other!P18 -> 0 | ... CN20: =Other!CN18 -> 0
B21: =Other!B19 -> 5. | C21: =Other!C19 | E21: =IFERROR(F21/$F$22,0) -> 0 | F21: =SUM(I21:CN21) -> 0 | G21: $ | I21: =Other!I19 -> 0 | J21: =Other!J19 -> 0 | K21: =Other!K19 -> 0 | L21: =Other!L19 -> 0 | M21: =Other!M19 -> 0 | N21: =Other!N19 -> 0 | O21: =Other!O19 -> 0 | P21: =Other!P19 -> 0 | ... CN21: =Other!CN19 -> 0
C22: Total investment phase | E22: =IFERROR(F22/$F$22,0) -> 1 | F22: =SUM(I22:CN22) -> -24400 | G22: $ | I22: =SUM(I17:I21) -> -5000 | J22: =SUM(J17:J21) -> -5000 | K22: =SUM(K17:K21) -> -5000 | L22: =SUM(L17:L21) -> -5000 | M22: =SUM(M17:M21) -> -4400 | N22: =SUM(N17:N21) -> 0 | O22: =SUM(O17:O21) -> 0 | P22: =SUM(P17:P21) -> 0 | ... CN22: =SUM(CN17:CN21) -> 0
B25: 2. | C25: Operational Phase
B27: 1. | C27: Income | E27: =IFERROR(F27/$F$27,0) -> 1 | F27: =SUM(I27:CN27) -> 7861922.9 | G27: $ | I27: =SUM(I28) -> 0 | J27: =SUM(J28) -> 0 | K27: =SUM(K28) -> 0 | L27: =SUM(L28) -> 0 | M27: =SUM(M28) -> 0 | N27: =SUM(N28) -> 0 | O27: =SUM(O28) -> 0 | P27: =SUM(P28) -> 0 | ... CN27: =SUM(CN28) -> 122931.44
B28: 1.1. | C28: =CONCATENATE("Income — ",'Input-Unit'!D9) -> Income — StepUP | E28: =IFERROR(F28/$F$27,0) -> 1 | F28: =SUM(I28:CN28) -> 7861922.9 | G28: $ | I28: =if(I5<13,sumifs('Results-Unit'!$57:$57,'Results-Unit'!$56:$56,I$4-Input!$F$40),max('Results-Unit'!$57:$57))*I9 -> 0 | J28: =if(J5<13,sumifs('Results-Unit'!$57:$57,'Results-Unit'!$56:$56,J$4-Input!$F$40),max('Results-Unit'!$57:$57))*J9 -> 0 | K28: =if(K5<13,sumifs('Results-Unit'!$57:$57,'Results-Unit'!$56:$56,K$4-Input!$F$40),max('Results-Unit'!$57:$57))*K9 -> 0 | L28: =if(L5<13,sumifs('Results-Unit'!$57:$57,'Results-Unit'!$56:$56,L$4-Input!$F$40),max('Results-Unit'!$57:$57))*L9 -> 0 | M28: =if(M5<13,sumifs('Results-Unit'!$57:$57,'Results-Unit'!$56:$56,M$4-Input!$F$40),max('Results-Unit'!$57:$57))*M9 -> 0 | N28: =if(N5<13,sumifs('Results-Unit'!$57:$57,'Results-Unit'!$56:$56,N$4-Input!$F$40),max('Results-Unit'!$57:$57))*N9 -> 0 | O28: =if(O5<13,sumifs('Results-Unit'!$57:$57,'Results-Unit'!$56:$56,O$4-Input!$F$40),max('Results-Unit'!$57:$57))*O9 -> 0 | P28: =if(P5<13,sumifs('Results-Unit'!$57:$57,'Results-Unit'!$56:$56,P$4-Input!$F$40),max('Results-Unit'!$57:$57))*P9 -> 0 | ... CN28: =if(CN5<13,sumifs('Results-Unit'!$57:$57,'Results-Unit'!$56:$56,CN$4-Input!$F$40),max('Results-Unit'!$57:$57))*CN9 -> 122931.44
B30: 2. | C30: Direct costs (marketing and sales) | E30: =IFERROR(F30/(CF!$F$30+$F$38+$F$49+$F$57+$F$35),0) -> 0.34015007 | F30: =SUM(I30:CN30) -> -1114153.3 | G30: $ | I30: =SUM(I31:I33) -> 0 | J30: =SUM(J31:J33) -> 0 | K30: =SUM(K31:K33) -> 0 | L30: =SUM(L31:L33) -> 0 | M30: =SUM(M31:M33) -> 0 | N30: =SUM(N31:N33) -> 0 | O30: =SUM(O31:O33) -> 0 | P30: =SUM(P31:P33) -> 0 | ... CN30: =SUM(CN31:CN33) -> -17421.243
B31: 2.1. | C31: ='Results-Unit'!C62 -> Advertising and marketing expenses | E31: =IFERROR(F31/(CF!$F$30+$F$38+$F$49+$F$57+$F$35),0) -> 0.13082695 | F31: =SUM(I31:CN31) -> -428520.51 | G31: $ | I31: =if(I5<13,sumifs('Results-Unit'!$62:$62,'Results-Unit'!$56:$56,I$4-Input!$F$40),'Results-Unit'!$R$62)*I$8 -> 0 | J31: =if(J5<13,sumifs('Results-Unit'!$62:$62,'Results-Unit'!$56:$56,J$4-Input!$F$40),'Results-Unit'!$R$62)*J$8 -> 0 | K31: =if(K5<13,sumifs('Results-Unit'!$62:$62,'Results-Unit'!$56:$56,K$4-Input!$F$40),'Results-Unit'!$R$62)*K$8 -> 0 | L31: =if(L5<13,sumifs('Results-Unit'!$62:$62,'Results-Unit'!$56:$56,L$4-Input!$F$40),'Results-Unit'!$R$62)*L$8 -> 0 | M31: =if(M5<13,sumifs('Results-Unit'!$62:$62,'Results-Unit'!$56:$56,M$4-Input!$F$40),'Results-Unit'!$R$62)*M$8 -> 0 | N31: =if(N5<13,sumifs('Results-Unit'!$62:$62,'Results-Unit'!$56:$56,N$4-Input!$F$40),'Results-Unit'!$R$62)*N$8 -> 0 | O31: =if(O5<13,sumifs('Results-Unit'!$62:$62,'Results-Unit'!$56:$56,O$4-Input!$F$40),'Results-Unit'!$R$62)*O$8 -> 0 | P31: =if(P5<13,sumifs('Results-Unit'!$62:$62,'Results-Unit'!$56:$56,P$4-Input!$F$40),'Results-Unit'!$R$62)*P$8 -> 0 | ... CN31: =if(CN5<13,sumifs('Results-Unit'!$62:$62,'Results-Unit'!$56:$56,CN$4-Input!$F$40),'Results-Unit'!$R$62)*CN$8 -> -6700.4782
B32: 2.2. | C32: ='Results-Unit'!C66&" (marketing and sales)" -> Salary (marketing and sales) | E32: =IFERROR(F32/(CF!$F$30+$F$38+$F$49+$F$57+$F$35),0) -> 0.20932312 | F32: =SUM(I32:CN32) -> -685632.81 | G32: $ | I32: =if(I5<13,sumifs('Results-Unit'!$66:$66,'Results-Unit'!$56:$56,I$4-Input!$F$40),'Results-Unit'!$R$66)*I$8 -> 0 | J32: =if(J5<13,sumifs('Results-Unit'!$66:$66,'Results-Unit'!$56:$56,J$4-Input!$F$40),'Results-Unit'!$R$66)*J$8 -> 0 | K32: =if(K5<13,sumifs('Results-Unit'!$66:$66,'Results-Unit'!$56:$56,K$4-Input!$F$40),'Results-Unit'!$R$66)*K$8 -> 0 | L32: =if(L5<13,sumifs('Results-Unit'!$66:$66,'Results-Unit'!$56:$56,L$4-Input!$F$40),'Results-Unit'!$R$66)*L$8 -> 0 | M32: =if(M5<13,sumifs('Results-Unit'!$66:$66,'Results-Unit'!$56:$56,M$4-Input!$F$40),'Results-Unit'!$R$66)*M$8 -> 0 | N32: =if(N5<13,sumifs('Results-Unit'!$66:$66,'Results-Unit'!$56:$56,N$4-Input!$F$40),'Results-Unit'!$R$66)*N$8 -> 0 | O32: =if(O5<13,sumifs('Results-Unit'!$66:$66,'Results-Unit'!$56:$56,O$4-Input!$F$40),'Results-Unit'!$R$66)*O$8 -> 0 | P32: =if(P5<13,sumifs('Results-Unit'!$66:$66,'Results-Unit'!$56:$56,P$4-Input!$F$40),'Results-Unit'!$R$66)*P$8 -> 0 | ... CN32: =if(CN5<13,sumifs('Results-Unit'!$66:$66,'Results-Unit'!$56:$56,CN$4-Input!$F$40),'Results-Unit'!$R$66)*CN$8 -> -10720.765
B33: 2.3. | C33: ='Results-Unit'!C77 -> Other marketing and advertising expenses | E33: =IFERROR(F33/(CF!$F$30+$F$38+$F$49+$F$57+$F$35),0) -> 0 | F33: =SUM(I33:CN33) -> 0 | G33: $ | I33: =if(I5<13,sumifs('Results-Unit'!$77:$77,'Results-Unit'!$56:$56,I$4-Input!$F$40),'Results-Unit'!$R$77)*I$8 -> 0 | J33: =if(J5<13,sumifs('Results-Unit'!$77:$77,'Results-Unit'!$56:$56,J$4-Input!$F$40),'Results-Unit'!$R$77)*J$8 -> 0 | K33: =if(K5<13,sumifs('Results-Unit'!$77:$77,'Results-Unit'!$56:$56,K$4-Input!$F$40),'Results-Unit'!$R$77)*K$8 -> 0 | L33: =if(L5<13,sumifs('Results-Unit'!$77:$77,'Results-Unit'!$56:$56,L$4-Input!$F$40),'Results-Unit'!$R$77)*L$8 -> 0 | M33: =if(M5<13,sumifs('Results-Unit'!$77:$77,'Results-Unit'!$56:$56,M$4-Input!$F$40),'Results-Unit'!$R$77)*M$8 -> 0 | N33: =if(N5<13,sumifs('Results-Unit'!$77:$77,'Results-Unit'!$56:$56,N$4-Input!$F$40),'Results-Unit'!$R$77)*N$8 -> 0 | O33: =if(O5<13,sumifs('Results-Unit'!$77:$77,'Results-Unit'!$56:$56,O$4-Input!$F$40),'Results-Unit'!$R$77)*O$8 -> 0 | P33: =if(P5<13,sumifs('Results-Unit'!$77:$77,'Results-Unit'!$56:$56,P$4-Input!$F$40),'Results-Unit'!$R$77)*P$8 -> 0 | ... CN33: =if(CN5<13,sumifs('Results-Unit'!$77:$77,'Results-Unit'!$56:$56,CN$4-Input!$F$40),'Results-Unit'!$R$77)*CN$8 -> 0
B35: 3. | C35: Payroll — admin and others | E35: =IFERROR(F35/(CF!$F$30+$F$38+$F$49+$F$57+$F$35),0) -> 0.31450804 | F35: =SUM(I35:CN35) -> -1030163.5 | G35: $ | I35: =I37+I36 -> -9500 | J35: =J37+J36 -> -9500 | K35: =K37+K36 -> -9500 | L35: =L37+L36 -> -9500 | M35: =M37+M36 -> -9500 | N35: =N37+N36 -> -10600 | O35: =O37+O36 -> -10600 | P35: =P37+P36 -> -10600 | ... CN35: =CN37+CN36 -> -14205.014
B36: 3.1. | C36: Salary (Gross) | E36: =IFERROR(F36/(CF!$F$30+$F$38+$F$49+$F$57+$F$35),0) -> 0.31450804 | F36: =SUM(I36:CN36) -> -1030163.5 | G36: $ | I36: =Other!I73 -> -9500 | J36: =Other!J73 -> -9500 | K36: =Other!K73 -> -9500 | L36: =Other!L73 -> -9500 | M36: =Other!M73 -> -9500 | N36: =Other!N73 -> -10600 | O36: =Other!O73 -> -10600 | P36: =Other!P73 -> -10600 | ... CN36: =Other!CN73 -> -14205.014
B37: 3.2. | C37: =Input!C116 -> Additional taxes and insurance contributions for employees | E37: =IFERROR(F37/(CF!$F$30+$F$38+$F$49+$F$57+$F$35),0) -> 0 | F37: =SUM(I37:CN37) -> 0 | G37: $ | I37: =Other!I86 -> 0 | J37: =Other!J86 -> 0 | K37: =Other!K86 -> 0 | L37: =Other!L86 -> 0 | M37: =Other!M86 -> 0 | N37: =Other!N86 -> 0 | O37: =Other!O86 -> 0 | P37: =Other!P86 -> 0 | ... CN37: =Other!CN86 -> 0
B38: 4. | C38: =Input!C61 -> Fixed Expenses | E38: =IFERROR(F38/(CF!$F$30+$F$38+$F$49+$F$57+$F$35),0) -> 0.040269123 | F38: =SUM(I38:CN38) -> -131900.54 | G38: $ | I38: =SUM(I39:I48) -> -1350 | J38: =SUM(J39:J48) -> -1350 | K38: =SUM(K39:K48) -> -1350 | L38: =SUM(L39:L48) -> -1350 | M38: =SUM(M39:M48) -> -1350 | N38: =SUM(N39:N48) -> -1350 | O38: =SUM(O39:O48) -> -1350 | P38: =SUM(P39:P48) -> -1350 | ... CN38: =SUM(CN39:CN48) -> -1809.1291
B39: 4.1. | C39: =Input!C64 -> Servers | E39: =IFERROR(F39/(CF!$F$30+$F$38+$F$49+$F$57+$F$35),0) -> 0.035794776 | F39: =SUM(I39:CN39) -> -117244.92 | G39: $ | I39: =-IF(AND(I$1>=Input!$E64,I$1<=Input!$F64),Input!$D64,0)*I$8 -> -1200 | J39: =-IF(AND(J$1>=Input!$E64,J$1<=Input!$F64),Input!$D64,0)*J$8 -> -1200 | K39: =-IF(AND(K$1>=Input!$E64,K$1<=Input!$F64),Input!$D64,0)*K$8 -> -1200 | L39: =-IF(AND(L$1>=Input!$E64,L$1<=Input!$F64),Input!$D64,0)*L$8 -> -1200 | M39: =-IF(AND(M$1>=Input!$E64,M$1<=Input!$F64),Input!$D64,0)*M$8 -> -1200 | N39: =-IF(AND(N$1>=Input!$E64,N$1<=Input!$F64),Input!$D64,0)*N$8 -> -1200 | O39: =-IF(AND(O$1>=Input!$E64,O$1<=Input!$F64),Input!$D64,0)*O$8 -> -1200 | P39: =-IF(AND(P$1>=Input!$E64,P$1<=Input!$F64),Input!$D64,0)*P$8 -> -1200 | ... CN39: =-IF(AND(CN$1>=Input!$E64,CN$1<=Input!$F64),Input!$D64,0)*CN$8 -> -1608.1148
B40: 4.2. | C40: =Input!C65 -> App analytics service | E40: =IFERROR(F40/(CF!$F$30+$F$38+$F$49+$F$57+$F$35),0) -> 0.004474347 | F40: =SUM(I40:CN40) -> -14655.615 | G40: $ | I40: =-IF(AND(I$1>=Input!$E65,I$1<=Input!$F65),Input!$D65,0)*I$8 -> -150 | J40: =-IF(AND(J$1>=Input!$E65,J$1<=Input!$F65),Input!$D65,0)*J$8 -> -150 | K40: =-IF(AND(K$1>=Input!$E65,K$1<=Input!$F65),Input!$D65,0)*K$8 -> -150 | L40: =-IF(AND(L$1>=Input!$E65,L$1<=Input!$F65),Input!$D65,0)*L$8 -> -150 | M40: =-IF(AND(M$1>=Input!$E65,M$1<=Input!$F65),Input!$D65,0)*M$8 -> -150 | N40: =-IF(AND(N$1>=Input!$E65,N$1<=Input!$F65),Input!$D65,0)*N$8 -> -150 | O40: =-IF(AND(O$1>=Input!$E65,O$1<=Input!$F65),Input!$D65,0)*O$8 -> -150 | P40: =-IF(AND(P$1>=Input!$E65,P$1<=Input!$F65),Input!$D65,0)*P$8 -> -150 | ... CN40: =-IF(AND(CN$1>=Input!$E65,CN$1<=Input!$F65),Input!$D65,0)*CN$8 -> -201.01435
B41: 4.3. | C41: =Input!C66 | E41: =IFERROR(F41/(CF!$F$30+$F$38+$F$49+$F$57+$F$35),0) -> 0 | F41: =SUM(I41:CN41) -> 0 | G41: $ | I41: =-IF(AND(I$1>=Input!$E66,I$1<=Input!$F66),Input!$D66,0)*I$8 -> 0 | J41: =-IF(AND(J$1>=Input!$E66,J$1<=Input!$F66),Input!$D66,0)*J$8 -> 0 | K41: =-IF(AND(K$1>=Input!$E66,K$1<=Input!$F66),Input!$D66,0)*K$8 -> 0 | L41: =-IF(AND(L$1>=Input!$E66,L$1<=Input!$F66),Input!$D66,0)*L$8 -> 0 | M41: =-IF(AND(M$1>=Input!$E66,M$1<=Input!$F66),Input!$D66,0)*M$8 -> 0 | N41: =-IF(AND(N$1>=Input!$E66,N$1<=Input!$F66),Input!$D66,0)*N$8 -> 0 | O41: =-IF(AND(O$1>=Input!$E66,O$1<=Input!$F66),Input!$D66,0)*O$8 -> 0 | P41: =-IF(AND(P$1>=Input!$E66,P$1<=Input!$F66),Input!$D66,0)*P$8 -> 0 | ... CN41: =-IF(AND(CN$1>=Input!$E66,CN$1<=Input!$F66),Input!$D66,0)*CN$8 -> 0
B42: 4.4. | C42: =Input!C67 | E42: =IFERROR(F42/(CF!$F$30+$F$38+$F$49+$F$57+$F$35),0) -> 0 | F42: =SUM(I42:CN42) -> 0 | G42: $ | I42: =-IF(AND(I$1>=Input!$E67,I$1<=Input!$F67),Input!$D67,0)*I$8 -> 0 | J42: =-IF(AND(J$1>=Input!$E67,J$1<=Input!$F67),Input!$D67,0)*J$8 -> 0 | K42: =-IF(AND(K$1>=Input!$E67,K$1<=Input!$F67),Input!$D67,0)*K$8 -> 0 | L42: =-IF(AND(L$1>=Input!$E67,L$1<=Input!$F67),Input!$D67,0)*L$8 -> 0 | M42: =-IF(AND(M$1>=Input!$E67,M$1<=Input!$F67),Input!$D67,0)*M$8 -> 0 | N42: =-IF(AND(N$1>=Input!$E67,N$1<=Input!$F67),Input!$D67,0)*N$8 -> 0 | O42: =-IF(AND(O$1>=Input!$E67,O$1<=Input!$F67),Input!$D67,0)*O$8 -> 0 | P42: =-IF(AND(P$1>=Input!$E67,P$1<=Input!$F67),Input!$D67,0)*P$8 -> 0 | ... CN42: =-IF(AND(CN$1>=Input!$E67,CN$1<=Input!$F67),Input!$D67,0)*CN$8 -> 0
B43: 4.5. | C43: =Input!C68 | E43: =IFERROR(F43/(CF!$F$30+$F$38+$F$49+$F$57+$F$35),0) -> 0 | F43: =SUM(I43:CN43) -> 0 | G43: $ | I43: =-IF(AND(I$1>=Input!$E68,I$1<=Input!$F68),Input!$D68,0)*I$8 -> 0 | J43: =-IF(AND(J$1>=Input!$E68,J$1<=Input!$F68),Input!$D68,0)*J$8 -> 0 | K43: =-IF(AND(K$1>=Input!$E68,K$1<=Input!$F68),Input!$D68,0)*K$8 -> 0 | L43: =-IF(AND(L$1>=Input!$E68,L$1<=Input!$F68),Input!$D68,0)*L$8 -> 0 | M43: =-IF(AND(M$1>=Input!$E68,M$1<=Input!$F68),Input!$D68,0)*M$8 -> 0 | N43: =-IF(AND(N$1>=Input!$E68,N$1<=Input!$F68),Input!$D68,0)*N$8 -> 0 | O43: =-IF(AND(O$1>=Input!$E68,O$1<=Input!$F68),Input!$D68,0)*O$8 -> 0 | P43: =-IF(AND(P$1>=Input!$E68,P$1<=Input!$F68),Input!$D68,0)*P$8 -> 0 | ... CN43: =-IF(AND(CN$1>=Input!$E68,CN$1<=Input!$F68),Input!$D68,0)*CN$8 -> 0
B44: 4.6. | C44: =Input!C69 | E44: =IFERROR(F44/(CF!$F$30+$F$38+$F$49+$F$57+$F$35),0) -> 0 | F44: =SUM(I44:CN44) -> 0 | G44: $ | I44: =-IF(AND(I$1>=Input!$E69,I$1<=Input!$F69),Input!$D69,0)*I$8 -> 0 | J44: =-IF(AND(J$1>=Input!$E69,J$1<=Input!$F69),Input!$D69,0)*J$8 -> 0 | K44: =-IF(AND(K$1>=Input!$E69,K$1<=Input!$F69),Input!$D69,0)*K$8 -> 0 | L44: =-IF(AND(L$1>=Input!$E69,L$1<=Input!$F69),Input!$D69,0)*L$8 -> 0 | M44: =-IF(AND(M$1>=Input!$E69,M$1<=Input!$F69),Input!$D69,0)*M$8 -> 0 | N44: =-IF(AND(N$1>=Input!$E69,N$1<=Input!$F69),Input!$D69,0)*N$8 -> 0 | O44: =-IF(AND(O$1>=Input!$E69,O$1<=Input!$F69),Input!$D69,0)*O$8 -> 0 | P44: =-IF(AND(P$1>=Input!$E69,P$1<=Input!$F69),Input!$D69,0)*P$8 -> 0 | ... CN44: =-IF(AND(CN$1>=Input!$E69,CN$1<=Input!$F69),Input!$D69,0)*CN$8 -> 0
B45: 4.7. | C45: =Input!C70 | E45: =IFERROR(F45/(CF!$F$30+$F$38+$F$49+$F$57+$F$35),0) -> 0 | F45: =SUM(I45:CN45) -> 0 | G45: $ | I45: =-IF(AND(I$1>=Input!$E70,I$1<=Input!$F70),Input!$D70,0)*I$8 -> 0 | J45: =-IF(AND(J$1>=Input!$E70,J$1<=Input!$F70),Input!$D70,0)*J$8 -> 0 | K45: =-IF(AND(K$1>=Input!$E70,K$1<=Input!$F70),Input!$D70,0)*K$8 -> 0 | L45: =-IF(AND(L$1>=Input!$E70,L$1<=Input!$F70),Input!$D70,0)*L$8 -> 0 | M45: =-IF(AND(M$1>=Input!$E70,M$1<=Input!$F70),Input!$D70,0)*M$8 -> 0 | N45: =-IF(AND(N$1>=Input!$E70,N$1<=Input!$F70),Input!$D70,0)*N$8 -> 0 | O45: =-IF(AND(O$1>=Input!$E70,O$1<=Input!$F70),Input!$D70,0)*O$8 -> 0 | P45: =-IF(AND(P$1>=Input!$E70,P$1<=Input!$F70),Input!$D70,0)*P$8 -> 0 | ... CN45: =-IF(AND(CN$1>=Input!$E70,CN$1<=Input!$F70),Input!$D70,0)*CN$8 -> 0
B46: 4.8. | C46: =Input!C71 | E46: =IFERROR(F46/(CF!$F$30+$F$38+$F$49+$F$57+$F$35),0) -> 0 | F46: =SUM(I46:CN46) -> 0 | G46: $ | I46: =-IF(AND(I$1>=Input!$E71,I$1<=Input!$F71),Input!$D71,0)*I$8 -> 0 | J46: =-IF(AND(J$1>=Input!$E71,J$1<=Input!$F71),Input!$D71,0)*J$8 -> 0 | K46: =-IF(AND(K$1>=Input!$E71,K$1<=Input!$F71),Input!$D71,0)*K$8 -> 0 | L46: =-IF(AND(L$1>=Input!$E71,L$1<=Input!$F71),Input!$D71,0)*L$8 -> 0 | M46: =-IF(AND(M$1>=Input!$E71,M$1<=Input!$F71),Input!$D71,0)*M$8 -> 0 | N46: =-IF(AND(N$1>=Input!$E71,N$1<=Input!$F71),Input!$D71,0)*N$8 -> 0 | O46: =-IF(AND(O$1>=Input!$E71,O$1<=Input!$F71),Input!$D71,0)*O$8 -> 0 | P46: =-IF(AND(P$1>=Input!$E71,P$1<=Input!$F71),Input!$D71,0)*P$8 -> 0 | ... CN46: =-IF(AND(CN$1>=Input!$E71,CN$1<=Input!$F71),Input!$D71,0)*CN$8 -> 0
B47: 4.9. | C47: =Input!C72 | E47: =IFERROR(F47/(CF!$F$30+$F$38+$F$49+$F$57+$F$35),0) -> 0 | F47: =SUM(I47:CN47) -> 0 | G47: $ | I47: =-IF(AND(I$1>=Input!$E72,I$1<=Input!$F72),Input!$D72,0)*I$8 -> 0 | J47: =-IF(AND(J$1>=Input!$E72,J$1<=Input!$F72),Input!$D72,0)*J$8 -> 0 | K47: =-IF(AND(K$1>=Input!$E72,K$1<=Input!$F72),Input!$D72,0)*K$8 -> 0 | L47: =-IF(AND(L$1>=Input!$E72,L$1<=Input!$F72),Input!$D72,0)*L$8 -> 0 | M47: =-IF(AND(M$1>=Input!$E72,M$1<=Input!$F72),Input!$D72,0)*M$8 -> 0 | N47: =-IF(AND(N$1>=Input!$E72,N$1<=Input!$F72),Input!$D72,0)*N$8 -> 0 | O47: =-IF(AND(O$1>=Input!$E72,O$1<=Input!$F72),Input!$D72,0)*O$8 -> 0 | P47: =-IF(AND(P$1>=Input!$E72,P$1<=Input!$F72),Input!$D72,0)*P$8 -> 0 | ... CN47: =-IF(AND(CN$1>=Input!$E72,CN$1<=Input!$F72),Input!$D72,0)*CN$8 -> 0
B48: 4.8. | C48: =Input!C73 | E48: =IFERROR(F48/(CF!$F$30+$F$38+$F$49+$F$57+$F$35),0) -> 0 | F48: =SUM(I48:CN48) -> 0 | G48: $ | I48: =-IF(AND(I$1>=Input!$E73,I$1<=Input!$F73),Input!$D73,0)*I$8 -> 0 | J48: =-IF(AND(J$1>=Input!$E73,J$1<=Input!$F73),Input!$D73,0)*J$8 -> 0 | K48: =-IF(AND(K$1>=Input!$E73,K$1<=Input!$F73),Input!$D73,0)*K$8 -> 0 | L48: =-IF(AND(L$1>=Input!$E73,L$1<=Input!$F73),Input!$D73,0)*L$8 -> 0 | M48: =-IF(AND(M$1>=Input!$E73,M$1<=Input!$F73),Input!$D73,0)*M$8 -> 0 | N48: =-IF(AND(N$1>=Input!$E73,N$1<=Input!$F73),Input!$D73,0)*N$8 -> 0 | O48: =-IF(AND(O$1>=Input!$E73,O$1<=Input!$F73),Input!$D73,0)*O$8 -> 0 | P48: =-IF(AND(P$1>=Input!$E73,P$1<=Input!$F73),Input!$D73,0)*P$8 -> 0 | ... CN48: =-IF(AND(CN$1>=Input!$E73,CN$1<=Input!$F73),Input!$D73,0)*CN$8 -> 0
B49: 5. | C49: =Input!C77 -> Other Variable Expenses | E49: =IFERROR(F49/(CF!$F$30+$F$38+$F$49+$F$57+$F$35),0) -> 0.0750721 | F49: =SUM(I49:CN49) -> -245896.84 | G49: $ | I49: =SUM(I50:I52,I53:I56) -> 0 | J49: =SUM(J50:J52,J53:J56) -> 0 | K49: =SUM(K50:K52,K53:K56) -> 0 | L49: =SUM(L50:L52,L53:L56) -> 0 | M49: =SUM(M50:M52,M53:M56) -> 0 | N49: =SUM(N50:N52,N53:N56) -> 0 | O49: =SUM(O50:O52,O53:O56) -> 0 | P49: =SUM(P50:P52,P53:P56) -> 0 | ... CN49: =SUM(CN50:CN52,CN53:CN56) -> -3621.3049
B50: 5.1. | C50: =Input!C80 -> Stores Commission | E50: =IFERROR(F50/(CF!$F$30+$F$38+$F$49+$F$57+$F$35),0) -> 0 | F50: =SUM(I50:CN50) -> 0 | G50: $ | I50: =CHOOSE(Input!$G80,-I$27*Input!$D80,-Input!$D80*I$2) -> 0 | J50: =CHOOSE(Input!$G80,-J$27*Input!$D80,-Input!$D80*J$2) -> 0 | K50: =CHOOSE(Input!$G80,-K$27*Input!$D80,-Input!$D80*K$2) -> 0 | L50: =CHOOSE(Input!$G80,-L$27*Input!$D80,-Input!$D80*L$2) -> 0 | M50: =CHOOSE(Input!$G80,-M$27*Input!$D80,-Input!$D80*M$2) -> 0 | N50: =CHOOSE(Input!$G80,-N$27*Input!$D80,-Input!$D80*N$2) -> 0 | O50: =CHOOSE(Input!$G80,-O$27*Input!$D80,-Input!$D80*O$2) -> 0 | P50: =CHOOSE(Input!$G80,-P$27*Input!$D80,-Input!$D80*P$2) -> 0 | ... CN50: =CHOOSE(Input!$G80,-CN$27*Input!$D80,-Input!$D80*CN$2) -> 0
B51: 5.2. | C51: =Input!C81 -> Bank's fee | E51: =IFERROR(F51/(CF!$F$30+$F$38+$F$49+$F$57+$F$35),0) -> 0.024002385 | F51: =SUM(I51:CN51) -> -78619.229 | G51: $ | I51: =CHOOSE(Input!$G81,-I$27*Input!$D81,-Input!$D81*I$2) -> 0 | J51: =CHOOSE(Input!$G81,-J$27*Input!$D81,-Input!$D81*J$2) -> 0 | K51: =CHOOSE(Input!$G81,-K$27*Input!$D81,-Input!$D81*K$2) -> 0 | L51: =CHOOSE(Input!$G81,-L$27*Input!$D81,-Input!$D81*L$2) -> 0 | M51: =CHOOSE(Input!$G81,-M$27*Input!$D81,-Input!$D81*M$2) -> 0 | N51: =CHOOSE(Input!$G81,-N$27*Input!$D81,-Input!$D81*N$2) -> 0 | O51: =CHOOSE(Input!$G81,-O$27*Input!$D81,-Input!$D81*O$2) -> 0 | P51: =CHOOSE(Input!$G81,-P$27*Input!$D81,-Input!$D81*P$2) -> 0 | ... CN51: =CHOOSE(Input!$G81,-CN$27*Input!$D81,-Input!$D81*CN$2) -> -1229.3144
B52: 5.3. | C52: =Input!C82 -> Other commissions | E52: =IFERROR(F52/(CF!$F$30+$F$38+$F$49+$F$57+$F$35),0) -> 0.012001192 | F52: =SUM(I52:CN52) -> -39309.615 | G52: $ | I52: =CHOOSE(Input!$G82,-I$27*Input!$D82,-Input!$D82*I$2) -> 0 | J52: =CHOOSE(Input!$G82,-J$27*Input!$D82,-Input!$D82*J$2) -> 0 | K52: =CHOOSE(Input!$G82,-K$27*Input!$D82,-Input!$D82*K$2) -> 0 | L52: =CHOOSE(Input!$G82,-L$27*Input!$D82,-Input!$D82*L$2) -> 0 | M52: =CHOOSE(Input!$G82,-M$27*Input!$D82,-Input!$D82*M$2) -> 0 | N52: =CHOOSE(Input!$G82,-N$27*Input!$D82,-Input!$D82*N$2) -> 0 | O52: =CHOOSE(Input!$G82,-O$27*Input!$D82,-Input!$D82*O$2) -> 0 | P52: =CHOOSE(Input!$G82,-P$27*Input!$D82,-Input!$D82*P$2) -> 0 | ... CN52: =CHOOSE(Input!$G82,-CN$27*Input!$D82,-Input!$D82*CN$2) -> -614.6572
B53: 5.4. | C53: =Input!C83 -> ChatGPT | E53: =IFERROR(F53/(CF!$F$30+$F$38+$F$49+$F$57+$F$35),0) -> 0.037808248 | F53: =SUM(I53:CN53) -> -123840 | G53: $ | I53: =CHOOSE(Input!$G83,-I$27*Input!$D83,-Input!$D83*I$2) -> 0 | J53: =CHOOSE(Input!$G83,-J$27*Input!$D83,-Input!$D83*J$2) -> 0 | K53: =CHOOSE(Input!$G83,-K$27*Input!$D83,-Input!$D83*K$2) -> 0 | L53: =CHOOSE(Input!$G83,-L$27*Input!$D83,-Input!$D83*L$2) -> 0 | M53: =CHOOSE(Input!$G83,-M$27*Input!$D83,-Input!$D83*M$2) -> 0 | N53: =CHOOSE(Input!$G83,-N$27*Input!$D83,-Input!$D83*N$2) -> 0 | O53: =CHOOSE(Input!$G83,-O$27*Input!$D83,-Input!$D83*O$2) -> 0 | P53: =CHOOSE(Input!$G83,-P$27*Input!$D83,-Input!$D83*P$2) -> 0 | ... CN53: =CHOOSE(Input!$G83,-CN$27*Input!$D83,-Input!$D83*CN$2) -> -1720
B54: 5.5. | C54: =Input!C84 -> Free user service | E54: =IFERROR(F54/(CF!$F$30+$F$38+$F$49+$F$57+$F$35),0) -> 0.0012602749 | F54: =SUM(I54:CN54) -> -4128 | G54: $ | I54: =CHOOSE(Input!$G84,-I$27*Input!$D84,-Input!$D84*I$2) -> 0 | J54: =CHOOSE(Input!$G84,-J$27*Input!$D84,-Input!$D84*J$2) -> 0 | K54: =CHOOSE(Input!$G84,-K$27*Input!$D84,-Input!$D84*K$2) -> 0 | L54: =CHOOSE(Input!$G84,-L$27*Input!$D84,-Input!$D84*L$2) -> 0 | M54: =CHOOSE(Input!$G84,-M$27*Input!$D84,-Input!$D84*M$2) -> 0 | N54: =CHOOSE(Input!$G84,-N$27*Input!$D84,-Input!$D84*N$2) -> 0 | O54: =CHOOSE(Input!$G84,-O$27*Input!$D84,-Input!$D84*O$2) -> 0 | P54: =CHOOSE(Input!$G84,-P$27*Input!$D84,-Input!$D84*P$2) -> 0 | ... CN54: =CHOOSE(Input!$G84,-CN$27*Input!$D84,-Input!$D84*CN$2) -> -57.333333
B55: 5.6. | C55: =Input!C85 | E55: =IFERROR(F55/(CF!$F$30+$F$38+$F$49+$F$57+$F$35),0) -> 0 | F55: =SUM(I55:CN55) -> 0 | G55: $ | I55: =CHOOSE(Input!$G85,-I$27*Input!$D85,-Input!$D85*I$2) -> 0 | J55: =CHOOSE(Input!$G85,-J$27*Input!$D85,-Input!$D85*J$2) -> 0 | K55: =CHOOSE(Input!$G85,-K$27*Input!$D85,-Input!$D85*K$2) -> 0 | L55: =CHOOSE(Input!$G85,-L$27*Input!$D85,-Input!$D85*L$2) -> 0 | M55: =CHOOSE(Input!$G85,-M$27*Input!$D85,-Input!$D85*M$2) -> 0 | N55: =CHOOSE(Input!$G85,-N$27*Input!$D85,-Input!$D85*N$2) -> 0 | O55: =CHOOSE(Input!$G85,-O$27*Input!$D85,-Input!$D85*O$2) -> 0 | P55: =CHOOSE(Input!$G85,-P$27*Input!$D85,-Input!$D85*P$2) -> 0 | ... CN55: =CHOOSE(Input!$G85,-CN$27*Input!$D85,-Input!$D85*CN$2) -> 0
B56: 5.7. | C56: =Input!C86 | E56: =IFERROR(F56/(CF!$F$30+$F$38+$F$49+$F$57+$F$35),0) -> 0 | F56: =SUM(I56:CN56) -> 0 | G56: $ | I56: =CHOOSE(Input!$G86,-I$27*Input!$D86,-Input!$D86*I$2) -> 0 | J56: =CHOOSE(Input!$G86,-J$27*Input!$D86,-Input!$D86*J$2) -> 0 | K56: =CHOOSE(Input!$G86,-K$27*Input!$D86,-Input!$D86*K$2) -> 0 | L56: =CHOOSE(Input!$G86,-L$27*Input!$D86,-Input!$D86*L$2) -> 0 | M56: =CHOOSE(Input!$G86,-M$27*Input!$D86,-Input!$D86*M$2) -> 0 | N56: =CHOOSE(Input!$G86,-N$27*Input!$D86,-Input!$D86*N$2) -> 0 | O56: =CHOOSE(Input!$G86,-O$27*Input!$D86,-Input!$D86*O$2) -> 0 | P56: =CHOOSE(Input!$G86,-P$27*Input!$D86,-Input!$D86*P$2) -> 0 | ... CN56: =CHOOSE(Input!$G86,-CN$27*Input!$D86,-Input!$D86*CN$2) -> 0
B57: 6. | C57: =Input!C111 -> Taxes | E57: =IFERROR(F57/(CF!$F$30+$F$38+$F$49+$F$57+$F$35),0) -> 0.23000066 | F57: =SUM(I57:CN57) -> -753361.58 | G57: $ | I57: =SUM(I58:I59) -> 0 | J57: =SUM(J58:J59) -> 0 | K57: =SUM(K58:K59) -> 0 | L57: =SUM(L58:L59) -> 0 | M57: =SUM(M58:M59) -> 0 | N57: =SUM(N58:N59) -> 0 | O57: =SUM(O58:O59) -> 0 | P57: =SUM(P58:P59) -> 0 | ... CN57: =SUM(CN58:CN59) -> -12065.517
B58: 6.1. | C58: =Input!C114 -> Income tax | E58: =IFERROR(F58/(CF!$F$30+$F$38+$F$49+$F$57+$F$35),0) -> 0.13774838 | F58: =SUM(I58:CN58) -> -451191.48 | G58: $ | I58: =Other!I119 -> 0 | J58: =Other!J119 -> 0 | K58: =Other!K119 -> 0 | L58: =Other!L119 -> 0 | M58: =Other!M119 -> 0 | N58: =Other!N119 -> 0 | O58: =Other!O119 -> 0 | P58: =Other!P119 -> 0 | ... CN58: =Other!CN119 -> -7299.8141
B59: 6.2. | C59: =Input!C115 -> VAT | E59: =IFERROR(F59/(CF!$F$30+$F$38+$F$49+$F$57+$F$35),0) -> 0.09225228 | F59: =SUM(I59:CN59) -> -302170.1 | G59: $ | I59: =Other!I110 -> 0 | J59: =Other!J110 -> 0 | K59: =Other!K110 -> 0 | L59: =Other!L110 -> 0 | M59: =Other!M110 -> 0 | N59: =Other!N110 -> 0 | O59: =Other!O110 -> 0 | P59: =Other!P110 -> 0 | ... CN59: =Other!CN110 -> -4765.703
C60: Total operational phase | F60: =SUM(I60:CN60) -> 4586447.1 | G60: $ | I60: =I57+I30+I27+I35+I38+I49 -> -10850 | J60: =J57+J30+J27+J35+J38+J49 -> -10850 | K60: =K57+K30+K27+K35+K38+K49 -> -10850 | L60: =L57+L30+L27+L35+L38+L49 -> -10850 | M60: =M57+M30+M27+M35+M38+M49 -> -10850 | N60: =N57+N30+N27+N35+N38+N49 -> -11950 | O60: =O57+O30+O27+O35+O38+O49 -> -11950 | P60: =P57+P30+P27+P35+P38+P49 -> -11950 | ... CN60: =CN57+CN30+CN27+CN35+CN38+CN49 -> 73809.232
B63: 3. | C63: Financial Phase
B65: 3.1. | C65: =Input!E91 -> Founders' funds | F65: =SUM(I65:CN65) -> 0 | G65: $ | I65: =sum(I66:I67) -> 9510 | J65: =sum(J66:J67) -> 9510 | K65: =sum(K66:K67) -> 9510 | L65: =sum(L66:L67) -> 9510 | M65: =sum(M66:M67) -> 9150 | N65: =sum(N66:N67) -> 7170 | O65: =sum(O66:O67) -> 7170 | P65: =sum(P66:P67) -> 7170 | ... CN65: =sum(CN66:CN67) -> -97380
C66: Contribution to the authorized capital | F66: =SUM(I66:CN66) -> 97380 | G66: $ | I66: =IF(I22+I60+H76<0,-(I22+I60+H76)*Input!$E$92,0) -> 9510 | J66: =IF(J22+J60+I76<0,-(J22+J60+I76)*Input!$E$92,0) -> 9510 | K66: =IF(K22+K60+J76<0,-(K22+K60+J76)*Input!$E$92,0) -> 9510 | L66: =IF(L22+L60+K76<0,-(L22+L60+K76)*Input!$E$92,0) -> 9510 | M66: =IF(M22+M60+L76<0,-(M22+M60+L76)*Input!$E$92,0) -> 9150 | N66: =IF(N22+N60+M76<0,-(N22+N60+M76)*Input!$E$92,0) -> 7170 | O66: =IF(O22+O60+N76<0,-(O22+O60+N76)*Input!$E$92,0) -> 7170 | P66: =IF(P22+P60+O76<0,-(P22+P60+O76)*Input!$E$92,0) -> 7170 | ... CN66: =IF(CN22+CN60+CM76<0,-(CN22+CN60+CM76)*Input!$E$92,0) -> 0
C67: Sale of share capital (at nominal value) | F67: =SUM(I67:CN67) -> -97380 | G67: $ | I67: =if(J$1=0,-$F66,0) -> 0 | J67: =if(K$1=0,-$F66,0) -> 0 | K67: =if(L$1=0,-$F66,0) -> 0 | L67: =if(M$1=0,-$F66,0) -> 0 | M67: =if(N$1=0,-$F66,0) -> 0 | N67: =if(O$1=0,-$F66,0) -> 0 | O67: =if(P$1=0,-$F66,0) -> 0 | P67: =if(Q$1=0,-$F66,0) -> 0 | ... CN67: =if(CO$1=0,-$F66,0) -> -97380
B68: 3.2. | C68: =Input!D91 -> Investor's funds | F68: =SUM(I68:CN68) -> 0 | G68: $ | I68: =sum(I69:I70) -> 6340 | J68: =sum(J69:J70) -> 6340 | K68: =sum(K69:K70) -> 6340 | L68: =sum(L69:L70) -> 6340 | M68: =sum(M69:M70) -> 6100 | N68: =sum(N69:N70) -> 4780 | O68: =sum(O69:O70) -> 4780 | P68: =sum(P69:P70) -> 4780 | ... CN68: =sum(CN69:CN70) -> -64920
C69: Contribution to the authorized capital | F69: =SUM(I69:CN69) -> 64920 | G69: $ | I69: =IF(I22+I60+H76<0,-(I22+I60+H76)*Input!$D$92,0) -> 6340 | J69: =IF(J22+J60+I76<0,-(J22+J60+I76)*Input!$D$92,0) -> 6340 | K69: =IF(K22+K60+J76<0,-(K22+K60+J76)*Input!$D$92,0) -> 6340 | L69: =IF(L22+L60+K76<0,-(L22+L60+K76)*Input!$D$92,0) -> 6340 | M69: =IF(M22+M60+L76<0,-(M22+M60+L76)*Input!$D$92,0) -> 6100 | N69: =IF(N22+N60+M76<0,-(N22+N60+M76)*Input!$D$92,0) -> 4780 | O69: =IF(O22+O60+N76<0,-(O22+O60+N76)*Input!$D$92,0) -> 4780 | P69: =IF(P22+P60+O76<0,-(P22+P60+O76)*Input!$D$92,0) -> 4780 | ... CN69: =IF(CN22+CN60+CM76<0,-(CN22+CN60+CM76)*Input!$D$92,0) -> 0
C70: Sale of share capital (at nominal value) | F70: =SUM(I70:CN70) -> -64920 | G70: $ | I70: =if(J$1=0,-$F69,0) -> 0 | J70: =if(K$1=0,-$F69,0) -> 0 | K70: =if(L$1=0,-$F69,0) -> 0 | L70: =if(M$1=0,-$F69,0) -> 0 | M70: =if(N$1=0,-$F69,0) -> 0 | N70: =if(O$1=0,-$F69,0) -> 0 | O70: =if(P$1=0,-$F69,0) -> 0 | P70: =if(Q$1=0,-$F69,0) -> 0 | ... CN70: =if(CO$1=0,-$F69,0) -> -64920
C71: Total financial phase | F71: =SUM(I71:CN71) -> 0 | G71: $ | I71: =I68+I65 -> 15850 | J71: =J68+J65 -> 15850 | K71: =K68+K65 -> 15850 | L71: =L68+L65 -> 15850 | M71: =M68+M65 -> 15250 | N71: =N68+N65 -> 11950 | O71: =O68+O65 -> 11950 | P71: =P68+P65 -> 11950 | ... CN71: =CN68+CN65 -> -162300
C73: Total turnover for the period | F73: =SUM(I73:CN73) -> 4562047.1 | G73: $ | I73: =IF(ROUND(I71+I60+I22,2)=0,0,I71+I60+I22) -> 0 | J73: =IF(ROUND(J71+J60+J22,2)=0,0,J71+J60+J22) -> 0 | K73: =IF(ROUND(K71+K60+K22,2)=0,0,K71+K60+K22) -> 0 | L73: =IF(ROUND(L71+L60+L22,2)=0,0,L71+L60+L22) -> 0 | M73: =IF(ROUND(M71+M60+M22,2)=0,0,M71+M60+M22) -> 0 | N73: =IF(ROUND(N71+N60+N22,2)=0,0,N71+N60+N22) -> 0 | O73: =IF(ROUND(O71+O60+O22,2)=0,0,O71+O60+O22) -> 0 | P73: =IF(ROUND(P71+P60+P22,2)=0,0,P71+P60+P22) -> 0 | ... CN73: =IF(ROUND(CN71+CN60+CN22,2)=0,0,CN71+CN60+CN22) -> -88490.768
C74: Selling a business | F74: =SUM(I74:CN74) -> 4781908.1 | G74: $ | U74: =IF(V1=0,SUM(PL!I45:T45)*Input!$D$132+U70,0) -> 0 | V74: =IF(W1=0,SUM(PL!J45:U45)*Input!$D$132+V70,0) -> 0 | W74: =IF(X1=0,SUM(PL!K45:V45)*Input!$D$132+W70,0) -> 0 | X74: =IF(Y1=0,SUM(PL!L45:W45)*Input!$D$132+X70,0) -> 0 | Y74: =IF(Z1=0,SUM(PL!M45:X45)*Input!$D$132+Y70,0) -> 0 | Z74: =IF(AA1=0,SUM(PL!N45:Y45)*Input!$D$132+Z70,0) -> 0 | AA74: =IF(AB1=0,SUM(PL!O45:Z45)*Input!$D$132+AA70,0) -> 0 | AB74: =IF(AC1=0,SUM(PL!P45:AA45)*Input!$D$132+AB70,0) -> 0 | ... CN74: =IF(CO1=0,SUM(PL!CB45:CM45)*Input!$D$132+CN70,0) -> 4781908.1
C75: Dividends | F75: =SUM(I75:CN75) -> -9343955.2 | G75: $ | I75: =PL!I57 -> 0 | J75: =PL!J57 -> 0 | K75: =PL!K57 -> 0 | L75: =PL!L57 -> 0 | M75: =PL!M57 -> 0 | N75: =PL!N57 -> 0 | O75: =PL!O57 -> 0 | P75: =PL!P57 -> 0 | ... CN75: =PL!CN57 -> -5947163
C76: Account balance | F76: =MIN(I76:CN76) -> 0 | G76: $ | I76: =IF(ROUND(I73+H76+I74+I75,0)=0,0,I73+H76+I74+I75) -> 0 | J76: =IF(ROUND(J73+I76+J74+J75,0)=0,0,J73+I76+J74+J75) -> 0 | K76: =IF(ROUND(K73+J76+K74+K75,0)=0,0,K73+J76+K74+K75) -> 0 | L76: =IF(ROUND(L73+K76+L74+L75,0)=0,0,L73+K76+L74+L75) -> 0 | M76: =IF(ROUND(M73+L76+M74+M75,0)=0,0,M73+L76+M74+M75) -> 0 | N76: =IF(ROUND(N73+M76+N74+N75,0)=0,0,N73+M76+N74+N75) -> 0 | O76: =IF(ROUND(O73+N76+O74+O75,0)=0,0,O73+N76+O74+O75) -> 0 | P76: =IF(ROUND(P73+O76+P74+P75,0)=0,0,P73+O76+P74+P75) -> 0 | ... CN76: =IF(ROUND(CN73+CM76+CN74+CN75,0)=0,0,CN73+CM76+CN74+CN75) -> 0

Sheet PL
A1: =BS!A1 -> Ok | B1: =CF!B1 -> № | C1: =CF!C1 -> Name | E1: =CF!E1 -> Share | F1: =CF!F1 -> Total | G1: =CF!G1 -> Unit | I1: =CF!I1 -> 46023 | J1: =CF!J1 -> 46054 | K1: =CF!K1 -> 46082 | L1: =CF!L1 -> 46113 | M1: =CF!M1 -> 46143 | N1: =CF!N1 -> 46174 | O1: =CF!O1 -> 46204 | P1: =CF!P1 -> 46235 | ... CN1: =CF!CN1 -> 48549
C2: =CF!C2 -> Sales volume, MAU | I2: =CF!I2 -> 0 | J2: =CF!J2 -> 0 | K2: =CF!K2 -> 0 | L2: =CF!L2 -> 0 | M2: =CF!M2 -> 0 | N2: =CF!N2 -> 0 | O2: =CF!O2 -> 0 | P2: =CF!P2 -> 0 | ... CN2: =CF!CN2 -> 229.33333
C3: =CF!C3 -> Year | I3: =CF!I3 -> 2026 | J3: =CF!J3 -> 2026 | K3: =CF!K3 -> 2026 | L3: =CF!L3 -> 2026 | M3: =CF!M3 -> 2026 | N3: =CF!N3 -> 2026 | O3: =CF!O3 -> 2026 | P3: =CF!P3 -> 2026 | ... CN3: =CF!CN3 -> 2032
C4: =CF!C4 -> Month | I4: =CF!I4 -> 1 | J4: =CF!J4 -> 2 | K4: =CF!K4 -> 3 | L4: =CF!L4 -> 4 | M4: =CF!M4 -> 5 | N4: =CF!N4 -> 6 | O4: =CF!O4 -> 7 | P4: =CF!P4 -> 8 | ... CN4: =CF!CN4 -> 12
C5: =CF!C5 -> Serial number of the period | I5: =CF!I5 -> 1 | J5: =CF!J5 -> 2 | K5: =CF!K5 -> 3 | L5: =CF!L5 -> 4 | M5: =CF!M5 -> 5 | N5: =CF!N5 -> 6 | O5: =CF!O5 -> 7 | P5: =CF!P5 -> 8 | ... CN5: =CF!CN5 -> 84
C6: =CF!C6 -> Indexation of production prices | I6: =CF!I6 -> 1 | J6: =CF!J6 -> 1 | K6: =CF!K6 -> 1 | L6: =CF!L6 -> 1 | M6: =CF!M6 -> 1 | N6: =CF!N6 -> 1 | O6: =CF!O6 -> 1 | P6: =CF!P6 -> 1 | ... CN6: =CF!CN6 -> 1.3400956
C7: =CF!C7 -> Payroll indexation | I7: =CF!I7 -> 1 | J7: =CF!J7 -> 1 | K7: =CF!K7 -> 1 | L7: =CF!L7 -> 1 | M7: =CF!M7 -> 1 | N7: =CF!N7 -> 1 | O7: =CF!O7 -> 1 | P7: =CF!P7 -> 1 | ... CN7: =CF!CN7 -> 1.3400956
C8: =CF!C8 -> Indexation of other expenses | I8: =CF!I8 -> 1 | J8: =CF!J8 -> 1 | K8: =CF!K8 -> 1 | L8: =CF!L8 -> 1 | M8: =CF!M8 -> 1 | N8: =CF!N8 -> 1 | O8: =CF!O8 -> 1 | P8: =CF!P8 -> 1 | ... CN8: =CF!CN8 -> 1.3400956
C9: =CF!C9 -> Sales price indexation | I9: =CF!I9 -> 1 | J9: =CF!J9 -> 1 | K9: =CF!K9 -> 1 | L9: =CF!L9 -> 1 | M9: =CF!M9 -> 1 | N9: =CF!N9 -> 1 | O9: =CF!O9 -> 1 | P9: =CF!P9 -> 1 | ... CN9: =CF!CN9 -> 1.3400956
C13: Profit and Loss Statement (PL)
B15: 1. | C15: Revenue | E15: =IFERROR(F15/$F$15,0) -> 1 | F15: =SUM(I15:CN15) -> 7487545.6 | G15: $ | I15: =SUM(I16) -> 0 | J15: =SUM(J16) -> 0 | K15: =SUM(K16) -> 0 | L15: =SUM(L16) -> 0 | M15: =SUM(M16) -> 0 | N15: =SUM(N16) -> 0 | O15: =SUM(O16) -> 0 | P15: =SUM(P16) -> 0 | ... CN15: =SUM(CN16) -> 117077.56
B16: 1.1. | C16: =CF!C28 -> Income — StepUP | E16: =IFERROR(F16/$F$15,0) -> 1 | F16: =SUM(I16:CN16) -> 7487545.6 | G16: $ | I16: =CF!I28/(1+Input!$D$115) -> 0 | J16: =CF!J28/(1+Input!$D$115) -> 0 | K16: =CF!K28/(1+Input!$D$115) -> 0 | L16: =CF!L28/(1+Input!$D$115) -> 0 | M16: =CF!M28/(1+Input!$D$115) -> 0 | N16: =CF!N28/(1+Input!$D$115) -> 0 | O16: =CF!O28/(1+Input!$D$115) -> 0 | P16: =CF!P28/(1+Input!$D$115) -> 0 | ... CN16: =CF!CN28/(1+Input!$D$115) -> 117077.56
B17: 2. | C17: =CF!C30 -> Direct costs (marketing and sales) | E17: =IFERROR(F17/($F$17+$F$23+$F$26+$F$37),0) -> 0.43291251 | F17: =SUM(I17:CN17) -> -1061098.4 | G17: $ | I17: =SUM(I18:I20) -> 0 | J17: =SUM(J18:J20) -> 0 | K17: =SUM(K18:K20) -> 0 | L17: =SUM(L18:L20) -> 0 | M17: =SUM(M18:M20) -> 0 | N17: =SUM(N18:N20) -> 0 | O17: =SUM(O18:O20) -> 0 | P17: =SUM(P18:P20) -> 0 | ... CN17: =SUM(CN18:CN20) -> -16591.66
B18: 2.1. | C18: =CF!C31 -> Advertising and marketing expenses | E18: =IFERROR(F18/($F$17+$F$23+$F$26+$F$37),0) -> 0.16650481 | F18: =SUM(I18:CN18) -> -408114.77 | G18: $ | I18: =CF!I31/(1+Input!$D$115) -> 0 | J18: =CF!J31/(1+Input!$D$115) -> 0 | K18: =CF!K31/(1+Input!$D$115) -> 0 | L18: =CF!L31/(1+Input!$D$115) -> 0 | M18: =CF!M31/(1+Input!$D$115) -> 0 | N18: =CF!N31/(1+Input!$D$115) -> 0 | O18: =CF!O31/(1+Input!$D$115) -> 0 | P18: =CF!P31/(1+Input!$D$115) -> 0 | ... CN18: =CF!CN31/(1+Input!$D$115) -> -6381.4078
B19: 2.2. | C19: =CF!C32 -> Salary (marketing and sales) | E19: =IFERROR(F19/($F$17+$F$23+$F$26+$F$37),0) -> 0.2664077 | F19: =SUM(I19:CN19) -> -652983.63 | G19: $ | I19: =CF!I32/(1+Input!$D$115) -> 0 | J19: =CF!J32/(1+Input!$D$115) -> 0 | K19: =CF!K32/(1+Input!$D$115) -> 0 | L19: =CF!L32/(1+Input!$D$115) -> 0 | M19: =CF!M32/(1+Input!$D$115) -> 0 | N19: =CF!N32/(1+Input!$D$115) -> 0 | O19: =CF!O32/(1+Input!$D$115) -> 0 | P19: =CF!P32/(1+Input!$D$115) -> 0 | ... CN19: =CF!CN32/(1+Input!$D$115) -> -10210.253
B20: 2.3. | C20: =CF!C33 -> Other marketing and advertising expenses | E20: =IFERROR(F20/($F$17+$F$23+$F$26+$F$37),0) -> 0 | F20: =SUM(I20:CN20) -> 0 | G20: $ | I20: =CF!I33/(1+Input!$D$115) -> 0 | J20: =CF!J33/(1+Input!$D$115) -> 0 | K20: =CF!K33/(1+Input!$D$115) -> 0 | L20: =CF!L33/(1+Input!$D$115) -> 0 | M20: =CF!M33/(1+Input!$D$115) -> 0 | N20: =CF!N33/(1+Input!$D$115) -> 0 | O20: =CF!O33/(1+Input!$D$115) -> 0 | P20: =CF!P33/(1+Input!$D$115) -> 0 | ... CN20: =CF!CN33/(1+Input!$D$115) -> 0
C21: Gross profit | F21: =SUM(I21:CN21) -> 6426447.2 | G21: $ | I21: =I17+I15 -> 0 | J21: =J17+J15 -> 0 | K21: =K17+K15 -> 0 | L21: =L17+L15 -> 0 | M21: =M17+M15 -> 0 | N21: =N17+N15 -> 0 | O21: =O17+O15 -> 0 | P21: =P17+P15 -> 0 | ... CN21: =CN17+CN15 -> 100485.9
C22: Return on sales | F22: =IFERROR(F21/F15,0) -> 0.85828488 | G22: % | I22: =IFERROR(I21/I15,0) -> 0 | J22: =IFERROR(J21/J15,0) -> 0 | K22: =IFERROR(K21/K15,0) -> 0 | L22: =IFERROR(L21/L15,0) -> 0 | M22: =IFERROR(M21/M15,0) -> 0 | N22: =IFERROR(N21/N15,0) -> 0 | O22: =IFERROR(O21/O15,0) -> 0 | P22: =IFERROR(P21/P15,0) -> 0 | ... CN22: =IFERROR(CN21/CN15,0) -> 0.85828488
B23: 3. | C23: =CF!C35 -> Payroll — admin and others | E23: =IFERROR(F23/($F$17+$F$23+$F$26+$F$37),0) -> 0.42029152 | F23: =SUM(I23:CN23) -> -1030163.5 | G23: $ | I23: =I25+I24 -> -9500 | J23: =J25+J24 -> -9500 | K23: =K25+K24 -> -9500 | L23: =L25+L24 -> -9500 | M23: =M25+M24 -> -9500 | N23: =N25+N24 -> -10600 | O23: =O25+O24 -> -10600 | P23: =P25+P24 -> -10600 | ... CN23: =CN25+CN24 -> -14205.014
B24: 3.1. | C24: =CF!C36 -> Salary (Gross) | E24: =IFERROR(F24/($F$17+$F$23+$F$26+$F$37),0) -> 0.42029152 | F24: =SUM(I24:CN24) -> -1030163.5 | G24: $ | I24: =CF!I36 -> -9500 | J24: =CF!J36 -> -9500 | K24: =CF!K36 -> -9500 | L24: =CF!L36 -> -9500 | M24: =CF!M36 -> -9500 | N24: =CF!N36 -> -10600 | O24: =CF!O36 -> -10600 | P24: =CF!P36 -> -10600 | ... CN24: =CF!CN36 -> -14205.014
B25: 3.2. | C25: =CF!C37 -> Additional taxes and insurance contributions for employees | E25: =IFERROR(F25/($F$17+$F$23+$F$26+$F$37),0) -> 0 | F25: =SUM(I25:CN25) -> 0 | G25: $ | I25: =CF!I37 -> 0 | J25: =CF!J37 -> 0 | K25: =CF!K37 -> 0 | L25: =CF!L37 -> 0 | M25: =CF!M37 -> 0 | N25: =CF!N37 -> 0 | O25: =CF!O37 -> 0 | P25: =CF!P37 -> 0 | ... CN25: =CF!CN37 -> 0
B26: 4. | C26: =CF!C38 -> Fixed Expenses | E26: =IFERROR(F26/($F$17+$F$23+$F$26+$F$37),0) -> 0.051250929 | F26: =SUM(I26:CN26) -> -125619.56 | G26: $ | I26: =SUM(I27:I36) -> -1285.7143 | J26: =SUM(J27:J36) -> -1285.7143 | K26: =SUM(K27:K36) -> -1285.7143 | L26: =SUM(L27:L36) -> -1285.7143 | M26: =SUM(M27:M36) -> -1285.7143 | N26: =SUM(N27:N36) -> -1285.7143 | O26: =SUM(O27:O36) -> -1285.7143 | P26: =SUM(P27:P36) -> -1285.7143 | ... CN26: =SUM(CN27:CN36) -> -1722.9801
B27: 4.1. | C27: =CF!C39 -> Servers | E27: =IFERROR(F27/($F$17+$F$23+$F$26+$F$37),0) -> 0.045556382 | F27: =SUM(I27:CN27) -> -111661.83 | G27: $ | I27: =CF!I39/(1+Input!$D$115) -> -1142.8571 | J27: =CF!J39/(1+Input!$D$115) -> -1142.8571 | K27: =CF!K39/(1+Input!$D$115) -> -1142.8571 | L27: =CF!L39/(1+Input!$D$115) -> -1142.8571 | M27: =CF!M39/(1+Input!$D$115) -> -1142.8571 | N27: =CF!N39/(1+Input!$D$115) -> -1142.8571 | O27: =CF!O39/(1+Input!$D$115) -> -1142.8571 | P27: =CF!P39/(1+Input!$D$115) -> -1142.8571 | ... CN27: =CF!CN39/(1+Input!$D$115) -> -1531.5379
B28: 4.2. | C28: =CF!C40 -> App analytics service | E28: =IFERROR(F28/($F$17+$F$23+$F$26+$F$37),0) -> 0.0056945477 | F28: =SUM(I28:CN28) -> -13957.729 | G28: $ | I28: =CF!I40/(1+Input!$D$115) -> -142.85714 | J28: =CF!J40/(1+Input!$D$115) -> -142.85714 | K28: =CF!K40/(1+Input!$D$115) -> -142.85714 | L28: =CF!L40/(1+Input!$D$115) -> -142.85714 | M28: =CF!M40/(1+Input!$D$115) -> -142.85714 | N28: =CF!N40/(1+Input!$D$115) -> -142.85714 | O28: =CF!O40/(1+Input!$D$115) -> -142.85714 | P28: =CF!P40/(1+Input!$D$115) -> -142.85714 | ... CN28: =CF!CN40/(1+Input!$D$115) -> -191.44223
B29: 4.3. | C29: =CF!C41 | E29: =IFERROR(F29/($F$17+$F$23+$F$26+$F$37),0) -> 0 | F29: =SUM(I29:CN29) -> 0 | G29: $ | I29: =CF!I41/(1+Input!$D$115) -> 0 | J29: =CF!J41/(1+Input!$D$115) -> 0 | K29: =CF!K41/(1+Input!$D$115) -> 0 | L29: =CF!L41/(1+Input!$D$115) -> 0 | M29: =CF!M41/(1+Input!$D$115) -> 0 | N29: =CF!N41/(1+Input!$D$115) -> 0 | O29: =CF!O41/(1+Input!$D$115) -> 0 | P29: =CF!P41/(1+Input!$D$115) -> 0 | ... CN29: =CF!CN41/(1+Input!$D$115) -> 0
B30: 4.4. | C30: =CF!C42 | E30: =IFERROR(F30/($F$17+$F$23+$F$26+$F$37),0) -> 0 | F30: =SUM(I30:CN30) -> 0 | G30: $ | I30: =CF!I42/(1+Input!$D$115) -> 0 | J30: =CF!J42/(1+Input!$D$115) -> 0 | K30: =CF!K42/(1+Input!$D$115) -> 0 | L30: =CF!L42/(1+Input!$D$115) -> 0 | M30: =CF!M42/(1+Input!$D$115) -> 0 | N30: =CF!N42/(1+Input!$D$115) -> 0 | O30: =CF!O42/(1+Input!$D$115) -> 0 | P30: =CF!P42/(1+Input!$D$115) -> 0 | ... CN30: =CF!CN42/(1+Input!$D$115) -> 0
B31: 4.5. | C31: =CF!C43 | E31: =IFERROR(F31/($F$17+$F$23+$F$26+$F$37),0) -> 0 | F31: =SUM(I31:CN31) -> 0 | G31: $ | I31: =CF!I43/(1+Input!$D$115) -> 0 | J31: =CF!J43/(1+Input!$D$115) -> 0 | K31: =CF!K43/(1+Input!$D$115) -> 0 | L31: =CF!L43/(1+Input!$D$115) -> 0 | M31: =CF!M43/(1+Input!$D$115) -> 0 | N31: =CF!N43/(1+Input!$D$115) -> 0 | O31: =CF!O43/(1+Input!$D$115) -> 0 | P31: =CF!P43/(1+Input!$D$115) -> 0 | ... CN31: =CF!CN43/(1+Input!$D$115) -> 0
B32: 4.6. | C32: =CF!C44 | E32: =IFERROR(F32/($F$17+$F$23+$F$26+$F$37),0) -> 0 | F32: =SUM(I32:CN32) -> 0 | G32: $ | I32: =CF!I44/(1+Input!$D$115) -> 0 | J32: =CF!J44/(1+Input!$D$115) -> 0 | K32: =CF!K44/(1+Input!$D$115) -> 0 | L32: =CF!L44/(1+Input!$D$115) -> 0 | M32: =CF!M44/(1+Input!$D$115) -> 0 | N32: =CF!N44/(1+Input!$D$115) -> 0 | O32: =CF!O44/(1+Input!$D$115) -> 0 | P32: =CF!P44/(1+Input!$D$115) -> 0 | ... CN32: =CF!CN44/(1+Input!$D$115) -> 0
B33: 4.7. | C33: =CF!C45 | E33: =IFERROR(F33/($F$17+$F$23+$F$26+$F$37),0) -> 0 | F33: =SUM(I33:CN33) -> 0 | G33: $ | I33: =CF!I45/(1+Input!$D$115) -> 0 | J33: =CF!J45/(1+Input!$D$115) -> 0 | K33: =CF!K45/(1+Input!$D$115) -> 0 | L33: =CF!L45/(1+Input!$D$115) -> 0 | M33: =CF!M45/(1+Input!$D$115) -> 0 | N33: =CF!N45/(1+Input!$D$115) -> 0 | O33: =CF!O45/(1+Input!$D$115) -> 0 | P33: =CF!P45/(1+Input!$D$115) -> 0 | ... CN33: =CF!CN45/(1+Input!$D$115) -> 0
B34: 4.8. | C34: =CF!C46 | E34: =IFERROR(F34/($F$17+$F$23+$F$26+$F$37),0) -> 0 | F34: =SUM(I34:CN34) -> 0 | G34: $ | I34: =CF!I46/(1+Input!$D$115) -> 0 | J34: =CF!J46/(1+Input!$D$115) -> 0 | K34: =CF!K46/(1+Input!$D$115) -> 0 | L34: =CF!L46/(1+Input!$D$115) -> 0 | M34: =CF!M46/(1+Input!$D$115) -> 0 | N34: =CF!N46/(1+Input!$D$115) -> 0 | O34: =CF!O46/(1+Input!$D$115) -> 0 | P34: =CF!P46/(1+Input!$D$115) -> 0 | ... CN34: =CF!CN46/(1+Input!$D$115) -> 0
B35: 4.9. | C35: =CF!C47 | E35: =IFERROR(F35/($F$17+$F$23+$F$26+$F$37),0) -> 0 | F35: =SUM(I35:CN35) -> 0 | G35: $ | I35: =CF!I47/(1+Input!$D$115) -> 0 | J35: =CF!J47/(1+Input!$D$115) -> 0 | K35: =CF!K47/(1+Input!$D$115) -> 0 | L35: =CF!L47/(1+Input!$D$115) -> 0 | M35: =CF!M47/(1+Input!$D$115) -> 0 | N35: =CF!N47/(1+Input!$D$115) -> 0 | O35: =CF!O47/(1+Input!$D$115) -> 0 | P35: =CF!P47/(1+Input!$D$115) -> 0 | ... CN35: =CF!CN47/(1+Input!$D$115) -> 0
B36: 4.10. | C36: =CF!C48 | E36: =IFERROR(F36/($F$17+$F$23+$F$26+$F$37),0) -> 0 | F36: =SUM(I36:CN36) -> 0 | G36: $ | I36: =CF!I48/(1+Input!$D$115) -> 0 | J36: =CF!J48/(1+Input!$D$115) -> 0 | K36: =CF!K48/(1+Input!$D$115) -> 0 | L36: =CF!L48/(1+Input!$D$115) -> 0 | M36: =CF!M48/(1+Input!$D$115) -> 0 | N36: =CF!N48/(1+Input!$D$115) -> 0 | O36: =CF!O48/(1+Input!$D$115) -> 0 | P36: =CF!P48/(1+Input!$D$115) -> 0 | ... CN36: =CF!CN48/(1+Input!$D$115) -> 0
B37: 5. | C37: =CF!C49 -> Other Variable Expenses | E37: =IFERROR(F37/($F$17+$F$23+$F$26+$F$37),0) -> 0.095545037 | F37: =SUM(I37:CN37) -> -234187.47 | G37: $ | I37: =SUM(I38:I44) -> 0 | J37: =SUM(J38:J44) -> 0 | K37: =SUM(K38:K44) -> 0 | L37: =SUM(L38:L44) -> 0 | M37: =SUM(M38:M44) -> 0 | N37: =SUM(N38:N44) -> 0 | O37: =SUM(O38:O44) -> 0 | P37: =SUM(P38:P44) -> 0 | ... CN37: =SUM(CN38:CN44) -> -3448.8618
B38: 5.1. | C38: =CF!C50 -> Stores Commission | E38: =IFERROR(F38/($F$17+$F$23+$F$26+$F$37),0) -> 0 | F38: =SUM(I38:CN38) -> 0 | G38: $ | I38: =CF!I50/(1+Input!$D$115) -> 0 | J38: =CF!J50/(1+Input!$D$115) -> 0 | K38: =CF!K50/(1+Input!$D$115) -> 0 | L38: =CF!L50/(1+Input!$D$115) -> 0 | M38: =CF!M50/(1+Input!$D$115) -> 0 | N38: =CF!N50/(1+Input!$D$115) -> 0 | O38: =CF!O50/(1+Input!$D$115) -> 0 | P38: =CF!P50/(1+Input!$D$115) -> 0 | ... CN38: =CF!CN50/(1+Input!$D$115) -> 0
B39: 5.2. | C39: =CF!C51 -> Bank's fee | E39: =IFERROR(F39/($F$17+$F$23+$F$26+$F$37),0) -> 0.030548083 | F39: =SUM(I39:CN39) -> -74875.456 | G39: $ | I39: =CF!I51/(1+Input!$D$115) -> 0 | J39: =CF!J51/(1+Input!$D$115) -> 0 | K39: =CF!K51/(1+Input!$D$115) -> 0 | L39: =CF!L51/(1+Input!$D$115) -> 0 | M39: =CF!M51/(1+Input!$D$115) -> 0 | N39: =CF!N51/(1+Input!$D$115) -> 0 | O39: =CF!O51/(1+Input!$D$115) -> 0 | P39: =CF!P51/(1+Input!$D$115) -> 0 | ... CN39: =CF!CN51/(1+Input!$D$115) -> -1170.7756
B40: 5.3. | C40: =CF!C52 -> Other commissions | E40: =IFERROR(F40/($F$17+$F$23+$F$26+$F$37),0) -> 0.015274041 | F40: =SUM(I40:CN40) -> -37437.728 | G40: $ | I40: =CF!I52/(1+Input!$D$115) -> 0 | J40: =CF!J52/(1+Input!$D$115) -> 0 | K40: =CF!K52/(1+Input!$D$115) -> 0 | L40: =CF!L52/(1+Input!$D$115) -> 0 | M40: =CF!M52/(1+Input!$D$115) -> 0 | N40: =CF!N52/(1+Input!$D$115) -> 0 | O40: =CF!O52/(1+Input!$D$115) -> 0 | P40: =CF!P52/(1+Input!$D$115) -> 0 | ... CN40: =CF!CN52/(1+Input!$D$115) -> -585.38781
B41: 5.4. | C41: =CF!C53 -> ChatGPT | E41: =IFERROR(F41/($F$17+$F$23+$F$26+$F$37),0) -> 0.048118948 | F41: =SUM(I41:CN41) -> -117942.86 | G41: $ | I41: =CF!I53/(1+Input!$D$115) -> 0 | J41: =CF!J53/(1+Input!$D$115) -> 0 | K41: =CF!K53/(1+Input!$D$115) -> 0 | L41: =CF!L53/(1+Input!$D$115) -> 0 | M41: =CF!M53/(1+Input!$D$115) -> 0 | N41: =CF!N53/(1+Input!$D$115) -> 0 | O41: =CF!O53/(1+Input!$D$115) -> 0 | P41: =CF!P53/(1+Input!$D$115) -> 0 | ... CN41: =CF!CN53/(1+Input!$D$115) -> -1638.0952
B42: 5.5. | C42: =CF!C54 -> Free user service | E42: =IFERROR(F42/($F$17+$F$23+$F$26+$F$37),0) -> 0.0016039649 | F42: =SUM(I42:CN42) -> -3931.4286 | G42: $ | I42: =CF!I54/(1+Input!$D$115) -> 0 | J42: =CF!J54/(1+Input!$D$115) -> 0 | K42: =CF!K54/(1+Input!$D$115) -> 0 | L42: =CF!L54/(1+Input!$D$115) -> 0 | M42: =CF!M54/(1+Input!$D$115) -> 0 | N42: =CF!N54/(1+Input!$D$115) -> 0 | O42: =CF!O54/(1+Input!$D$115) -> 0 | P42: =CF!P54/(1+Input!$D$115) -> 0 | ... CN42: =CF!CN54/(1+Input!$D$115) -> -54.603175
B43: 5.6. | C43: =CF!C55 | E43: =IFERROR(F43/($F$17+$F$23+$F$26+$F$37),0) -> 0 | F43: =SUM(I43:CN43) -> 0 | G43: $ | I43: =CF!I55/(1+Input!$D$115) -> 0 | J43: =CF!J55/(1+Input!$D$115) -> 0 | K43: =CF!K55/(1+Input!$D$115) -> 0 | L43: =CF!L55/(1+Input!$D$115) -> 0 | M43: =CF!M55/(1+Input!$D$115) -> 0 | N43: =CF!N55/(1+Input!$D$115) -> 0 | O43: =CF!O55/(1+Input!$D$115) -> 0 | P43: =CF!P55/(1+Input!$D$115) -> 0 | ... CN43: =CF!CN55/(1+Input!$D$115) -> 0
B44: 5.7. | C44: =CF!C56 | E44: =IFERROR(F44/($F$17+$F$23+$F$26+$F$37),0) -> 0 | F44: =SUM(I44:CN44) -> 0 | G44: $ | I44: =CF!I56/(1+Input!$D$115) -> 0 | J44: =CF!J56/(1+Input!$D$115) -> 0 | K44: =CF!K56/(1+Input!$D$115) -> 0 | L44: =CF!L56/(1+Input!$D$115) -> 0 | M44: =CF!M56/(1+Input!$D$115) -> 0 | N44: =CF!N56/(1+Input!$D$115) -> 0 | O44: =CF!O56/(1+Input!$D$115) -> 0 | P44: =CF!P56/(1+Input!$D$115) -> 0 | ... CN44: =CF!CN56/(1+Input!$D$115) -> 0
B45: 7. | C45: EBITDA | F45: =SUM(I45:CN45) -> 5036476.7 | G45: $ | I45: =I17+I15+I23+I26+I37 -> -10785.714 | J45: =J17+J15+J23+J26+J37 -> -10785.714 | K45: =K17+K15+K23+K26+K37 -> -10785.714 | L45: =L17+L15+L23+L26+L37 -> -10785.714 | M45: =M17+M15+M23+M26+M37 -> -10785.714 | N45: =N17+N15+N23+N26+N37 -> -11885.714 | O45: =O17+O15+O23+O26+O37 -> -11885.714 | P45: =P17+P15+P23+P26+P37 -> -11885.714 | ... CN45: =CN17+CN15+CN23+CN26+CN37 -> 81109.046
C46: EBITDA margin | F46: =IFERROR(F45/F15,0) -> 0.67264722 | G46: % | I46: =IFERROR(I45/I15,0) -> 0 | J46: =IFERROR(J45/J15,0) -> 0 | K46: =IFERROR(K45/K15,0) -> 0 | L46: =IFERROR(L45/L15,0) -> 0 | M46: =IFERROR(M45/M15,0) -> 0 | N46: =IFERROR(N45/N15,0) -> 0 | O46: =IFERROR(O45/O15,0) -> 0 | P46: =IFERROR(P45/P15,0) -> 0 | ... CN46: =IFERROR(CN45/CN15,0) -> 0.69278045
B47: 7.1. | C47: Depreciation | F47: =SUM(I47:CN47) -> -23238.095 | G47: $ | I47: =Other!I29 -> 0 | J47: =Other!J29 -> 0 | K47: =Other!K29 -> 0 | L47: =Other!L29 -> 0 | M47: =Other!M29 -> 0 | N47: =Other!N29 -> 0 | O47: =Other!O29 -> -387.30159 | P47: =Other!P29 -> -387.30159 | ... CN47: =Other!CN29 -> 0
B48: 8. | C48: EBIT | F48: =SUM(I48:CN48) -> 5013238.6 | G48: $ | I48: =I45+I47 -> -10785.714 | J48: =J45+J47 -> -10785.714 | K48: =K45+K47 -> -10785.714 | L48: =L45+L47 -> -10785.714 | M48: =M45+M47 -> -10785.714 | N48: =N45+N47 -> -11885.714 | O48: =O45+O47 -> -12273.016 | P48: =P45+P47 -> -12273.016 | ... CN48: =CN45+CN47 -> 81109.046
B49: 8.1. | C49: Interest receivable | F49: =SUM(I49:CN49) -> 0 | G49: $
B50: 8.2. | C50: Interest paid | F50: =SUM(I50:CN50) -> 0 | G50: $
B51: 9. | C51: Profit (loss) before tax | F51: =SUM(I51:CN51) -> 5013238.6 | G51: $ | I51: =SUM(I48:I50) -> -10785.714 | J51: =SUM(J48:J50) -> -10785.714 | K51: =SUM(K48:K50) -> -10785.714 | L51: =SUM(L48:L50) -> -10785.714 | M51: =SUM(M48:M50) -> -10785.714 | N51: =SUM(N48:N50) -> -11885.714 | O51: =SUM(O48:O50) -> -12273.016 | P51: =SUM(P48:P50) -> -12273.016 | ... CN51: =SUM(CN48:CN50) -> 81109.046
B52: 9.1. | C52: Income tax | F52: =SUM(I52:CN52) -> -451191.48 | G52: $ | I52: =Other!I119 -> 0 | J52: =Other!J119 -> 0 | K52: =Other!K119 -> 0 | L52: =Other!L119 -> 0 | M52: =Other!M119 -> 0 | N52: =Other!N119 -> 0 | O52: =Other!O119 -> 0 | P52: =Other!P119 -> 0 | ... CN52: =Other!CN119 -> -7299.8141
C53: Change in deferred tax liabilities | F53: =SUM(I53:CN53) -> 0 | G53: $
C54: Change in deferred tax assets | F54: =SUM(I54:CN54) -> 0 | G54: $ | I54: =Other!I121-Other!H121 -> 970.71429 | J54: =Other!J121-Other!I121 -> 970.71429 | K54: =Other!K121-Other!J121 -> 970.71429 | L54: =Other!L121-Other!K121 -> 970.71429 | M54: =Other!M121-Other!L121 -> 970.71429 | N54: =Other!N121-Other!M121 -> 1069.7143 | O54: =Other!O121-Other!N121 -> 1104.5714 | P54: =Other!P121-Other!O121 -> 1104.5714 | ... CN54: =Other!CN121-Other!CM121 -> 0
B55: 10. | C55: Net profit | F55: =SUM(I55:CN55) -> 4562047.1 | G55: $ | I55: =SUM(I51:I54) -> -9815 | J55: =SUM(J51:J54) -> -9815 | K55: =SUM(K51:K54) -> -9815 | L55: =SUM(L51:L54) -> -9815 | M55: =SUM(M51:M54) -> -9815 | N55: =SUM(N51:N54) -> -10816 | O55: =SUM(O51:O54) -> -11168.444 | P55: =SUM(P51:P54) -> -11168.444 | ... CN55: =SUM(CN51:CN54) -> 73809.232
B56: 11. | C56: Selling a business | F56: =SUM(I56:CN56) -> 4781908.1 | G56: $ | I56: =CF!I74 | J56: =CF!J74 | K56: =CF!K74 | L56: =CF!L74 | M56: =CF!M74 | N56: =CF!N74 | O56: =CF!O74 | P56: =CF!P74 | ... CN56: =CF!CN74 -> 4781908.1
B57: 12. | C57: Dividends | F57: =SUM(I57:CN57) -> -9343955.2 | G57: $ | I57: =IF(J$1=0,-PL!H58-PL!I56-PL!I55,IF(I$4=1,if(-(H58+I55+I56)*Input!$D$105>0,0,-(H58+I55+I56)*Input!$D$105),0)) -> 0 | J57: =IF(K$1=0,-PL!I58-PL!J56-PL!J55,IF(J$4=1,if(-(I58+J55+J56)*Input!$D$105>0,0,-(I58+J55+J56)*Input!$D$105),0)) -> 0 | K57: =IF(L$1=0,-PL!J58-PL!K56-PL!K55,IF(K$4=1,if(-(J58+K55+K56)*Input!$D$105>0,0,-(J58+K55+K56)*Input!$D$105),0)) -> 0 | L57: =IF(M$1=0,-PL!K58-PL!L56-PL!L55,IF(L$4=1,if(-(K58+L55+L56)*Input!$D$105>0,0,-(K58+L55+L56)*Input!$D$105),0)) -> 0 | M57: =IF(N$1=0,-PL!L58-PL!M56-PL!M55,IF(M$4=1,if(-(L58+M55+M56)*Input!$D$105>0,0,-(L58+M55+M56)*Input!$D$105),0)) -> 0 | N57: =IF(O$1=0,-PL!M58-PL!N56-PL!N55,IF(N$4=1,if(-(M58+N55+N56)*Input!$D$105>0,0,-(M58+N55+N56)*Input!$D$105),0)) -> 0 | O57: =IF(P$1=0,-PL!N58-PL!O56-PL!O55,IF(O$4=1,if(-(N58+O55+O56)*Input!$D$105>0,0,-(N58+O55+O56)*Input!$D$105),0)) -> 0 | P57: =IF(Q$1=0,-PL!O58-PL!P56-PL!P55,IF(P$4=1,if(-(O58+P55+P56)*Input!$D$105>0,0,-(O58+P55+P56)*Input!$D$105),0)) -> 0 | ... CN57: =IF(CO$1=0,-PL!CM58-PL!CN56-PL!CN55,IF(CN$4=1,if(-(CM58+CN55+CN56)*Input!$D$105>0,0,-(CM58+CN55+CN56)*Input!$D$105),0)) -> -5947163
B58: 13. | C58: Retained earnings | G58: $ | I58: =I55+H58+I56+I57 -> -9815 | J58: =J55+I58+J56+J57 -> -19630 | K58: =K55+J58+K56+K57 -> -29445 | L58: =L55+K58+L56+L57 -> -39260 | M58: =M55+L58+M56+M57 -> -49075 | N58: =N55+M58+N56+N57 -> -59891 | O58: =O55+N58+O56+O57 -> -71059.444 | P58: =P55+O58+P56+P57 -> -82227.889 | ... CN58: =CN55+CM58+CN56+CN57 -> 0
C59: Net profit margin | F59: =IFERROR(F55/F15,0) -> 0.60928472 | G59: % | I59: =IFERROR(I55/I15,0) -> 0 | J59: =IFERROR(J55/J15,0) -> 0 | K59: =IFERROR(K55/K15,0) -> 0 | L59: =IFERROR(L55/L15,0) -> 0 | M59: =IFERROR(M55/M15,0) -> 0 | N59: =IFERROR(N55/N15,0) -> 0 | O59: =IFERROR(O55/O15,0) -> 0 | P59: =IFERROR(P55/P15,0) -> 0 | ... CN59: =IFERROR(CN55/CN15,0) -> 0.63043021

Sheet BS
A1: =C48 -> Ok | B1: =CF!B1 -> № | C1: =CF!C1 -> Name | E1: =CF!E1 -> Share | F1: =CF!F1 -> Total | G1: =CF!G1 -> Unit | I1: =CF!I1 -> 46023 | J1: =CF!J1 -> 46054 | K1: =CF!K1 -> 46082 | L1: =CF!L1 -> 46113 | M1: =CF!M1 -> 46143 | N1: =CF!N1 -> 46174 | O1: =CF!O1 -> 46204 | P1: =CF!P1 -> 46235 | ... CN1: =CF!CN1 -> 48549
C2: =CF!C2 -> Sales volume, MAU | I2: =CF!I2 -> 0 | J2: =CF!J2 -> 0 | K2: =CF!K2 -> 0 | L2: =CF!L2 -> 0 | M2: =CF!M2 -> 0 | N2: =CF!N2 -> 0 | O2: =CF!O2 -> 0 | P2: =CF!P2 -> 0 | ... CN2: =CF!CN2 -> 229.33333
C3: =CF!C3 -> Year | I3: =CF!I3 -> 2026 | J3: =CF!J3 -> 2026 | K3: =CF!K3 -> 2026 | L3: =CF!L3 -> 2026 | M3: =CF!M3 -> 2026 | N3: =CF!N3 -> 2026 | O3: =CF!O3 -> 2026 | P3: =CF!P3 -> 2026 | ... CN3: =CF!CN3 -> 2032
C4: =CF!C4 -> Month | I4: =CF!I4 -> 1 | J4: =CF!J4 -> 2 | K4: =CF!K4 -> 3 | L4: =CF!L4 -> 4 | M4: =CF!M4 -> 5 | N4: =CF!N4 -> 6 | O4: =CF!O4 -> 7 | P4: =CF!P4 -> 8 | ... CN4: =CF!CN4 -> 12
C5: =CF!C5 -> Serial number of the period | I5: =CF!I5 -> 1 | J5: =CF!J5 -> 2 | K5: =CF!K5 -> 3 | L5: =CF!L5 -> 4 | M5: =CF!M5 -> 5 | N5: =CF!N5 -> 6 | O5: =CF!O5 -> 7 | P5: =CF!P5 -> 8 | ... CN5: =CF!CN5 -> 84
C6: =CF!C6 -> Indexation of production prices | I6: =CF!I6 -> 1 | J6: =CF!J6 -> 1 | K6: =CF!K6 -> 1 | L6: =CF!L6 -> 1 | M6: =CF!M6 -> 1 | N6: =CF!N6 -> 1 | O6: =CF!O6 -> 1 | P6: =CF!P6 -> 1 | ... CN6: =CF!CN6 -> 1.3400956
C7: =CF!C7 -> Payroll indexation | I7: =CF!I7 -> 1 | J7: =CF!J7 -> 1 | K7: =CF!K7 -> 1 | L7: =CF!L7 -> 1 | M7: =CF!M7 -> 1 | N7: =CF!N7 -> 1 | O7: =CF!O7 -> 1 | P7: =CF!P7 -> 1 | ... CN7: =CF!CN7 -> 1.3400956
C8: =CF!C8 -> Indexation of other expenses | I8: =CF!I8 -> 1 | J8: =CF!J8 -> 1 | K8: =CF!K8 -> 1 | L8: =CF!L8 -> 1 | M8: =CF!M8 -> 1 | N8: =CF!N8 -> 1 | O8: =CF!O8 -> 1 | P8: =CF!P8 -> 1 | ... CN8: =CF!CN8 -> 1.3400956
C9: =CF!C9 -> Sales price indexation | I9: =CF!I9 -> 1 | J9: =CF!J9 -> 1 | K9: =CF!K9 -> 1 | L9: =CF!L9 -> 1 | M9: =CF!M9 -> 1 | N9: =CF!N9 -> 1 | O9: =CF!O9 -> 1 | P9: =CF!P9 -> 1 | ... CN9: =CF!CN9 -> 1.3400956
C13: Balance Sheet (BS)
B15: 1. | C15: Assets
B17: 1 | C17: Fixed assets | G17: $ | I17: =SUM(I18:I23) -> 6035 | J17: =SUM(J18:J23) -> 12070 | K17: =SUM(K18:K23) -> 18105 | L17: =SUM(L18:L23) -> 24140 | M17: =SUM(M18:M23) -> 29575 | N17: =SUM(N18:N23) -> 30709 | O17: =SUM(O18:O23) -> 31490.556 | P17: =SUM(P18:P23) -> 32272.111 | ... CN17: =SUM(CN18:CN23) -> 0
B18: 1.1. | C18: Intangible assets | G18: $
B19: 1.2. | C19: Fixed assets | G19: $ | I19: =Other!I30 -> 0 | J19: =Other!J30 -> 0 | K19: =Other!K30 -> 0 | L19: =Other!L30 -> 0 | M19: =Other!M30 -> 0 | N19: =Other!N30 -> 23238.095 | O19: =Other!O30 -> 22850.794 | P19: =Other!P30 -> 22463.492 | ... CN19: =Other!CN30 -> 0
B20: 1.3. | C20: Unfinished production | G20: $ | I20: =Other!I27 -> 4761.9048 | J20: =Other!J27 -> 9523.8095 | K20: =Other!K27 -> 14285.714 | L20: =Other!L27 -> 19047.619 | M20: =Other!M27 -> 23238.095 | N20: =Other!N27 -> 0 | O20: =Other!O27 -> 0 | P20: =Other!P27 -> 0 | ... CN20: =Other!CN27 -> 0
B21: 1.4. | C21: Profitable investments in material assets | G21: $
B22: 1.5. | C22: Deferred tax assets (VAT) | G22: $ | I22: =Other!I112 -> 302.38095 | J22: =Other!J112 -> 604.7619 | K22: =Other!K112 -> 907.14286 | L22: =Other!L112 -> 1209.5238 | M22: =Other!M112 -> 1483.3333 | N22: =Other!N112 -> 1547.619 | O22: =Other!O112 -> 1611.9048 | P22: =Other!P112 -> 1676.1905 | ... CN22: =Other!CN112 -> 0
B23: 1.6. | C23: Deferred tax assets (income taxes) | G23: $ | I23: =Other!I121 -> 970.71429 | J23: =Other!J121 -> 1941.4286 | K23: =Other!K121 -> 2912.1429 | L23: =Other!L121 -> 3882.8571 | M23: =Other!M121 -> 4853.5714 | N23: =Other!N121 -> 5923.2857 | O23: =Other!O121 -> 7027.8571 | P23: =Other!P121 -> 8132.4286 | ... CN23: =Other!CN121 -> 0
B24: 2 | C24: Current assets | G24: $ | I24: =SUM(I25:I28) -> 0 | J24: =SUM(J25:J28) -> 0 | K24: =SUM(K25:K28) -> 0 | L24: =SUM(L25:L28) -> 0 | M24: =SUM(M25:M28) -> 0 | N24: =SUM(N25:N28) -> 0 | O24: =SUM(O25:O28) -> 0 | P24: =SUM(P25:P28) -> 0 | ... CN24: =SUM(CN25:CN28) -> 0
B25: 2.1. | C25: Reserves | G25: $
B26: 2.2. | C26: Advances received | G26: $
B27: 2.3. | C27: Cash | G27: $ | I27: =CF!I76 -> 0 | J27: =CF!J76 -> 0 | K27: =CF!K76 -> 0 | L27: =CF!L76 -> 0 | M27: =CF!M76 -> 0 | N27: =CF!N76 -> 0 | O27: =CF!O76 -> 0 | P27: =CF!P76 -> 0 | ... CN27: =CF!CN76 -> 0
B28: 2.4. | C28: Other current assets | G28: $
C29: Total assets | G29: $ | I29: =I24+I17 -> 6035 | J29: =J24+J17 -> 12070 | K29: =K24+K17 -> 18105 | L29: =L24+L17 -> 24140 | M29: =M24+M17 -> 29575 | N29: =N24+N17 -> 30709 | O29: =O24+O17 -> 31490.556 | P29: =P24+P17 -> 32272.111 | ... CN29: =CN24+CN17 -> 0
B32: 2. | C32: Liabilities
B34: 3 | C34: Capital and reserves | G34: $ | I34: =I35+I38 -> 6035 | J34: =J35+J38 -> 12070 | K34: =K35+K38 -> 18105 | L34: =L35+L38 -> 24140 | M34: =M35+M38 -> 29575 | N34: =N35+N38 -> 30709 | O34: =O35+O38 -> 31490.556 | P34: =P35+P38 -> 32272.111 | ... CN34: =CN35+CN38 -> 0
B35: 3.1. | C35: Authorized capital | G35: $ | I35: =sum(I36:I37) -> 15850 | J35: =sum(J36:J37) -> 31700 | K35: =sum(K36:K37) -> 47550 | L35: =sum(L36:L37) -> 63400 | M35: =sum(M36:M37) -> 78650 | N35: =sum(N36:N37) -> 90600 | O35: =sum(O36:O37) -> 102550 | P35: =sum(P36:P37) -> 114500 | ... CN35: =sum(CN36:CN37) -> 0
B36: 3.1.1. | C36: =CF!C65 -> Founders' funds | G36: $ | I36: =sum(CF!$H65:I65) -> 9510 | J36: =sum(CF!$H65:J65) -> 19020 | K36: =sum(CF!$H65:K65) -> 28530 | L36: =sum(CF!$H65:L65) -> 38040 | M36: =sum(CF!$H65:M65) -> 47190 | N36: =sum(CF!$H65:N65) -> 54360 | O36: =sum(CF!$H65:O65) -> 61530 | P36: =sum(CF!$H65:P65) -> 68700 | ... CN36: =sum(CF!$H65:CN65) -> 0
B37: 3.1.2. | C37: =CF!C68 -> Investor's funds | G37: $ | I37: =sum(CF!$H68:I68) -> 6340 | J37: =sum(CF!$H68:J68) -> 12680 | K37: =sum(CF!$H68:K68) -> 19020 | L37: =sum(CF!$H68:L68) -> 25360 | M37: =sum(CF!$H68:M68) -> 31460 | N37: =sum(CF!$H68:N68) -> 36240 | O37: =sum(CF!$H68:O68) -> 41020 | P37: =sum(CF!$H68:P68) -> 45800 | ... CN37: =sum(CF!$H68:CN68) -> 0
B38: 3.2. | C38: Retained earnings (uncovered loss) | G38: $ | I38: =PL!I58 -> -9815 | J38: =PL!J58 -> -19630 | K38: =PL!K58 -> -29445 | L38: =PL!L58 -> -39260 | M38: =PL!M58 -> -49075 | N38: =PL!N58 -> -59891 | O38: =PL!O58 -> -71059.444 | P38: =PL!P58 -> -82227.889 | ... CN38: =PL!CN58 -> 0
B39: 4 | C39: Long-term liabilities | G39: $ | I39: =SUM(I40:I42) -> 0 | J39: =SUM(J40:J42) -> 0 | K39: =SUM(K40:K42) -> 0 | L39: =SUM(L40:L42) -> 0 | M39: =SUM(M40:M42) -> 0 | N39: =SUM(N40:N42) -> 0 | O39: =SUM(O40:O42) -> 0 | P39: =SUM(P40:P42) -> 0 | ... CN39: =SUM(CN40:CN42) -> 0
B40: 4.1. | C40: Loans received (bank) | G40: $
B41: 4.2. | C41: Loans received (investors) | G41: $
B42: 4.3. | C42: Deferred tax liabilities | G42: $
B43: 5 | C43: Short-term liabilities | G43: $ | I43: =SUM(I44:I46) -> 0 | J43: =SUM(J44:J46) -> 0 | K43: =SUM(K44:K46) -> 0 | L43: =SUM(L44:L46) -> 0 | M43: =SUM(M44:M46) -> 0 | N43: =SUM(N44:N46) -> 0 | O43: =SUM(O44:O46) -> 0 | P43: =SUM(P44:P46) -> 0 | ... CN43: =SUM(CN44:CN46) -> 0
B44: 5.1. | C44: Accounts payable | G44: $
B45: 5.2. | C45: Interest debt | G45: $
B46: 5.3. | C46: Loans received | G46: $
C47: Total Liabilities | G47: $ | I47: =I43+I39+I34 -> 6035 | J47: =J43+J39+J34 -> 12070 | K47: =K43+K39+K34 -> 18105 | L47: =L43+L39+L34 -> 24140 | M47: =M43+M39+M34 -> 29575 | N47: =N43+N39+N34 -> 30709 | O47: =O43+O39+O34 -> 31490.556 | P47: =P43+P39+P34 -> 32272.111 | ... CN47: =CN43+CN39+CN34 -> 0
C48: =IF(SUM(I48:CN48)=0,"Ok","Fls") -> Ok | I48: =IF(ROUND(I47-I29,0)=0,0,I47-I29) -> 0 | J48: =IF(ROUND(J47-J29,0)=0,0,J47-J29) -> 0 | K48: =IF(ROUND(K47-K29,0)=0,0,K47-K29) -> 0 | L48: =IF(ROUND(L47-L29,0)=0,0,L47-L29) -> 0 | M48: =IF(ROUND(M47-M29,0)=0,0,M47-M29) -> 0 | N48: =IF(ROUND(N47-N29,0)=0,0,N47-N29) -> 0 | O48: =IF(ROUND(O47-O29,0)=0,0,O47-O29) -> 0 | P48: =IF(ROUND(P47-P29,0)=0,0,P47-P29) -> 0 | ... CN48: =IF(ROUND(CN47-CN29,0)=0,0,CN47-CN29) -> 0

Sheet Invest
A1: =BS!A1 -> Ok | B1: =CF!B1 -> № | C1: =CF!C1 -> Name | E1: =CF!E1 -> Share | F1: =CF!F1 -> Total | G1: =CF!G1 -> Unit | I1: =CF!I1 -> 46023 | J1: =CF!J1 -> 46054 | K1: =CF!K1 -> 46082 | L1: =CF!L1 -> 46113 | M1: =CF!M1 -> 46143 | N1: =CF!N1 -> 46174 | O1: =CF!O1 -> 46204 | P1: =CF!P1 -> 46235 | ... CN1: =CF!CN1 -> 48549
C2: =CF!C2 -> Sales volume, MAU | I2: =CF!I2 -> 0 | J2: =CF!J2 -> 0 | K2: =CF!K2 -> 0 | L2: =CF!L2 -> 0 | M2: =CF!M2 -> 0 | N2: =CF!N2 -> 0 | O2: =CF!O2 -> 0 | P2: =CF!P2 -> 0 | ... CN2: =CF!CN2 -> 229.33333
C3: =CF!C3 -> Year | I3: =CF!I3 -> 2026 | J3: =CF!J3 -> 2026 | K3: =CF!K3 -> 2026 | L3: =CF!L3 -> 2026 | M3: =CF!M3 -> 2026 | N3: =CF!N3 -> 2026 | O3: =CF!O3 -> 2026 | P3: =CF!P3 -> 2026 | ... CN3: =CF!CN3 -> 2032
C4: =CF!C4 -> Month | I4: =CF!I4 -> 1 | J4: =CF!J4 -> 2 | K4: =CF!K4 -> 3 | L4: =CF!L4 -> 4 | M4: =CF!M4 -> 5 | N4: =CF!N4 -> 6 | O4: =CF!O4 -> 7 | P4: =CF!P4 -> 8 | ... CN4: =CF!CN4 -> 12
C5: =CF!C5 -> Serial number of the period | I5: =CF!I5 -> 1 | J5: =CF!J5 -> 2 | K5: =CF!K5 -> 3 | L5: =CF!L5 -> 4 | M5: =CF!M5 -> 5 | N5: =CF!N5 -> 6 | O5: =CF!O5 -> 7 | P5: =CF!P5 -> 8 | ... CN5: =CF!CN5 -> 84
C6: =CF!C6 -> Indexation of production prices | I6: =CF!I6 -> 1 | J6: =CF!J6 -> 1 | K6: =CF!K6 -> 1 | L6: =CF!L6 -> 1 | M6: =CF!M6 -> 1 | N6: =CF!N6 -> 1 | O6: =CF!O6 -> 1 | P6: =CF!P6 -> 1 | ... CN6: =CF!CN6 -> 1.3400956
C7: =CF!C7 -> Payroll indexation | I7: =CF!I7 -> 1 | J7: =CF!J7 -> 1 | K7: =CF!K7 -> 1 | L7: =CF!L7 -> 1 | M7: =CF!M7 -> 1 | N7: =CF!N7 -> 1 | O7: =CF!O7 -> 1 | P7: =CF!P7 -> 1 | ... CN7: =CF!CN7 -> 1.3400956
C8: =CF!C8 -> Indexation of other expenses | I8: =CF!I8 -> 1 | J8: =CF!J8 -> 1 | K8: =CF!K8 -> 1 | L8: =CF!L8 -> 1 | M8: =CF!M8 -> 1 | N8: =CF!N8 -> 1 | O8: =CF!O8 -> 1 | P8: =CF!P8 -> 1 | ... CN8: =CF!CN8 -> 1.3400956
C9: =CF!C9 -> Sales price indexation | I9: =CF!I9 -> 1 | J9: =CF!J9 -> 1 | K9: =CF!K9 -> 1 | L9: =CF!L9 -> 1 | M9: =CF!M9 -> 1 | N9: =CF!N9 -> 1 | O9: =CF!O9 -> 1 | P9: =CF!P9 -> 1 | ... CN9: =CF!CN9 -> 1.3400956
C11: Investment indicators
B13: 1 | C13: Profitability
B15: 1. | C15: ROA (return on assets) | G15: % | I15: =IFERROR(I16/I17,0) -> -1.6263463 | J15: =IFERROR(J16/J17,0) -> -0.81317316 | K15: =IFERROR(K16/K17,0) -> -0.54211544 | L15: =IFERROR(L16/L17,0) -> -0.40658658 | M15: =IFERROR(M16/M17,0) -> -0.33186813 | N15: =IFERROR(N16/N17,0) -> -0.35220945 | O15: =IFERROR(O16/O17,0) -> -0.35466013 | P15: =IFERROR(P16/P17,0) -> -0.34607108 | ... CN15: =IFERROR(CN16/CN17,0) -> 0
C16: Net profit | F16: =PL!F55 -> 4562047.1 | G16: $ | I16: =PL!I55 -> -9815 | J16: =PL!J55 -> -9815 | K16: =PL!K55 -> -9815 | L16: =PL!L55 -> -9815 | M16: =PL!M55 -> -9815 | N16: =PL!N55 -> -10816 | O16: =PL!O55 -> -11168.444 | P16: =PL!P55 -> -11168.444 | ... CN16: =PL!CN55 -> 73809.232
C17: Assets | G17: =G16 -> $ | I17: =BS!I29 -> 6035 | J17: =BS!J29 -> 12070 | K17: =BS!K29 -> 18105 | L17: =BS!L29 -> 24140 | M17: =BS!M29 -> 29575 | N17: =BS!N29 -> 30709 | O17: =BS!O29 -> 31490.556 | P17: =BS!P29 -> 32272.111 | ... CN17: =BS!CN29 -> 0
B18: 2. | C18: ROE (return on equity) | G18: =G15 -> % | I18: =IFERROR(I19/I20,0) -> -1.6263463 | J18: =IFERROR(J19/J20,0) -> -0.81317316 | K18: =IFERROR(K19/K20,0) -> -0.54211544 | L18: =IFERROR(L19/L20,0) -> -0.40658658 | M18: =IFERROR(M19/M20,0) -> -0.33186813 | N18: =IFERROR(N19/N20,0) -> -0.35220945 | O18: =IFERROR(O19/O20,0) -> -0.35466013 | P18: =IFERROR(P19/P20,0) -> -0.34607108 | ... CN18: =IFERROR(CN19/CN20,0) -> 0
C19: Net profit | F19: =F16 -> 4562047.1 | G19: =G16 -> $ | I19: =I16 -> -9815 | J19: =J16 -> -9815 | K19: =K16 -> -9815 | L19: =L16 -> -9815 | M19: =M16 -> -9815 | N19: =N16 -> -10816 | O19: =O16 -> -11168.444 | P19: =P16 -> -11168.444 | ... CN19: =CN16 -> 73809.232
C20: Equity | G20: =G17 -> $ | I20: =BS!I34 -> 6035 | J20: =BS!J34 -> 12070 | K20: =BS!K34 -> 18105 | L20: =BS!L34 -> 24140 | M20: =BS!M34 -> 29575 | N20: =BS!N34 -> 30709 | O20: =BS!O34 -> 31490.556 | P20: =BS!P34 -> 32272.111 | ... CN20: =BS!CN34 -> 0
B21: 3. | C21: ROS (return on sales) | F21: =IFERROR(F22/F23,0) -> 0.85828488 | G21: =G18 -> % | I21: =IFERROR(I22/I23,0) -> 0 | J21: =IFERROR(J22/J23,0) -> 0 | K21: =IFERROR(K22/K23,0) -> 0 | L21: =IFERROR(L22/L23,0) -> 0 | M21: =IFERROR(M22/M23,0) -> 0 | N21: =IFERROR(N22/N23,0) -> 0 | O21: =IFERROR(O22/O23,0) -> 0 | P21: =IFERROR(P22/P23,0) -> 0 | ... CN21: =IFERROR(CN22/CN23,0) -> 0.85828488
C22: =PL!C21 -> Gross profit | F22: =PL!F21 -> 6426447.2 | G22: =G19 -> $ | I22: =PL!I21 -> 0 | J22: =PL!J21 -> 0 | K22: =PL!K21 -> 0 | L22: =PL!L21 -> 0 | M22: =PL!M21 -> 0 | N22: =PL!N21 -> 0 | O22: =PL!O21 -> 0 | P22: =PL!P21 -> 0 | ... CN22: =PL!CN21 -> 100485.9
C23: Revenue | F23: =PL!F15 -> 7487545.6 | G23: =G20 -> $ | I23: =PL!I15 -> 0 | J23: =PL!J15 -> 0 | K23: =PL!K15 -> 0 | L23: =PL!L15 -> 0 | M23: =PL!M15 -> 0 | N23: =PL!N15 -> 0 | O23: =PL!O15 -> 0 | P23: =PL!P15 -> 0 | ... CN23: =PL!CN15 -> 117077.56
B27: 2 | C27: Break-even Point
B29: 2.1. | C29: By month
B31: 1. | C31: Sales volume, units/month | F31: =SUM(I31:CN31) -> 16512 | G31: un./month | I31: =I2 -> 0 | J31: =J2 -> 0 | K31: =K2 -> 0 | L31: =L2 -> 0 | M31: =M2 -> 0 | N31: =N2 -> 0 | O31: =O2 -> 0 | P31: =P2 -> 0 | ... CN31: =CN2 -> 229.33333
B32: 2. | C32: Revenue | F32: =SUM(I32:CN32) -> 7487545.6 | G32: =G22 -> $ | I32: =PL!I15 -> 0 | J32: =PL!J15 -> 0 | K32: =PL!K15 -> 0 | L32: =PL!L15 -> 0 | M32: =PL!M15 -> 0 | N32: =PL!N15 -> 0 | O32: =PL!O15 -> 0 | P32: =PL!P15 -> 0 | ... CN32: =PL!CN15 -> 117077.56
B33: 3. | C33: Direct costs | F33: =SUM(I33:CN33) -> -1061098.4 | G33: =G32 -> $ | I33: =PL!I17 -> 0 | J33: =PL!J17 -> 0 | K33: =PL!K17 -> 0 | L33: =PL!L17 -> 0 | M33: =PL!M17 -> 0 | N33: =PL!N17 -> 0 | O33: =PL!O17 -> 0 | P33: =PL!P17 -> 0 | ... CN33: =PL!CN17 -> -16591.66
B34: 4. | C34: Gross profit | F34: =SUM(I34:CN34) -> 6426447.2 | G34: =G33 -> $ | I34: =I32+I33 -> 0 | J34: =J32+J33 -> 0 | K34: =K32+K33 -> 0 | L34: =L32+L33 -> 0 | M34: =M32+M33 -> 0 | N34: =N32+N33 -> 0 | O34: =O32+O33 -> 0 | P34: =P32+P33 -> 0 | ... CN34: =CN32+CN33 -> 100485.9
B35: 5. | C35: Indirect costs | F35: =SUM(I35:CN35) -> -1389970.5 | G35: =G34 -> $ | I35: =PL!I23+PL!I26+PL!I37 -> -10785.714 | J35: =PL!J23+PL!J26+PL!J37 -> -10785.714 | K35: =PL!K23+PL!K26+PL!K37 -> -10785.714 | L35: =PL!L23+PL!L26+PL!L37 -> -10785.714 | M35: =PL!M23+PL!M26+PL!M37 -> -10785.714 | N35: =PL!N23+PL!N26+PL!N37 -> -11885.714 | O35: =PL!O23+PL!O26+PL!O37 -> -11885.714 | P35: =PL!P23+PL!P26+PL!P37 -> -11885.714 | ... CN35: =PL!CN23+PL!CN26+PL!CN37 -> -19376.856
C36: Break even point | F36: =AVERAGEIF(I36:CN36,">0",I36:CN36) -> 44.739029 | G36: un./month | I36: =IFERROR(-I35/(I34/I31),0) -> 0 | J36: =IFERROR(-J35/(J34/J31),0) -> 0 | K36: =IFERROR(-K35/(K34/K31),0) -> 0 | L36: =IFERROR(-L35/(L34/L31),0) -> 0 | M36: =IFERROR(-M35/(M34/M31),0) -> 0 | N36: =IFERROR(-N35/(N34/N31),0) -> 0 | O36: =IFERROR(-O35/(O34/O31),0) -> 0 | P36: =IFERROR(-P35/(P34/P31),0) -> 0 | ... CN36: =IFERROR(-CN35/(CN34/CN31),0) -> 44.22271
B39: 2.2. | C39: By year
C41: By year | I41: =YEAR(I1) -> 2026 | J41: =I41+1 -> 2027 | K41: =J41+1 -> 2028 | L41: =K41+1 -> 2029 | M41: =L41+1 -> 2030 | N41: =M41+1 -> 2031 | O41: =N41+1 -> 2032
B42: 1. | C42: Sales volume, units/year | F42: =SUM(I42:CN42) -> 16512 | G42: units/year | I42: =SUMIFS(31:31,$3:$3,I$41) -> 0 | J42: =SUMIFS(31:31,$3:$3,J$41) -> 2752 | K42: =SUMIFS(31:31,$3:$3,K$41) -> 2752 | L42: =SUMIFS(31:31,$3:$3,L$41) -> 2752 | M42: =SUMIFS(31:31,$3:$3,M$41) -> 2752 | N42: =SUMIFS(31:31,$3:$3,N$41) -> 2752 | O42: =SUMIFS(31:31,$3:$3,O$41) -> 2752
B43: 2. | C43: Revenue | F43: =SUM(I43:CN43) -> 7487545.6 | G43: =G32 -> $ | I43: =SUMIFS(32:32,$3:$3,I$41) -> 0 | J43: =SUMIFS(32:32,$3:$3,J$41) -> 1100800 | K43: =SUMIFS(32:32,$3:$3,K$41) -> 1155840 | L43: =SUMIFS(32:32,$3:$3,L$41) -> 1213632 | M43: =SUMIFS(32:32,$3:$3,M$41) -> 1274313.6 | N43: =SUMIFS(32:32,$3:$3,N$41) -> 1338029.3 | O43: =SUMIFS(32:32,$3:$3,O$41) -> 1404930.7
B44: 3. | C44: Direct costs | F44: =SUM(I44:CN44) -> -1061098.4 | G44: =G33 -> $ | I44: =SUMIFS(33:33,$3:$3,I$41) -> 0 | J44: =SUMIFS(33:33,$3:$3,J$41) -> -156000 | K44: =SUMIFS(33:33,$3:$3,K$41) -> -163800 | L44: =SUMIFS(33:33,$3:$3,L$41) -> -171990 | M44: =SUMIFS(33:33,$3:$3,M$41) -> -180589.5 | N44: =SUMIFS(33:33,$3:$3,N$41) -> -189618.98 | O44: =SUMIFS(33:33,$3:$3,O$41) -> -199099.92
B45: 4. | C45: Gross profit | F45: =SUM(I45:CN45) -> 6426447.2 | G45: =G34 -> $ | I45: =SUMIFS(34:34,$3:$3,I$41) -> 0 | J45: =SUMIFS(34:34,$3:$3,J$41) -> 944800 | K45: =SUMIFS(34:34,$3:$3,K$41) -> 992040 | L45: =SUMIFS(34:34,$3:$3,L$41) -> 1041642 | M45: =SUMIFS(34:34,$3:$3,M$41) -> 1093724.1 | N45: =SUMIFS(34:34,$3:$3,N$41) -> 1148410.3 | O45: =SUMIFS(34:34,$3:$3,O$41) -> 1205830.8
B46: 5. | C46: Indirect costs | F46: =SUM(I46:CN46) -> -1389970.5 | G46: =G35 -> $ | I46: =SUMIFS(35:35,$3:$3,I$41) -> -137128.57 | J46: =SUMIFS(35:35,$3:$3,J$41) -> -186584.38 | K46: =SUMIFS(35:35,$3:$3,K$41) -> -194897.98 | L46: =SUMIFS(35:35,$3:$3,L$41) -> -203627.26 | M46: =SUMIFS(35:35,$3:$3,M$41) -> -212793.01 | N46: =SUMIFS(35:35,$3:$3,N$41) -> -222417.04 | O46: =SUMIFS(35:35,$3:$3,O$41) -> -232522.27
C47: Break even point | F47: =AVERAGEIF(I47:O47,">0",I47:O47) -> 536.86834 | G47: units/year | I47: =IFERROR(-I46/(I45/I42),0) -> 0 | J47: =IFERROR(-J46/(J45/J42),0) -> 543.48033 | K47: =IFERROR(-K46/(K45/K42),0) -> 540.66292 | L47: =IFERROR(-L46/(L45/L42),0) -> 537.97967 | M47: =IFERROR(-M46/(M45/M42),0) -> 535.4242 | N47: =IFERROR(-N46/(N45/N42),0) -> 532.99041 | O47: =IFERROR(-O46/(O45/O42),0) -> 530.67252
B51: 3 | C51: Marginality
B53: 1. | C53: Average sales volume | F53: =AVERAGEIF(I53:CN53,">0",I53:CN53) -> 229.33333 | G53: units/month | I53: =I2 -> 0 | J53: =J2 -> 0 | K53: =K2 -> 0 | L53: =L2 -> 0 | M53: =M2 -> 0 | N53: =N2 -> 0 | O53: =O2 -> 0 | P53: =P2 -> 0 | ... CN53: =CN2 -> 229.33333
B54: 2. | C54: Cost of 1 unit of product, including VAT | F54: =AVERAGEIF(I54:CN54,">0",I54:CN54) -> 67.475371 | G54: $ / unit | I54: =-IFERROR(PL!I17/I$53*(1+Input!$D$115),0) -> 0 | J54: =-IFERROR(PL!J17/J$53*(1+Input!$D$115),0) -> 0 | K54: =-IFERROR(PL!K17/K$53*(1+Input!$D$115),0) -> 0 | L54: =-IFERROR(PL!L17/L$53*(1+Input!$D$115),0) -> 0 | M54: =-IFERROR(PL!M17/M$53*(1+Input!$D$115),0) -> 0 | N54: =-IFERROR(PL!N17/N$53*(1+Input!$D$115),0) -> 0 | O54: =-IFERROR(PL!O17/O$53*(1+Input!$D$115),0) -> 0 | P54: =-IFERROR(PL!P17/P$53*(1+Input!$D$115),0) -> 0 | ... CN54: =-IFERROR(PL!CN17/CN$53*(1+Input!$D$115),0) -> 75.964724
B55: 3. | C55: Sales price for 1 unit of product, including VAT | F55: =AVERAGEIF(I55:CN55,">0",I55:CN55) -> 476.1339 | G55: $ / unit | I55: =IFERROR(PL!I15/I$53*(1+Input!$D$115),0) -> 0 | J55: =IFERROR(PL!J15/J$53*(1+Input!$D$115),0) -> 0 | K55: =IFERROR(PL!K15/K$53*(1+Input!$D$115),0) -> 0 | L55: =IFERROR(PL!L15/L$53*(1+Input!$D$115),0) -> 0 | M55: =IFERROR(PL!M15/M$53*(1+Input!$D$115),0) -> 0 | N55: =IFERROR(PL!N15/N$53*(1+Input!$D$115),0) -> 0 | O55: =IFERROR(PL!O15/O$53*(1+Input!$D$115),0) -> 0 | P55: =IFERROR(PL!P15/P$53*(1+Input!$D$115),0) -> 0 | ... CN55: =IFERROR(PL!CN15/CN$53*(1+Input!$D$115),0) -> 536.03826
B56: 4. | C56: Gross profit per 1 unit of product, including VAT | F56: =F55-F54 -> 408.65853 | G56: $ / unit | I56: =I55-I54 -> 0 | J56: =J55-J54 -> 0 | K56: =K55-K54 -> 0 | L56: =L55-L54 -> 0 | M56: =M55-M54 -> 0 | N56: =N55-N54 -> 0 | O56: =O55-O54 -> 0 | P56: =P55-P54 -> 0 | ... CN56: =CN55-CN54 -> 460.07353
B57: 5. | C57: Markup, % | F57: =IFERROR(F56/F54,0) -> 6.0564103 | G57: %/unit | I57: =IFERROR(I56/I54,0) -> 0 | J57: =IFERROR(J56/J54,0) -> 0 | K57: =IFERROR(K56/K54,0) -> 0 | L57: =IFERROR(L56/L54,0) -> 0 | M57: =IFERROR(M56/M54,0) -> 0 | N57: =IFERROR(N56/N54,0) -> 0 | O57: =IFERROR(O56/O54,0) -> 0 | P57: =IFERROR(P56/P54,0) -> 0 | ... CN57: =IFERROR(CN56/CN54,0) -> 6.0564103
B58: 6. | C58: Marginality, % | F58: =IFERROR(F56/F55,0) -> 0.85828488 | G58: %/unit | I58: =IFERROR(I56/I55,0) -> 0 | J58: =IFERROR(J56/J55,0) -> 0 | K58: =IFERROR(K56/K55,0) -> 0 | L58: =IFERROR(L56/L55,0) -> 0 | M58: =IFERROR(M56/M55,0) -> 0 | N58: =IFERROR(N56/N55,0) -> 0 | O58: =IFERROR(O56/O55,0) -> 0 | P58: =IFERROR(P56/P55,0) -> 0 | ... CN58: =IFERROR(CN56/CN55,0) -> 0.85828488
B61: 4. | C61: Investment Attractiveness
B63: 4.1. | C63: On project
I64: =I1 -> 46023 | J64: =J1 -> 46054 | K64: =K1 -> 46082 | L64: =L1 -> 46113 | M64: =M1 -> 46143 | N64: =N1 -> 46174 | O64: =O1 -> 46204 | P64: =P1 -> 46235 | ... CN64: =CN1 -> 48549
C65: Free Cash Flow (FCF) | F65: =SUM(I65:CN65) -> 9343955.2 | G65: $ | I65: =CF!I60+CF!I22-Other!I119+Other!I125+CF!I74 -> -15850 | J65: =CF!J60+CF!J22-Other!J119+Other!J125+CF!J74 -> -15850 | K65: =CF!K60+CF!K22-Other!K119+Other!K125+CF!K74 -> -15850 | L65: =CF!L60+CF!L22-Other!L119+Other!L125+CF!L74 -> -15850 | M65: =CF!M60+CF!M22-Other!M119+Other!M125+CF!M74 -> -15250 | N65: =CF!N60+CF!N22-Other!N119+Other!N125+CF!N74 -> -11950 | O65: =CF!O60+CF!O22-Other!O119+Other!O125+CF!O74 -> -11950 | P65: =CF!P60+CF!P22-Other!P119+Other!P125+CF!P74 -> -11950 | ... CN65: =CF!CN60+CF!CN22-Other!CN119+Other!CN125+CF!CN74 -> 4855717.3
C66: Cumulative total | F66: =F65 -> 9343955.2 | G66: $ | I66: =I65+H66 -> -15850 | J66: =J65+I66 -> -31700 | K66: =K65+J66 -> -47550 | L66: =L65+K66 -> -63400 | M66: =M65+L66 -> -78650 | N66: =N65+M66 -> -90600 | O66: =O65+N66 -> -102550 | P66: =P65+O66 -> -114500 | ... CN66: =CN65+CM66 -> 9343955.2
C67: Discount rate | F67: =AVERAGE(I67:CN67) -> 0.3 | G67: % | I67: =Input!$D$131 -> 0.3 | J67: =Input!$D$131 -> 0.3 | K67: =Input!$D$131 -> 0.3 | L67: =Input!$D$131 -> 0.3 | M67: =Input!$D$131 -> 0.3 | N67: =Input!$D$131 -> 0.3 | O67: =Input!$D$131 -> 0.3 | P67: =Input!$D$131 -> 0.3 | ... CN67: =Input!$D$131 -> 0.3
C68: Net Present Value (NPV) | F68: =SUM(I68:CN68) -> 2422012.2 | G68: $ | I68: =I65/(1+I67)^((COUNT($I$1:I$1)-1)/12) -> -15850 | J68: =J65/(1+J67)^((COUNT($I$1:J$1)-1)/12) -> -15507.221 | K68: =K65/(1+K67)^((COUNT($I$1:K$1)-1)/12) -> -15171.856 | L68: =L65/(1+L67)^((COUNT($I$1:L$1)-1)/12) -> -14843.743 | M68: =M65/(1+M67)^((COUNT($I$1:M$1)-1)/12) -> -13972.97 | N68: =N65/(1+N67)^((COUNT($I$1:N$1)-1)/12) -> -10712.517 | O68: =O65/(1+O67)^((COUNT($I$1:O$1)-1)/12) -> -10480.843 | P68: =P65/(1+P67)^((COUNT($I$1:P$1)-1)/12) -> -10254.18 | ... CN68: =CN65/(1+CN67)^((COUNT($I$1:CN$1)-1)/12) -> 790943.04
C69: Cumulative total | F69: =F68 -> 2422012.2 | G69: $ | I69: =I68+H69 -> -15850 | J69: =J68+I69 -> -31357.221 | K69: =K68+J69 -> -46529.077 | L69: =L68+K69 -> -61372.82 | M69: =M68+L69 -> -75345.79 | N69: =N68+M69 -> -86058.307 | O69: =O68+N69 -> -96539.15 | P69: =P68+O69 -> -106793.33 | ... CN69: =CN68+CM69 -> 2422012.2
C70: Internal rate of return (IRR) | F70: =IFERROR(XIRR(I65:CN65,I1:CN1,0),"n/d") -> 4.194825 | G70: %
C71: Profitability Index (PI) | F71: =F65/(CF!F66+CF!F69) -> 57.572121 | G71: k | I71: =C65 -> Free Cash Flow (FCF) | M71: Discounted Cash Flow (NPV)
C72: Discounted Profitability Index (DPI) | F72: =F68/(CF!F66+CF!F69) -> 14.923057 | G72: k | I72: Project payback | M72: Discounted payback of the project
C73: Payback period (PBP) | F73: =COUNTIF(I66:CN66,"<0")/12 -> 1.1666667 | G73: years
C74: Discounted payback period (DPBP) | F74: =COUNTIF(I69:CN69,"<0")/12 -> 1.25 | G74: years
F75: =if(round(F65-CF!F71-F90,0)=0,"Ok",F65-CF!F71-F90) -> 7475164.2
B88: 4.2. | C88: On equity (investors)
C90: Investor cash flow, including: | F90: =SUM(I90:CN90) -> 1868791 | G90: $ | I90: =SUM(I91:I93) -> -6340 | J90: =SUM(J91:J93) -> -6340 | K90: =SUM(K91:K93) -> -6340 | L90: =SUM(L91:L93) -> -6340 | M90: =SUM(M91:M93) -> -6100 | N90: =SUM(N91:N93) -> -4780 | O90: =SUM(O91:O93) -> -4780 | P90: =SUM(P91:P93) -> -4780 | ... CN90: =SUM(CN91:CN93) -> 1254352.6
C91: =CF!C66 -> Contribution to the authorized capital | F91: =SUM(I91:CN91) -> -64920 | G91: $ | I91: =-CF!I69 -> -6340 | J91: =-CF!J69 -> -6340 | K91: =-CF!K69 -> -6340 | L91: =-CF!L69 -> -6340 | M91: =-CF!M69 -> -6100 | N91: =-CF!N69 -> -4780 | O91: =-CF!O69 -> -4780 | P91: =-CF!P69 -> -4780 | ... CN91: =-CF!CN69 -> 0
C92: Dividends | F92: =SUM(I92:CN92) -> 977329.43 | G92: $ | I92: =-CF!I75*Input!$D$93-I93-CF!I70 -> 0 | J92: =-CF!J75*Input!$D$93-J93-CF!J70 -> 0 | K92: =-CF!K75*Input!$D$93-K93-CF!K70 -> 0 | L92: =-CF!L75*Input!$D$93-L93-CF!L70 -> 0 | M92: =-CF!M75*Input!$D$93-M93-CF!M70 -> 0 | N92: =-CF!N75*Input!$D$93-N93-CF!N70 -> 0 | O92: =-CF!O75*Input!$D$93-O93-CF!O70 -> 0 | P92: =-CF!P75*Input!$D$93-P93-CF!P70 -> 0 | ... CN92: =-CF!CN75*Input!$D$93-CN93-CF!CN70 -> 297970.99
C93: Sale of a share in a business | F93: =SUM(I93:CN93) -> 956381.61 | G93: $ | I93: =CF!I74*Input!$D$93 -> 0 | J93: =CF!J74*Input!$D$93 -> 0 | K93: =CF!K74*Input!$D$93 -> 0 | L93: =CF!L74*Input!$D$93 -> 0 | M93: =CF!M74*Input!$D$93 -> 0 | N93: =CF!N74*Input!$D$93 -> 0 | O93: =CF!O74*Input!$D$93 -> 0 | P93: =CF!P74*Input!$D$93 -> 0 | ... CN93: =CF!CN74*Input!$D$93 -> 956381.61
C94: Cumulative total | F94: =CN94 -> 1868791 | G94: $ | I94: =I90+H94 -> -6340 | J94: =J90+I94 -> -12680 | K94: =K90+J94 -> -19020 | L94: =L90+K94 -> -25360 | M94: =M90+L94 -> -31460 | N94: =N90+M94 -> -36240 | O94: =O90+N94 -> -41020 | P94: =P90+O94 -> -45800 | ... CN94: =CN90+CM94 -> 1868791
C95: Discount rate | F95: =AVERAGE(I95:CN95) -> 0.3 | G95: % | I95: =Input!$D$131 -> 0.3 | J95: =Input!$D$131 -> 0.3 | K95: =Input!$D$131 -> 0.3 | L95: =Input!$D$131 -> 0.3 | M95: =Input!$D$131 -> 0.3 | N95: =Input!$D$131 -> 0.3 | O95: =Input!$D$131 -> 0.3 | P95: =Input!$D$131 -> 0.3 | ... CN95: =Input!$D$131 -> 0.3
C96: Net Present Value (NPV) | F96: =SUM(I96:CN96) -> 382099.52 | G96: $ | I96: =I90/(1+I95)^((COUNT($I$1:I$1)-1)/12) -> -6340 | J96: =J90/(1+J95)^((COUNT($I$1:J$1)-1)/12) -> -6202.8886 | K96: =K90/(1+K95)^((COUNT($I$1:K$1)-1)/12) -> -6068.7423 | L96: =L90/(1+L95)^((COUNT($I$1:L$1)-1)/12) -> -5937.4972 | M96: =M90/(1+M95)^((COUNT($I$1:M$1)-1)/12) -> -5589.188 | N96: =N90/(1+N95)^((COUNT($I$1:N$1)-1)/12) -> -4285.0066 | O96: =O90/(1+O95)^((COUNT($I$1:O$1)-1)/12) -> -4192.3373 | P96: =P90/(1+P95)^((COUNT($I$1:P$1)-1)/12) -> -4101.6721 | ... CN96: =CN90/(1+CN95)^((COUNT($I$1:CN$1)-1)/12) -> 204320.27
C97: Cumulative total | F97: =F96 -> 382099.52 | G97: $ | I97: =I96+H97 -> -6340 | J97: =J96+I97 -> -12542.889 | K97: =K96+J97 -> -18611.631 | L97: =L96+K97 -> -24549.128 | M97: =M96+L97 -> -30138.316 | N97: =N96+M97 -> -34423.323 | O97: =O96+N97 -> -38615.66 | P97: =P96+O97 -> -42717.332 | ... CN97: =CN96+CM97 -> 382099.52
C98: Internal rate of return (IRR) | F98: =IFERROR(XIRR(I90:CN90,I1:CN1,0),"n/d") -> 1.17074 | G98: %
C99: Profitability Index (PI) | F99: =-F90/F91 -> 28.78606 | G99: k
C100: Discounted Profitability Index (DPI) | F100: =-F96/F91 -> 5.885698 | G100: k
C101: Payback period (PBP) | F101: =COUNTIF(I94:CN94,"<0")/12 -> 2 | G101: years
C102: Discounted payback period (DPBP) | F102: =COUNTIF(I97:CN97,"<0")/12 -> 3 | G102: years
B106: 5 | C106: Data for Charts
B108: 5.1. | C108: Income, expenses, payback
C110: Index | I110: =I1 -> 46023 | J110: =J1 -> 46054 | K110: =K1 -> 46082 | L110: =L1 -> 46113 | M110: =M1 -> 46143 | N110: =N1 -> 46174 | O110: =O1 -> 46204 | P110: =P1 -> 46235 | ... CN110: =CN1 -> 48549
C111: Income | F111: =sum(I111:CN111) -> 7861922.9 | I111: =CF!I27 -> 0 | J111: =CF!J27 -> 0 | K111: =CF!K27 -> 0 | L111: =CF!L27 -> 0 | M111: =CF!M27 -> 0 | N111: =CF!N27 -> 0 | O111: =CF!O27 -> 0 | P111: =CF!P27 -> 0 | ... CN111: =CF!CN27 -> 122931.44
C112: Expenses (total) | F112: =sum(I112:CN112) -> 3299875.8 | I112: =-(CF!I30+CF!I35+CF!I38+CF!I49+CF!I57+CF!I22) -> 15850 | J112: =-(CF!J30+CF!J35+CF!J38+CF!J49+CF!J57+CF!J22) -> 15850 | K112: =-(CF!K30+CF!K35+CF!K38+CF!K49+CF!K57+CF!K22) -> 15850 | L112: =-(CF!L30+CF!L35+CF!L38+CF!L49+CF!L57+CF!L22) -> 15850 | M112: =-(CF!M30+CF!M35+CF!M38+CF!M49+CF!M57+CF!M22) -> 15250 | N112: =-(CF!N30+CF!N35+CF!N38+CF!N49+CF!N57+CF!N22) -> 11950 | O112: =-(CF!O30+CF!O35+CF!O38+CF!O49+CF!O57+CF!O22) -> 11950 | P112: =-(CF!P30+CF!P35+CF!P38+CF!P49+CF!P57+CF!P22) -> 11950 | ... CN112: =-(CF!CN30+CF!CN35+CF!CN38+CF!CN49+CF!CN57+CF!CN22) -> 49122.208
C113: Total | F113: =F111-F112 -> 4562047.1 | I113: =I111-I112 -> -15850 | J113: =J111-J112 -> -15850 | K113: =K111-K112 -> -15850 | L113: =L111-L112 -> -15850 | M113: =M111-M112 -> -15250 | N113: =N111-N112 -> -11950 | O113: =O111-O112 -> -11950 | P113: =P111-P112 -> -11950 | ... CN113: =CN111-CN112 -> 73809.232
C114: Payback | I114: =I113+H114 -> -15850 | J114: =J113+I114 -> -31700 | K114: =K113+J114 -> -47550 | L114: =L113+K114 -> -63400 | M114: =M113+L114 -> -78650 | N114: =N113+M114 -> -90600 | O114: =O113+N114 -> -102550 | P114: =P113+O114 -> -114500 | ... CN114: =CN113+CM114 -> 4562047.1

Sheet Other
A1: =BS!A1 -> Ok | B1: =CF!B1 -> № | C1: =CF!C1 -> Name | E1: =CF!E1 -> Share | F1: =CF!F1 -> Total | G1: =CF!G1 -> Unit | I1: =CF!I1 -> 46023 | J1: =CF!J1 -> 46054 | K1: =CF!K1 -> 46082 | L1: =CF!L1 -> 46113 | M1: =CF!M1 -> 46143 | N1: =CF!N1 -> 46174 | O1: =CF!O1 -> 46204 | P1: =CF!P1 -> 46235 | ... CN1: =CF!CN1 -> 48549
C2: =CF!C2 -> Sales volume, MAU | I2: =CF!I2 -> 0 | J2: =CF!J2 -> 0 | K2: =CF!K2 -> 0 | L2: =CF!L2 -> 0 | M2: =CF!M2 -> 0 | N2: =CF!N2 -> 0 | O2: =CF!O2 -> 0 | P2: =CF!P2 -> 0 | ... CN2: =CF!CN2 -> 229.33333
C3: =CF!C3 -> Year | I3: =CF!I3 -> 2026 | J3: =CF!J3 -> 2026 | K3: =CF!K3 -> 2026 | L3: =CF!L3 -> 2026 | M3: =CF!M3 -> 2026 | N3: =CF!N3 -> 2026 | O3: =CF!O3 -> 2026 | P3: =CF!P3 -> 2026 | ... CN3: =CF!CN3 -> 2032
C4: =CF!C4 -> Month | I4: =CF!I4 -> 1 | J4: =CF!J4 -> 2 | K4: =CF!K4 -> 3 | L4: =CF!L4 -> 4 | M4: =CF!M4 -> 5 | N4: =CF!N4 -> 6 | O4: =CF!O4 -> 7 | P4: =CF!P4 -> 8 | ... CN4: =CF!CN4 -> 12
C5: =CF!C5 -> Serial number of the period | I5: =CF!I5 -> 1 | J5: =CF!J5 -> 2 | K5: =CF!K5 -> 3 | L5: =CF!L5 -> 4 | M5: =CF!M5 -> 5 | N5: =CF!N5 -> 6 | O5: =CF!O5 -> 7 | P5: =CF!P5 -> 8 | ... CN5: =CF!CN5 -> 84
C6: =CF!C6 -> Indexation of production prices | I6: =CF!I6 -> 1 | J6: =CF!J6 -> 1 | K6: =CF!K6 -> 1 | L6: =CF!L6 -> 1 | M6: =CF!M6 -> 1 | N6: =CF!N6 -> 1 | O6: =CF!O6 -> 1 | P6: =CF!P6 -> 1 | ... CN6: =CF!CN6 -> 1.3400956
C7: =CF!C7 -> Payroll indexation | I7: =CF!I7 -> 1 | J7: =CF!J7 -> 1 | K7: =CF!K7 -> 1 | L7: =CF!L7 -> 1 | M7: =CF!M7 -> 1 | N7: =CF!N7 -> 1 | O7: =CF!O7 -> 1 | P7: =CF!P7 -> 1 | ... CN7: =CF!CN7 -> 1.3400956
C8: =CF!C8 -> Indexation of other expenses | I8: =CF!I8 -> 1 | J8: =CF!J8 -> 1 | K8: =CF!K8 -> 1 | L8: =CF!L8 -> 1 | M8: =CF!M8 -> 1 | N8: =CF!N8 -> 1 | O8: =CF!O8 -> 1 | P8: =CF!P8 -> 1 | ... CN8: =CF!CN8 -> 1.3400956
C9: =CF!C9 -> Sales price indexation | I9: =CF!I9 -> 1 | J9: =CF!J9 -> 1 | K9: =CF!K9 -> 1 | L9: =CF!L9 -> 1 | M9: =CF!M9 -> 1 | N9: =CF!N9 -> 1 | O9: =CF!O9 -> 1 | P9: =CF!P9 -> 1 | ... CN9: =CF!CN9 -> 1.3400956
C11: Other calculations
B13: 1 | C13: Development / Financing Schedule
B15: =Input!B28 -> 1. | C15: =Input!C28 -> Platform development | F15: =SUM(I15:CN15) -> -20000 | G15: $ | I15: =-Input!F28 -> -5000 | J15: =-Input!G28 -> -5000 | K15: =-Input!H28 -> -5000 | L15: =-Input!I28 -> -5000 | M15: =-Input!J28 -> 0 | N15: =-Input!K28 -> 0 | O15: =-Input!L28 -> 0 | P15: =-Input!M28 -> 0 | ... CN15: =-Input!CK28 -> 0
B16: =Input!B29 -> 2. | C16: =Input!C29 -> Infrastructure setup | F16: =SUM(I16:CN16) -> -4400 | G16: $ | I16: =-Input!F29 -> 0 | J16: =-Input!G29 -> 0 | K16: =-Input!H29 -> 0 | L16: =-Input!I29 -> 0 | M16: =-Input!J29 -> -4400 | N16: =-Input!K29 -> 0 | O16: =-Input!L29 -> 0 | P16: =-Input!M29 -> 0 | ... CN16: =-Input!CK29 -> 0
B17: 3. | C17: =Input!C30 | F17: =SUM(I17:CN17) -> 0 | G17: $ | I17: =-Input!F30 -> 0 | J17: =-Input!G30 -> 0 | K17: =-Input!H30 -> 0 | L17: =-Input!I30 -> 0 | M17: =-Input!J30 -> 0 | N17: =-Input!K30 -> 0 | O17: =-Input!L30 -> 0 | P17: =-Input!M30 -> 0 | ... CN17: =-Input!CK30 -> 0
B18: 4. | C18: =Input!C31 | F18: =SUM(I18:CN18) -> 0 | G18: $ | I18: =-Input!F31 -> 0 | J18: =-Input!G31 -> 0 | K18: =-Input!H31 -> 0 | L18: =-Input!I31 -> 0 | M18: =-Input!J31 -> 0 | N18: =-Input!K31 -> 0 | O18: =-Input!L31 -> 0 | P18: =-Input!M31 -> 0 | ... CN18: =-Input!CK31 -> 0
B19: =Input!B32 -> 5. | C19: =Input!C32 | F19: =SUM(I19:CN19) -> 0 | G19: $ | I19: =-Input!F32 -> 0 | J19: =-Input!G32 -> 0 | K19: =-Input!H32 -> 0 | L19: =-Input!I32 -> 0 | M19: =-Input!J32 -> 0 | N19: =-Input!K32 -> 0 | O19: =-Input!L32 -> 0 | P19: =-Input!M32 -> 0 | ... CN19: =-Input!CK32 -> 0
C20: Total | F20: =SUM(I20:CN20) -> -24400 | G20: $ | I20: =SUM(I15:I19) -> -5000 | J20: =SUM(J15:J19) -> -5000 | K20: =SUM(K15:K19) -> -5000 | L20: =SUM(L15:L19) -> -5000 | M20: =SUM(M15:M19) -> -4400 | N20: =SUM(N15:N19) -> 0 | O20: =SUM(O15:O19) -> 0 | P20: =SUM(P15:P19) -> 0 | ... CN20: =SUM(CN15:CN19) -> 0
B23: 2 | C23: Fixed Assets
C25: Summary data for all fixed assets
C26: Fixed assets at the beginning of the period | G26: $ | I26: =H30 | J26: =I30 -> 0 | K26: =J30 -> 0 | L26: =K30 -> 0 | M26: =L30 -> 0 | N26: =M30 -> 0 | O26: =N30 -> 23238.095 | P26: =O30 -> 22850.794 | ... CN26: =CM30 -> 0
C27: Unfinished production | F27: =MAX(I27:CN27) -> 23238.095 | G27: $ | I27: =SUMIFS(I$32:I$66,$C$32:$C$66,$C27) -> 4761.9048 | J27: =SUMIFS(J$32:J$66,$C$32:$C$66,$C27) -> 9523.8095 | K27: =SUMIFS(K$32:K$66,$C$32:$C$66,$C27) -> 14285.714 | L27: =SUMIFS(L$32:L$66,$C$32:$C$66,$C27) -> 19047.619 | M27: =SUMIFS(M$32:M$66,$C$32:$C$66,$C27) -> 23238.095 | N27: =SUMIFS(N$32:N$66,$C$32:$C$66,$C27) -> 0 | O27: =SUMIFS(O$32:O$66,$C$32:$C$66,$C27) -> 0 | P27: =SUMIFS(P$32:P$66,$C$32:$C$66,$C27) -> 0 | ... CN27: =SUMIFS(CN$32:CN$66,$C$32:$C$66,$C27) -> 0
C28: Commissioning | F28: =SUM(I28:CN28) -> 23238.095 | G28: $ | I28: =SUMIFS(I$32:I$66,$C$32:$C$66,$C28) -> 0 | J28: =SUMIFS(J$32:J$66,$C$32:$C$66,$C28) -> 0 | K28: =SUMIFS(K$32:K$66,$C$32:$C$66,$C28) -> 0 | L28: =SUMIFS(L$32:L$66,$C$32:$C$66,$C28) -> 0 | M28: =SUMIFS(M$32:M$66,$C$32:$C$66,$C28) -> 0 | N28: =SUMIFS(N$32:N$66,$C$32:$C$66,$C28) -> 23238.095 | O28: =SUMIFS(O$32:O$66,$C$32:$C$66,$C28) -> 0 | P28: =SUMIFS(P$32:P$66,$C$32:$C$66,$C28) -> 0 | ... CN28: =SUMIFS(CN$32:CN$66,$C$32:$C$66,$C28) -> 0
C29: Depreciation | F29: =SUM(I29:CN29) -> -23238.095 | G29: $ | I29: =SUMIFS(I$32:I$66,$C$32:$C$66,$C29) -> 0 | J29: =SUMIFS(J$32:J$66,$C$32:$C$66,$C29) -> 0 | K29: =SUMIFS(K$32:K$66,$C$32:$C$66,$C29) -> 0 | L29: =SUMIFS(L$32:L$66,$C$32:$C$66,$C29) -> 0 | M29: =SUMIFS(M$32:M$66,$C$32:$C$66,$C29) -> 0 | N29: =SUMIFS(N$32:N$66,$C$32:$C$66,$C29) -> 0 | O29: =SUMIFS(O$32:O$66,$C$32:$C$66,$C29) -> -387.30159 | P29: =SUMIFS(P$32:P$66,$C$32:$C$66,$C29) -> -387.30159 | ... CN29: =SUMIFS(CN$32:CN$66,$C$32:$C$66,$C29) -> 0
C30: Fixed assets at the end of the period | G30: $ | I30: =IF(ROUND(I26+I29+I28,2)=0,0,I26+I29+I28) -> 0 | J30: =IF(ROUND(J26+J29+J28,2)=0,0,J26+J29+J28) -> 0 | K30: =IF(ROUND(K26+K29+K28,2)=0,0,K26+K29+K28) -> 0 | L30: =IF(ROUND(L26+L29+L28,2)=0,0,L26+L29+L28) -> 0 | M30: =IF(ROUND(M26+M29+M28,2)=0,0,M26+M29+M28) -> 0 | N30: =IF(ROUND(N26+N29+N28,2)=0,0,N26+N29+N28) -> 23238.095 | O30: =IF(ROUND(O26+O29+O28,2)=0,0,O26+O29+O28) -> 22850.794 | P30: =IF(ROUND(P26+P29+P28,2)=0,0,P26+P29+P28) -> 22463.492 | ... CN30: =IF(ROUND(CN26+CN29+CN28,2)=0,0,CN26+CN29+CN28) -> 0
B32: =B15 -> 1. | C32: =C15 -> Platform development
C33: =C26 -> Fixed assets at the beginning of the period | G33: $ | I33: =H37 | J33: =I37 -> 0 | K33: =J37 -> 0 | L33: =K37 -> 0 | M33: =L37 -> 0 | N33: =M37 -> 0 | O33: =N37 -> 19047.619 | P33: =O37 -> 18730.159 | ... CN33: =CM37 -> 0
C34: =C27 -> Unfinished production | F34: =MAX(I34:CN34) -> 19047.619 | G34: $ | I34: =IF(SUM(I$20:$CN$20)=0,0,-SUMIFS(I$15:I$19,$B$15:$B$19,$B32)/(1+Input!$D$115)+H34) -> 4761.9048 | J34: =IF(SUM(J$20:$CN$20)=0,0,-SUMIFS(J$15:J$19,$B$15:$B$19,$B32)/(1+Input!$D$115)+I34) -> 9523.8095 | K34: =IF(SUM(K$20:$CN$20)=0,0,-SUMIFS(K$15:K$19,$B$15:$B$19,$B32)/(1+Input!$D$115)+J34) -> 14285.714 | L34: =IF(SUM(L$20:$CN$20)=0,0,-SUMIFS(L$15:L$19,$B$15:$B$19,$B32)/(1+Input!$D$115)+K34) -> 19047.619 | M34: =IF(SUM(M$20:$CN$20)=0,0,-SUMIFS(M$15:M$19,$B$15:$B$19,$B32)/(1+Input!$D$115)+L34) -> 19047.619 | N34: =IF(SUM(N$20:$CN$20)=0,0,-SUMIFS(N$15:N$19,$B$15:$B$19,$B32)/(1+Input!$D$115)+M34) -> 0 | O34: =IF(SUM(O$20:$CN$20)=0,0,-SUMIFS(O$15:O$19,$B$15:$B$19,$B32)/(1+Input!$D$115)+N34) -> 0 | P34: =IF(SUM(P$20:$CN$20)=0,0,-SUMIFS(P$15:P$19,$B$15:$B$19,$B32)/(1+Input!$D$115)+O34) -> 0 | ... CN34: =IF(SUM(CN$20:$CN$20)=0,0,-SUMIFS(CN$15:CN$19,$B$15:$B$19,$B32)/(1+Input!$D$115)+CM34) -> 0
C35: =C28 -> Commissioning | F35: =SUM(I35:CN35) -> 19047.619 | G35: $ | I35: =IF(AND(I34=0,H34>0),H34,0) -> 0 | J35: =IF(AND(J34=0,I34>0),I34,0) -> 0 | K35: =IF(AND(K34=0,J34>0),J34,0) -> 0 | L35: =IF(AND(L34=0,K34>0),K34,0) -> 0 | M35: =IF(AND(M34=0,L34>0),L34,0) -> 0 | N35: =IF(AND(N34=0,M34>0),M34,0) -> 19047.619 | O35: =IF(AND(O34=0,N34>0),N34,0) -> 0 | P35: =IF(AND(P34=0,O34>0),O34,0) -> 0 | ... CN35: =IF(AND(CN34=0,CM34>0),CM34,0) -> 0
C36: =C29 -> Depreciation | F36: =SUM(I36:CN36) -> -19047.619 | G36: $ | I36: =IF(H37=0,0,-$F34/VLOOKUP($B32,Input!$B$28:$D$32,3,FALSE)/12) -> 0 | J36: =IF(I37=0,0,-$F34/VLOOKUP($B32,Input!$B$28:$D$32,3,FALSE)/12) -> 0 | K36: =IF(J37=0,0,-$F34/VLOOKUP($B32,Input!$B$28:$D$32,3,FALSE)/12) -> 0 | L36: =IF(K37=0,0,-$F34/VLOOKUP($B32,Input!$B$28:$D$32,3,FALSE)/12) -> 0 | M36: =IF(L37=0,0,-$F34/VLOOKUP($B32,Input!$B$28:$D$32,3,FALSE)/12) -> 0 | N36: =IF(M37=0,0,-$F34/VLOOKUP($B32,Input!$B$28:$D$32,3,FALSE)/12) -> 0 | O36: =IF(N37=0,0,-$F34/VLOOKUP($B32,Input!$B$28:$D$32,3,FALSE)/12) -> -317.46032 | P36: =IF(O37=0,0,-$F34/VLOOKUP($B32,Input!$B$28:$D$32,3,FALSE)/12) -> -317.46032 | ... CN36: =IF(CM37=0,0,-$F34/VLOOKUP($B32,Input!$B$28:$D$32,3,FALSE)/12) -> 0
C37: =C30 -> Fixed assets at the end of the period | G37: $ | I37: =IF(ROUND(I33+I36+I35,2)=0,0,I33+I36+I35) -> 0 | J37: =IF(ROUND(J33+J36+J35,2)=0,0,J33+J36+J35) -> 0 | K37: =IF(ROUND(K33+K36+K35,2)=0,0,K33+K36+K35) -> 0 | L37: =IF(ROUND(L33+L36+L35,2)=0,0,L33+L36+L35) -> 0 | M37: =IF(ROUND(M33+M36+M35,2)=0,0,M33+M36+M35) -> 0 | N37: =IF(ROUND(N33+N36+N35,2)=0,0,N33+N36+N35) -> 19047.619 | O37: =IF(ROUND(O33+O36+O35,2)=0,0,O33+O36+O35) -> 18730.159 | P37: =IF(ROUND(P33+P36+P35,2)=0,0,P33+P36+P35) -> 18412.698 | ... CN37: =IF(ROUND(CN33+CN36+CN35,2)=0,0,CN33+CN36+CN35) -> 0
B39: =B16 -> 2. | C39: =C16 -> Infrastructure setup
C40: =C33 -> Fixed assets at the beginning of the period | G40: $ | I40: =H44 | J40: =I44 -> 0 | K40: =J44 -> 0 | L40: =K44 -> 0 | M40: =L44 -> 0 | N40: =M44 -> 0 | O40: =N44 -> 4190.4762 | P40: =O44 -> 4120.6349 | ... CN40: =CM44 -> 0
C41: =C34 -> Unfinished production | F41: =MAX(I41:CN41) -> 4190.4762 | G41: $ | I41: =IF(SUM(I$20:$CN$20)=0,0,-SUMIFS(I$15:I$19,$B$15:$B$19,$B39)/(1+Input!$D$115)+H41) -> 0 | J41: =IF(SUM(J$20:$CN$20)=0,0,-SUMIFS(J$15:J$19,$B$15:$B$19,$B39)/(1+Input!$D$115)+I41) -> 0 | K41: =IF(SUM(K$20:$CN$20)=0,0,-SUMIFS(K$15:K$19,$B$15:$B$19,$B39)/(1+Input!$D$115)+J41) -> 0 | L41: =IF(SUM(L$20:$CN$20)=0,0,-SUMIFS(L$15:L$19,$B$15:$B$19,$B39)/(1+Input!$D$115)+K41) -> 0 | M41: =IF(SUM(M$20:$CN$20)=0,0,-SUMIFS(M$15:M$19,$B$15:$B$19,$B39)/(1+Input!$D$115)+L41) -> 4190.4762 | N41: =IF(SUM(N$20:$CN$20)=0,0,-SUMIFS(N$15:N$19,$B$15:$B$19,$B39)/(1+Input!$D$115)+M41) -> 0 | O41: =IF(SUM(O$20:$CN$20)=0,0,-SUMIFS(O$15:O$19,$B$15:$B$19,$B39)/(1+Input!$D$115)+N41) -> 0 | P41: =IF(SUM(P$20:$CN$20)=0,0,-SUMIFS(P$15:P$19,$B$15:$B$19,$B39)/(1+Input!$D$115)+O41) -> 0 | ... CN41: =IF(SUM(CN$20:$CN$20)=0,0,-SUMIFS(CN$15:CN$19,$B$15:$B$19,$B39)/(1+Input!$D$115)+CM41) -> 0
C42: =C35 -> Commissioning | F42: =SUM(I42:CN42) -> 4190.4762 | G42: $ | I42: =IF(AND(H41>0,I41=0),H41,0) -> 0 | J42: =IF(AND(I41>0,J41=0),I41,0) -> 0 | K42: =IF(AND(J41>0,K41=0),J41,0) -> 0 | L42: =IF(AND(K41>0,L41=0),K41,0) -> 0 | M42: =IF(AND(L41>0,M41=0),L41,0) -> 0 | N42: =IF(AND(M41>0,N41=0),M41,0) -> 4190.4762 | O42: =IF(AND(N41>0,O41=0),N41,0) -> 0 | P42: =IF(AND(O41>0,P41=0),O41,0) -> 0 | ... CN42: =IF(AND(CM41>0,CN41=0),CM41,0) -> 0
C43: =C36 -> Depreciation | F43: =SUM(I43:CN43) -> -4190.4762 | G43: $ | I43: =IF(H44=0,0,-$F41/VLOOKUP($B39,Input!$B$28:$D$32,3,FALSE)/12) -> 0 | J43: =IF(I44=0,0,-$F41/VLOOKUP($B39,Input!$B$28:$D$32,3,FALSE)/12) -> 0 | K43: =IF(J44=0,0,-$F41/VLOOKUP($B39,Input!$B$28:$D$32,3,FALSE)/12) -> 0 | L43: =IF(K44=0,0,-$F41/VLOOKUP($B39,Input!$B$28:$D$32,3,FALSE)/12) -> 0 | M43: =IF(L44=0,0,-$F41/VLOOKUP($B39,Input!$B$28:$D$32,3,FALSE)/12) -> 0 | N43: =IF(M44=0,0,-$F41/VLOOKUP($B39,Input!$B$28:$D$32,3,FALSE)/12) -> 0 | O43: =IF(N44=0,0,-$F41/VLOOKUP($B39,Input!$B$28:$D$32,3,FALSE)/12) -> -69.84127 | P43: =IF(O44=0,0,-$F41/VLOOKUP($B39,Input!$B$28:$D$32,3,FALSE)/12) -> -69.84127 | ... CN43: =IF(CM44=0,0,-$F41/VLOOKUP($B39,Input!$B$28:$D$32,3,FALSE)/12) -> 0
C44: =C37 -> Fixed assets at the end of the period | G44: $ | I44: =IF(ROUND(I40+I43+I42,2)=0,0,I40+I43+I42) -> 0 | J44: =IF(ROUND(J40+J43+J42,2)=0,0,J40+J43+J42) -> 0 | K44: =IF(ROUND(K40+K43+K42,2)=0,0,K40+K43+K42) -> 0 | L44: =IF(ROUND(L40+L43+L42,2)=0,0,L40+L43+L42) -> 0 | M44: =IF(ROUND(M40+M43+M42,2)=0,0,M40+M43+M42) -> 0 | N44: =IF(ROUND(N40+N43+N42,2)=0,0,N40+N43+N42) -> 4190.4762 | O44: =IF(ROUND(O40+O43+O42,2)=0,0,O40+O43+O42) -> 4120.6349 | P44: =IF(ROUND(P40+P43+P42,2)=0,0,P40+P43+P42) -> 4050.7937 | ... CN44: =IF(ROUND(CN40+CN43+CN42,2)=0,0,CN40+CN43+CN42) -> 0
B46: =B17 -> 3. | C46: =C17
C47: =C40 -> Fixed assets at the beginning of the period | G47: $ | I47: =H51 | J47: =I51 -> 0 | K47: =J51 -> 0 | L47: =K51 -> 0 | M47: =L51 -> 0 | N47: =M51 -> 0 | O47: =N51 -> 0 | P47: =O51 -> 0 | ... CN47: =CM51 -> 0
C48: =C41 -> Unfinished production | F48: =MAX(I48:CN48) -> 0 | G48: $ | I48: =IF(SUM(I$20:$CN$20)=0,0,-SUMIFS(I$15:I$19,$B$15:$B$19,$B46)/(1+Input!$D$115)+H48) -> 0 | J48: =IF(SUM(J$20:$CN$20)=0,0,-SUMIFS(J$15:J$19,$B$15:$B$19,$B46)/(1+Input!$D$115)+I48) -> 0 | K48: =IF(SUM(K$20:$CN$20)=0,0,-SUMIFS(K$15:K$19,$B$15:$B$19,$B46)/(1+Input!$D$115)+J48) -> 0 | L48: =IF(SUM(L$20:$CN$20)=0,0,-SUMIFS(L$15:L$19,$B$15:$B$19,$B46)/(1+Input!$D$115)+K48) -> 0 | M48: =IF(SUM(M$20:$CN$20)=0,0,-SUMIFS(M$15:M$19,$B$15:$B$19,$B46)/(1+Input!$D$115)+L48) -> 0 | N48: =IF(SUM(N$20:$CN$20)=0,0,-SUMIFS(N$15:N$19,$B$15:$B$19,$B46)/(1+Input!$D$115)+M48) -> 0 | O48: =IF(SUM(O$20:$CN$20)=0,0,-SUMIFS(O$15:O$19,$B$15:$B$19,$B46)/(1+Input!$D$115)+N48) -> 0 | P48: =IF(SUM(P$20:$CN$20)=0,0,-SUMIFS(P$15:P$19,$B$15:$B$19,$B46)/(1+Input!$D$115)+O48) -> 0 | ... CN48: =IF(SUM(CN$20:$CN$20)=0,0,-SUMIFS(CN$15:CN$19,$B$15:$B$19,$B46)/(1+Input!$D$115)+CM48) -> 0
C49: =C42 -> Commissioning | F49: =SUM(I49:CN49) -> 0 | G49: $ | I49: =IF(AND(H48>0,I48=0),H48,0) -> 0 | J49: =IF(AND(I48>0,J48=0),I48,0) -> 0 | K49: =IF(AND(J48>0,K48=0),J48,0) -> 0 | L49: =IF(AND(K48>0,L48=0),K48,0) -> 0 | M49: =IF(AND(L48>0,M48=0),L48,0) -> 0 | N49: =IF(AND(M48>0,N48=0),M48,0) -> 0 | O49: =IF(AND(N48>0,O48=0),N48,0) -> 0 | P49: =IF(AND(O48>0,P48=0),O48,0) -> 0 | ... CN49: =IF(AND(CM48>0,CN48=0),CM48,0) -> 0
C50: =C43 -> Depreciation | F50: =SUM(I50:CN50) -> 0 | G50: $ | I50: =IF(H51=0,0,-$F48/VLOOKUP($B46,Input!$B$28:$D$32,3,FALSE)/12) -> 0 | J50: =IF(I51=0,0,-$F48/VLOOKUP($B46,Input!$B$28:$D$32,3,FALSE)/12) -> 0 | K50: =IF(J51=0,0,-$F48/VLOOKUP($B46,Input!$B$28:$D$32,3,FALSE)/12) -> 0 | L50: =IF(K51=0,0,-$F48/VLOOKUP($B46,Input!$B$28:$D$32,3,FALSE)/12) -> 0 | M50: =IF(L51=0,0,-$F48/VLOOKUP($B46,Input!$B$28:$D$32,3,FALSE)/12) -> 0 | N50: =IF(M51=0,0,-$F48/VLOOKUP($B46,Input!$B$28:$D$32,3,FALSE)/12) -> 0 | O50: =IF(N51=0,0,-$F48/VLOOKUP($B46,Input!$B$28:$D$32,3,FALSE)/12) -> 0 | P50: =IF(O51=0,0,-$F48/VLOOKUP($B46,Input!$B$28:$D$32,3,FALSE)/12) -> 0 | ... CN50: =IF(CM51=0,0,-$F48/VLOOKUP($B46,Input!$B$28:$D$32,3,FALSE)/12) -> 0
C51: =C44 -> Fixed assets at the end of the period | G51: $ | I51: =IF(ROUND(I47+I50+I49,2)=0,0,I47+I50+I49) -> 0 | J51: =IF(ROUND(J47+J50+J49,2)=0,0,J47+J50+J49) -> 0 | K51: =IF(ROUND(K47+K50+K49,2)=0,0,K47+K50+K49) -> 0 | L51: =IF(ROUND(L47+L50+L49,2)=0,0,L47+L50+L49) -> 0 | M51: =IF(ROUND(M47+M50+M49,2)=0,0,M47+M50+M49) -> 0 | N51: =IF(ROUND(N47+N50+N49,2)=0,0,N47+N50+N49) -> 0 | O51: =IF(ROUND(O47+O50+O49,2)=0,0,O47+O50+O49) -> 0 | P51: =IF(ROUND(P47+P50+P49,2)=0,0,P47+P50+P49) -> 0 | ... CN51: =IF(ROUND(CN47+CN50+CN49,2)=0,0,CN47+CN50+CN49) -> 0
B53: =B18 -> 4. | C53: =C18
C54: =C47 -> Fixed assets at the beginning of the period | G54: $ | I54: =H58 | J54: =I58 -> 0 | K54: =J58 -> 0 | L54: =K58 -> 0 | M54: =L58 -> 0 | N54: =M58 -> 0 | O54: =N58 -> 0 | P54: =O58 -> 0 | ... CN54: =CM58 -> 0
C55: =C48 -> Unfinished production | F55: =MAX(I55:CN55) -> 0 | G55: $ | I55: =IF(SUM(I$20:$CN$20)=0,0,-SUMIFS(I$15:I$19,$B$15:$B$19,$B53)/(1+Input!$D$115)+H55) -> 0 | J55: =IF(SUM(J$20:$CN$20)=0,0,-SUMIFS(J$15:J$19,$B$15:$B$19,$B53)/(1+Input!$D$115)+I55) -> 0 | K55: =IF(SUM(K$20:$CN$20)=0,0,-SUMIFS(K$15:K$19,$B$15:$B$19,$B53)/(1+Input!$D$115)+J55) -> 0 | L55: =IF(SUM(L$20:$CN$20)=0,0,-SUMIFS(L$15:L$19,$B$15:$B$19,$B53)/(1+Input!$D$115)+K55) -> 0 | M55: =IF(SUM(M$20:$CN$20)=0,0,-SUMIFS(M$15:M$19,$B$15:$B$19,$B53)/(1+Input!$D$115)+L55) -> 0 | N55: =IF(SUM(N$20:$CN$20)=0,0,-SUMIFS(N$15:N$19,$B$15:$B$19,$B53)/(1+Input!$D$115)+M55) -> 0 | O55: =IF(SUM(O$20:$CN$20)=0,0,-SUMIFS(O$15:O$19,$B$15:$B$19,$B53)/(1+Input!$D$115)+N55) -> 0 | P55: =IF(SUM(P$20:$CN$20)=0,0,-SUMIFS(P$15:P$19,$B$15:$B$19,$B53)/(1+Input!$D$115)+O55) -> 0 | ... CN55: =IF(SUM(CN$20:$CN$20)=0,0,-SUMIFS(CN$15:CN$19,$B$15:$B$19,$B53)/(1+Input!$D$115)+CM55) -> 0
C56: =C49 -> Commissioning | F56: =SUM(I56:CN56) -> 0 | G56: $ | I56: =IF(AND(H55>0,I55=0),H55,0) -> 0 | J56: =IF(AND(I55>0,J55=0),I55,0) -> 0 | K56: =IF(AND(J55>0,K55=0),J55,0) -> 0 | L56: =IF(AND(K55>0,L55=0),K55,0) -> 0 | M56: =IF(AND(L55>0,M55=0),L55,0) -> 0 | N56: =IF(AND(M55>0,N55=0),M55,0) -> 0 | O56: =IF(AND(N55>0,O55=0),N55,0) -> 0 | P56: =IF(AND(O55>0,P55=0),O55,0) -> 0 | ... CN56: =IF(AND(CM55>0,CN55=0),CM55,0) -> 0
C57: =C50 -> Depreciation | F57: =SUM(I57:CN57) -> 0 | G57: $ | I57: =IF(H58=0,0,-$F55/VLOOKUP($B53,Input!$B$28:$D$32,3,FALSE)/12) -> 0 | J57: =IF(I58=0,0,-$F55/VLOOKUP($B53,Input!$B$28:$D$32,3,FALSE)/12) -> 0 | K57: =IF(J58=0,0,-$F55/VLOOKUP($B53,Input!$B$28:$D$32,3,FALSE)/12) -> 0 | L57: =IF(K58=0,0,-$F55/VLOOKUP($B53,Input!$B$28:$D$32,3,FALSE)/12) -> 0 | M57: =IF(L58=0,0,-$F55/VLOOKUP($B53,Input!$B$28:$D$32,3,FALSE)/12) -> 0 | N57: =IF(M58=0,0,-$F55/VLOOKUP($B53,Input!$B$28:$D$32,3,FALSE)/12) -> 0 | O57: =IF(N58=0,0,-$F55/VLOOKUP($B53,Input!$B$28:$D$32,3,FALSE)/12) -> 0 | P57: =IF(O58=0,0,-$F55/VLOOKUP($B53,Input!$B$28:$D$32,3,FALSE)/12) -> 0 | ... CN57: =IF(CM58=0,0,-$F55/VLOOKUP($B53,Input!$B$28:$D$32,3,FALSE)/12) -> 0
C58: =C51 -> Fixed assets at the end of the period | G58: $ | I58: =IF(ROUND(I54+I57+I56,2)=0,0,I54+I57+I56) -> 0 | J58: =IF(ROUND(J54+J57+J56,2)=0,0,J54+J57+J56) -> 0 | K58: =IF(ROUND(K54+K57+K56,2)=0,0,K54+K57+K56) -> 0 | L58: =IF(ROUND(L54+L57+L56,2)=0,0,L54+L57+L56) -> 0 | M58: =IF(ROUND(M54+M57+M56,2)=0,0,M54+M57+M56) -> 0 | N58: =IF(ROUND(N54+N57+N56,2)=0,0,N54+N57+N56) -> 0 | O58: =IF(ROUND(O54+O57+O56,2)=0,0,O54+O57+O56) -> 0 | P58: =IF(ROUND(P54+P57+P56,2)=0,0,P54+P57+P56) -> 0 | ... CN58: =IF(ROUND(CN54+CN57+CN56,2)=0,0,CN54+CN57+CN56) -> 0
B60: =B19 -> 5. | C60: =C19
C61: =C54 -> Fixed assets at the beginning of the period | G61: $ | I61: =H65 | J61: =I65 -> 0 | K61: =J65 -> 0 | L61: =K65 -> 0 | M61: =L65 -> 0 | N61: =M65 -> 0 | O61: =N65 -> 0 | P61: =O65 -> 0 | ... CN61: =CM65 -> 0
C62: =C55 -> Unfinished production | F62: =MAX(I62:CN62) -> 0 | G62: $ | I62: =IF(SUM(I$20:$CN$20)=0,0,-SUMIFS(I$15:I$19,$B$15:$B$19,$B60)/(1+Input!$D$115)+H62) -> 0 | J62: =IF(SUM(J$20:$CN$20)=0,0,-SUMIFS(J$15:J$19,$B$15:$B$19,$B60)/(1+Input!$D$115)+I62) -> 0 | K62: =IF(SUM(K$20:$CN$20)=0,0,-SUMIFS(K$15:K$19,$B$15:$B$19,$B60)/(1+Input!$D$115)+J62) -> 0 | L62: =IF(SUM(L$20:$CN$20)=0,0,-SUMIFS(L$15:L$19,$B$15:$B$19,$B60)/(1+Input!$D$115)+K62) -> 0 | M62: =IF(SUM(M$20:$CN$20)=0,0,-SUMIFS(M$15:M$19,$B$15:$B$19,$B60)/(1+Input!$D$115)+L62) -> 0 | N62: =IF(SUM(N$20:$CN$20)=0,0,-SUMIFS(N$15:N$19,$B$15:$B$19,$B60)/(1+Input!$D$115)+M62) -> 0 | O62: =IF(SUM(O$20:$CN$20)=0,0,-SUMIFS(O$15:O$19,$B$15:$B$19,$B60)/(1+Input!$D$115)+N62) -> 0 | P62: =IF(SUM(P$20:$CN$20)=0,0,-SUMIFS(P$15:P$19,$B$15:$B$19,$B60)/(1+Input!$D$115)+O62) -> 0 | ... CN62: =IF(SUM(CN$20:$CN$20)=0,0,-SUMIFS(CN$15:CN$19,$B$15:$B$19,$B60)/(1+Input!$D$115)+CM62) -> 0
C63: =C56 -> Commissioning | F63: =SUM(I63:CN63) -> 0 | G63: $ | I63: =IF(AND(H62>0,I62=0),H62,0) -> 0 | J63: =IF(AND(I62>0,J62=0),I62,0) -> 0 | K63: =IF(AND(J62>0,K62=0),J62,0) -> 0 | L63: =IF(AND(K62>0,L62=0),K62,0) -> 0 | M63: =IF(AND(L62>0,M62=0),L62,0) -> 0 | N63: =IF(AND(M62>0,N62=0),M62,0) -> 0 | O63: =IF(AND(N62>0,O62=0),N62,0) -> 0 | P63: =IF(AND(O62>0,P62=0),O62,0) -> 0 | ... CN63: =IF(AND(CM62>0,CN62=0),CM62,0) -> 0
C64: =C57 -> Depreciation | F64: =SUM(I64:CN64) -> 0 | G64: $ | I64: =IF(H65-IF(AND(I61=0,I63=0),0,SUM($H63:I63)/VLOOKUP($B60,Input!$B$28:$E$32,3,FALSE)/12)<0,-H65,-IF(AND(I61=0,I63=0),0,SUM($H63:I63)/VLOOKUP($B60,Input!$B$28:$E$32,3,FALSE)/12)) -> 0 | J64: =IF(I65-IF(AND(J61=0,J63=0),0,SUM($H63:J63)/VLOOKUP($B60,Input!$B$28:$E$32,3,FALSE)/12)<0,-I65,-IF(AND(J61=0,J63=0),0,SUM($H63:J63)/VLOOKUP($B60,Input!$B$28:$E$32,3,FALSE)/12)) -> 0 | K64: =IF(J65-IF(AND(K61=0,K63=0),0,SUM($H63:K63)/VLOOKUP($B60,Input!$B$28:$E$32,3,FALSE)/12)<0,-J65,-IF(AND(K61=0,K63=0),0,SUM($H63:K63)/VLOOKUP($B60,Input!$B$28:$E$32,3,FALSE)/12)) -> 0 | L64: =IF(K65-IF(AND(L61=0,L63=0),0,SUM($H63:L63)/VLOOKUP($B60,Input!$B$28:$E$32,3,FALSE)/12)<0,-K65,-IF(AND(L61=0,L63=0),0,SUM($H63:L63)/VLOOKUP($B60,Input!$B$28:$E$32,3,FALSE)/12)) -> 0 | M64: =IF(L65-IF(AND(M61=0,M63=0),0,SUM($H63:M63)/VLOOKUP($B60,Input!$B$28:$E$32,3,FALSE)/12)<0,-L65,-IF(AND(M61=0,M63=0),0,SUM($H63:M63)/VLOOKUP($B60,Input!$B$28:$E$32,3,FALSE)/12)) -> 0 | N64: =IF(M65-IF(AND(N61=0,N63=0),0,SUM($H63:N63)/VLOOKUP($B60,Input!$B$28:$E$32,3,FALSE)/12)<0,-M65,-IF(AND(N61=0,N63=0),0,SUM($H63:N63)/VLOOKUP($B60,Input!$B$28:$E$32,3,FALSE)/12)) -> 0 | O64: =IF(N65-IF(AND(O61=0,O63=0),0,SUM($H63:O63)/VLOOKUP($B60,Input!$B$28:$E$32,3,FALSE)/12)<0,-N65,-IF(AND(O61=0,O63=0),0,SUM($H63:O63)/VLOOKUP($B60,Input!$B$28:$E$32,3,FALSE)/12)) -> 0 | P64: =IF(O65-IF(AND(P61=0,P63=0),0,SUM($H63:P63)/VLOOKUP($B60,Input!$B$28:$E$32,3,FALSE)/12)<0,-O65,-IF(AND(P61=0,P63=0),0,SUM($H63:P63)/VLOOKUP($B60,Input!$B$28:$E$32,3,FALSE)/12)) -> 0 | ... CN64: =IF(CM65-IF(AND(CN61=0,CN63=0),0,SUM($H63:CN63)/VLOOKUP($B60,Input!$B$28:$E$32,3,FALSE)/12)<0,-CM65,-IF(AND(CN61=0,CN63=0),0,SUM($H63:CN63)/VLOOKUP($B60,Input!$B$28:$E$32,3,FALSE)/12)) -> 0
C65: =C58 -> Fixed assets at the end of the period | G65: $ | I65: =IF(ROUND(I61+I64+I63,2)=0,0,I61+I64+I63) -> 0 | J65: =IF(ROUND(J61+J64+J63,2)=0,0,J61+J64+J63) -> 0 | K65: =IF(ROUND(K61+K64+K63,2)=0,0,K61+K64+K63) -> 0 | L65: =IF(ROUND(L61+L64+L63,2)=0,0,L61+L64+L63) -> 0 | M65: =IF(ROUND(M61+M64+M63,2)=0,0,M61+M64+M63) -> 0 | N65: =IF(ROUND(N61+N64+N63,2)=0,0,N61+N64+N63) -> 0 | O65: =IF(ROUND(O61+O64+O63,2)=0,0,O61+O64+O63) -> 0 | P65: =IF(ROUND(P61+P64+P63,2)=0,0,P61+P64+P63) -> 0 | ... CN65: =IF(ROUND(CN61+CN64+CN63,2)=0,0,CN61+CN64+CN63) -> 0
B70: 3 | C70: =CF!C35 -> Payroll — admin and others
C72: Total | E72: =IFERROR(F72/$F$72,0) -> 1 | F72: =SUM(I72:CN72) -> -1030163.5 | G72: $ | I72: =I86+I73 -> -9500 | J72: =J86+J73 -> -9500 | K72: =K86+K73 -> -9500 | L72: =L86+L73 -> -9500 | M72: =M86+M73 -> -9500 | N72: =N86+N73 -> -10600 | O72: =O86+O73 -> -10600 | P72: =P86+P73 -> -10600 | ... CN72: =CN86+CN73 -> -14205.014
B73: 1. | C73: =CF!C36 -> Salary (Gross) | E73: =IFERROR(F73/$F$72,0) -> 1 | F73: =SUM(I73:CN73) -> -1030163.5 | G73: $ | I73: =SUM(I74:I83) -> -9500 | J73: =SUM(J74:J83) -> -9500 | K73: =SUM(K74:K83) -> -9500 | L73: =SUM(L74:L83) -> -9500 | M73: =SUM(M74:M83) -> -9500 | N73: =SUM(N74:N83) -> -10600 | O73: =SUM(O74:O83) -> -10600 | P73: =SUM(P74:P83) -> -10600 | ... CN73: =SUM(CN74:CN83) -> -14205.014
C74: =Input!C48 -> CEO | E74: =IFERROR(F74/$F$72,0) -> 0.28452989 | F74: =SUM(I74:CN74) -> -293112.3 | G74: $ | I74: =(-IF(AND(I$1>=Input!$F48,I$1<Input!$G48),(Input!$E48),0))*I$7 -> -3000 | J74: =(-IF(AND(J$1>=Input!$F48,J$1<Input!$G48),(Input!$E48),0))*J$7 -> -3000 | K74: =(-IF(AND(K$1>=Input!$F48,K$1<Input!$G48),(Input!$E48),0))*K$7 -> -3000 | L74: =(-IF(AND(L$1>=Input!$F48,L$1<Input!$G48),(Input!$E48),0))*L$7 -> -3000 | M74: =(-IF(AND(M$1>=Input!$F48,M$1<Input!$G48),(Input!$E48),0))*M$7 -> -3000 | N74: =(-IF(AND(N$1>=Input!$F48,N$1<Input!$G48),(Input!$E48),0))*N$7 -> -3000 | O74: =(-IF(AND(O$1>=Input!$F48,O$1<Input!$G48),(Input!$E48),0))*O$7 -> -3000 | P74: =(-IF(AND(P$1>=Input!$F48,P$1<Input!$G48),(Input!$E48),0))*P$7 -> -3000 | ... CN74: =(-IF(AND(CN$1>=Input!$F48,CN$1<Input!$G48),(Input!$E48),0))*CN$7 -> -4020.2869
C75: =Input!C49 -> CPO | E75: =IFERROR(F75/$F$72,0) -> 0.28452989 | F75: =SUM(I75:CN75) -> -293112.3 | G75: $ | I75: =(-IF(AND(I$1>=Input!$F49,I$1<Input!$G49),(Input!$E49),0))*I$7 -> -3000 | J75: =(-IF(AND(J$1>=Input!$F49,J$1<Input!$G49),(Input!$E49),0))*J$7 -> -3000 | K75: =(-IF(AND(K$1>=Input!$F49,K$1<Input!$G49),(Input!$E49),0))*K$7 -> -3000 | L75: =(-IF(AND(L$1>=Input!$F49,L$1<Input!$G49),(Input!$E49),0))*L$7 -> -3000 | M75: =(-IF(AND(M$1>=Input!$F49,M$1<Input!$G49),(Input!$E49),0))*M$7 -> -3000 | N75: =(-IF(AND(N$1>=Input!$F49,N$1<Input!$G49),(Input!$E49),0))*N$7 -> -3000 | O75: =(-IF(AND(O$1>=Input!$F49,O$1<Input!$G49),(Input!$E49),0))*O$7 -> -3000 | P75: =(-IF(AND(P$1>=Input!$F49,P$1<Input!$G49),(Input!$E49),0))*P$7 -> -3000 | ... CN75: =(-IF(AND(CN$1>=Input!$F49,CN$1<Input!$G49),(Input!$E49),0))*CN$7 -> -4020.2869
C76: =Input!C50 -> DevOps | E76: =IFERROR(F76/$F$72,0) -> 0.098988669 | F76: =SUM(I76:CN76) -> -101974.51 | G76: $ | I76: =(-IF(AND(I$1>=Input!$F50,I$1<Input!$G50),(Input!$E50),0))*I$7 -> 0 | J76: =(-IF(AND(J$1>=Input!$F50,J$1<Input!$G50),(Input!$E50),0))*J$7 -> 0 | K76: =(-IF(AND(K$1>=Input!$F50,K$1<Input!$G50),(Input!$E50),0))*K$7 -> 0 | L76: =(-IF(AND(L$1>=Input!$F50,L$1<Input!$G50),(Input!$E50),0))*L$7 -> 0 | M76: =(-IF(AND(M$1>=Input!$F50,M$1<Input!$G50),(Input!$E50),0))*M$7 -> 0 | N76: =(-IF(AND(N$1>=Input!$F50,N$1<Input!$G50),(Input!$E50),0))*N$7 -> -1100 | O76: =(-IF(AND(O$1>=Input!$F50,O$1<Input!$G50),(Input!$E50),0))*O$7 -> -1100 | P76: =(-IF(AND(P$1>=Input!$F50,P$1<Input!$G50),(Input!$E50),0))*P$7 -> -1100 | ... CN76: =(-IF(AND(CN$1>=Input!$F50,CN$1<Input!$G50),(Input!$E50),0))*CN$7 -> -1474.1052
C77: =Input!C51 -> Senior Fullstack Engineer | E77: =IFERROR(F77/$F$72,0) -> 0.33195154 | F77: =SUM(I77:CN77) -> -341964.35 | G77: $ | I77: =(-IF(AND(I$1>=Input!$F51,I$1<Input!$G51),(Input!$E51),0))*I$7 -> -3500 | J77: =(-IF(AND(J$1>=Input!$F51,J$1<Input!$G51),(Input!$E51),0))*J$7 -> -3500 | K77: =(-IF(AND(K$1>=Input!$F51,K$1<Input!$G51),(Input!$E51),0))*K$7 -> -3500 | L77: =(-IF(AND(L$1>=Input!$F51,L$1<Input!$G51),(Input!$E51),0))*L$7 -> -3500 | M77: =(-IF(AND(M$1>=Input!$F51,M$1<Input!$G51),(Input!$E51),0))*M$7 -> -3500 | N77: =(-IF(AND(N$1>=Input!$F51,N$1<Input!$G51),(Input!$E51),0))*N$7 -> -3500 | O77: =(-IF(AND(O$1>=Input!$F51,O$1<Input!$G51),(Input!$E51),0))*O$7 -> -3500 | P77: =(-IF(AND(P$1>=Input!$F51,P$1<Input!$G51),(Input!$E51),0))*P$7 -> -3500 | ... CN77: =(-IF(AND(CN$1>=Input!$F51,CN$1<Input!$G51),(Input!$E51),0))*CN$7 -> -4690.3347
C78: =Input!C52 | E78: =IFERROR(F78/$F$72,0) -> 0 | F78: =SUM(I78:CN78) -> 0 | G78: $ | I78: =(-IF(AND(I$1>=Input!$F52,I$1<Input!$G52),(Input!$E52),0))*I$7 -> 0 | J78: =(-IF(AND(J$1>=Input!$F52,J$1<Input!$G52),(Input!$E52),0))*J$7 -> 0 | K78: =(-IF(AND(K$1>=Input!$F52,K$1<Input!$G52),(Input!$E52),0))*K$7 -> 0 | L78: =(-IF(AND(L$1>=Input!$F52,L$1<Input!$G52),(Input!$E52),0))*L$7 -> 0 | M78: =(-IF(AND(M$1>=Input!$F52,M$1<Input!$G52),(Input!$E52),0))*M$7 -> 0 | N78: =(-IF(AND(N$1>=Input!$F52,N$1<Input!$G52),(Input!$E52),0))*N$7 -> 0 | O78: =(-IF(AND(O$1>=Input!$F52,O$1<Input!$G52),(Input!$E52),0))*O$7 -> 0 | P78: =(-IF(AND(P$1>=Input!$F52,P$1<Input!$G52),(Input!$E52),0))*P$7 -> 0 | ... CN78: =(-IF(AND(CN$1>=Input!$F52,CN$1<Input!$G52),(Input!$E52),0))*CN$7 -> 0
C79: =Input!C53 | E79: =IFERROR(F79/$F$72,0) -> 0 | F79: =SUM(I79:CN79) -> 0 | G79: $ | I79: =(-IF(AND(I$1>=Input!$F53,I$1<Input!$G53),(Input!$E53),0))*I$7 -> 0 | J79: =(-IF(AND(J$1>=Input!$F53,J$1<Input!$G53),(Input!$E53),0))*J$7 -> 0 | K79: =(-IF(AND(K$1>=Input!$F53,K$1<Input!$G53),(Input!$E53),0))*K$7 -> 0 | L79: =(-IF(AND(L$1>=Input!$F53,L$1<Input!$G53),(Input!$E53),0))*L$7 -> 0 | M79: =(-IF(AND(M$1>=Input!$F53,M$1<Input!$G53),(Input!$E53),0))*M$7 -> 0 | N79: =(-IF(AND(N$1>=Input!$F53,N$1<Input!$G53),(Input!$E53),0))*N$7 -> 0 | O79: =(-IF(AND(O$1>=Input!$F53,O$1<Input!$G53),(Input!$E53),0))*O$7 -> 0 | P79: =(-IF(AND(P$1>=Input!$F53,P$1<Input!$G53),(Input!$E53),0))*P$7 -> 0 | ... CN79: =(-IF(AND(CN$1>=Input!$F53,CN$1<Input!$G53),(Input!$E53),0))*CN$7 -> 0
C80: =Input!C54 | E80: =IFERROR(F80/$F$72,0) -> 0 | F80: =SUM(I80:CN80) -> 0 | G80: $ | I80: =(-IF(AND(I$1>=Input!$F54,I$1<Input!$G54),(Input!$E54),0))*I$7 -> 0 | J80: =(-IF(AND(J$1>=Input!$F54,J$1<Input!$G54),(Input!$E54),0))*J$7 -> 0 | K80: =(-IF(AND(K$1>=Input!$F54,K$1<Input!$G54),(Input!$E54),0))*K$7 -> 0 | L80: =(-IF(AND(L$1>=Input!$F54,L$1<Input!$G54),(Input!$E54),0))*L$7 -> 0 | M80: =(-IF(AND(M$1>=Input!$F54,M$1<Input!$G54),(Input!$E54),0))*M$7 -> 0 | N80: =(-IF(AND(N$1>=Input!$F54,N$1<Input!$G54),(Input!$E54),0))*N$7 -> 0 | O80: =(-IF(AND(O$1>=Input!$F54,O$1<Input!$G54),(Input!$E54),0))*O$7 -> 0 | P80: =(-IF(AND(P$1>=Input!$F54,P$1<Input!$G54),(Input!$E54),0))*P$7 -> 0 | ... CN80: =(-IF(AND(CN$1>=Input!$F54,CN$1<Input!$G54),(Input!$E54),0))*CN$7 -> 0
C81: =Input!C55 | E81: =IFERROR(F81/$F$72,0) -> 0 | F81: =SUM(I81:CN81) -> 0 | G81: $ | I81: =(-IF(AND(I$1>=Input!$F55,I$1<Input!$G55),(Input!$E55),0))*I$7 -> 0 | J81: =(-IF(AND(J$1>=Input!$F55,J$1<Input!$G55),(Input!$E55),0))*J$7 -> 0 | K81: =(-IF(AND(K$1>=Input!$F55,K$1<Input!$G55),(Input!$E55),0))*K$7 -> 0 | L81: =(-IF(AND(L$1>=Input!$F55,L$1<Input!$G55),(Input!$E55),0))*L$7 -> 0 | M81: =(-IF(AND(M$1>=Input!$F55,M$1<Input!$G55),(Input!$E55),0))*M$7 -> 0 | N81: =(-IF(AND(N$1>=Input!$F55,N$1<Input!$G55),(Input!$E55),0))*N$7 -> 0 | O81: =(-IF(AND(O$1>=Input!$F55,O$1<Input!$G55),(Input!$E55),0))*O$7 -> 0 | P81: =(-IF(AND(P$1>=Input!$F55,P$1<Input!$G55),(Input!$E55),0))*P$7 -> 0 | ... CN81: =(-IF(AND(CN$1>=Input!$F55,CN$1<Input!$G55),(Input!$E55),0))*CN$7 -> 0
C82: =Input!C56 | E82: =IFERROR(F82/$F$72,0) -> 0 | F82: =SUM(I82:CN82) -> 0 | G82: $ | I82: =(-IF(AND(I$1>=Input!$F56,I$1<Input!$G56),(Input!$E56),0))*I$7 -> 0 | J82: =(-IF(AND(J$1>=Input!$F56,J$1<Input!$G56),(Input!$E56),0))*J$7 -> 0 | K82: =(-IF(AND(K$1>=Input!$F56,K$1<Input!$G56),(Input!$E56),0))*K$7 -> 0 | L82: =(-IF(AND(L$1>=Input!$F56,L$1<Input!$G56),(Input!$E56),0))*L$7 -> 0 | M82: =(-IF(AND(M$1>=Input!$F56,M$1<Input!$G56),(Input!$E56),0))*M$7 -> 0 | N82: =(-IF(AND(N$1>=Input!$F56,N$1<Input!$G56),(Input!$E56),0))*N$7 -> 0 | O82: =(-IF(AND(O$1>=Input!$F56,O$1<Input!$G56),(Input!$E56),0))*O$7 -> 0 | P82: =(-IF(AND(P$1>=Input!$F56,P$1<Input!$G56),(Input!$E56),0))*P$7 -> 0 | ... CN82: =(-IF(AND(CN$1>=Input!$F56,CN$1<Input!$G56),(Input!$E56),0))*CN$7 -> 0
C83: =Input!C57 | E83: =IFERROR(F83/$F$72,0) -> 0 | F83: =SUM(I83:CN83) -> 0 | G83: $ | I83: =(-IF(AND(I$1>=Input!$F57,I$1<Input!$G57),(Input!$E57),0))*I$7 -> 0 | J83: =(-IF(AND(J$1>=Input!$F57,J$1<Input!$G57),(Input!$E57),0))*J$7 -> 0 | K83: =(-IF(AND(K$1>=Input!$F57,K$1<Input!$G57),(Input!$E57),0))*K$7 -> 0 | L83: =(-IF(AND(L$1>=Input!$F57,L$1<Input!$G57),(Input!$E57),0))*L$7 -> 0 | M83: =(-IF(AND(M$1>=Input!$F57,M$1<Input!$G57),(Input!$E57),0))*M$7 -> 0 | N83: =(-IF(AND(N$1>=Input!$F57,N$1<Input!$G57),(Input!$E57),0))*N$7 -> 0 | O83: =(-IF(AND(O$1>=Input!$F57,O$1<Input!$G57),(Input!$E57),0))*O$7 -> 0 | P83: =(-IF(AND(P$1>=Input!$F57,P$1<Input!$G57),(Input!$E57),0))*P$7 -> 0 | ... CN83: =(-IF(AND(CN$1>=Input!$F57,CN$1<Input!$G57),(Input!$E57),0))*CN$7 -> 0
B86: 2. | C86: =CF!C37 -> Additional taxes and insurance contributions for employees | E86: =IFERROR(F86/$F$72,0) -> 0 | F86: =SUM(I86:CN86) -> 0 | G86: $ | I86: =SUM(I87:I96) -> 0 | J86: =SUM(J87:J96) -> 0 | K86: =SUM(K87:K96) -> 0 | L86: =SUM(L87:L96) -> 0 | M86: =SUM(M87:M96) -> 0 | N86: =SUM(N87:N96) -> 0 | O86: =SUM(O87:O96) -> 0 | P86: =SUM(P87:P96) -> 0 | ... CN86: =SUM(CN87:CN96) -> 0
C87: =C74 -> CEO | E87: =IFERROR(F87/$F$72,0) -> 0 | F87: =SUM(I87:CN87) -> 0 | G87: $ | I87: =I74*Input!$D$116 -> 0 | J87: =J74*Input!$D$116 -> 0 | K87: =K74*Input!$D$116 -> 0 | L87: =L74*Input!$D$116 -> 0 | M87: =M74*Input!$D$116 -> 0 | N87: =N74*Input!$D$116 -> 0 | O87: =O74*Input!$D$116 -> 0 | P87: =P74*Input!$D$116 -> 0 | ... CN87: =CN74*Input!$D$116 -> 0
C88: =C75 -> CPO | E88: =IFERROR(F88/$F$72,0) -> 0 | F88: =SUM(I88:CN88) -> 0 | G88: $ | I88: =I75*Input!$D$116 -> 0 | J88: =J75*Input!$D$116 -> 0 | K88: =K75*Input!$D$116 -> 0 | L88: =L75*Input!$D$116 -> 0 | M88: =M75*Input!$D$116 -> 0 | N88: =N75*Input!$D$116 -> 0 | O88: =O75*Input!$D$116 -> 0 | P88: =P75*Input!$D$116 -> 0 | ... CN88: =CN75*Input!$D$116 -> 0
C89: =C76 -> DevOps | E89: =IFERROR(F89/$F$72,0) -> 0 | F89: =SUM(I89:CN89) -> 0 | G89: $ | I89: =I76*Input!$D$116 -> 0 | J89: =J76*Input!$D$116 -> 0 | K89: =K76*Input!$D$116 -> 0 | L89: =L76*Input!$D$116 -> 0 | M89: =M76*Input!$D$116 -> 0 | N89: =N76*Input!$D$116 -> 0 | O89: =O76*Input!$D$116 -> 0 | P89: =P76*Input!$D$116 -> 0 | ... CN89: =CN76*Input!$D$116 -> 0
C90: =C77 -> Senior Fullstack Engineer | E90: =IFERROR(F90/$F$72,0) -> 0 | F90: =SUM(I90:CN90) -> 0 | G90: $ | I90: =I77*Input!$D$116 -> 0 | J90: =J77*Input!$D$116 -> 0 | K90: =K77*Input!$D$116 -> 0 | L90: =L77*Input!$D$116 -> 0 | M90: =M77*Input!$D$116 -> 0 | N90: =N77*Input!$D$116 -> 0 | O90: =O77*Input!$D$116 -> 0 | P90: =P77*Input!$D$116 -> 0 | ... CN90: =CN77*Input!$D$116 -> 0
C91: =C78 | E91: =IFERROR(F91/$F$72,0) -> 0 | F91: =SUM(I91:CN91) -> 0 | G91: $ | I91: =I78*Input!$D$116 -> 0 | J91: =J78*Input!$D$116 -> 0 | K91: =K78*Input!$D$116 -> 0 | L91: =L78*Input!$D$116 -> 0 | M91: =M78*Input!$D$116 -> 0 | N91: =N78*Input!$D$116 -> 0 | O91: =O78*Input!$D$116 -> 0 | P91: =P78*Input!$D$116 -> 0 | ... CN91: =CN78*Input!$D$116 -> 0
C92: =C79 | E92: =IFERROR(F92/$F$72,0) -> 0 | F92: =SUM(I92:CN92) -> 0 | G92: $ | I92: =I79*Input!$D$116 -> 0 | J92: =J79*Input!$D$116 -> 0 | K92: =K79*Input!$D$116 -> 0 | L92: =L79*Input!$D$116 -> 0 | M92: =M79*Input!$D$116 -> 0 | N92: =N79*Input!$D$116 -> 0 | O92: =O79*Input!$D$116 -> 0 | P92: =P79*Input!$D$116 -> 0 | ... CN92: =CN79*Input!$D$116 -> 0
C93: =C80 | E93: =IFERROR(F93/$F$72,0) -> 0 | F93: =SUM(I93:CN93) -> 0 | G93: $ | I93: =I80*Input!$D$116 -> 0 | J93: =J80*Input!$D$116 -> 0 | K93: =K80*Input!$D$116 -> 0 | L93: =L80*Input!$D$116 -> 0 | M93: =M80*Input!$D$116 -> 0 | N93: =N80*Input!$D$116 -> 0 | O93: =O80*Input!$D$116 -> 0 | P93: =P80*Input!$D$116 -> 0 | ... CN93: =CN80*Input!$D$116 -> 0
C94: =C81 | E94: =IFERROR(F94/$F$72,0) -> 0 | F94: =SUM(I94:CN94) -> 0 | G94: $ | I94: =I81*Input!$D$116 -> 0 | J94: =J81*Input!$D$116 -> 0 | K94: =K81*Input!$D$116 -> 0 | L94: =L81*Input!$D$116 -> 0 | M94: =M81*Input!$D$116 -> 0 | N94: =N81*Input!$D$116 -> 0 | O94: =O81*Input!$D$116 -> 0 | P94: =P81*Input!$D$116 -> 0 | ... CN94: =CN81*Input!$D$116 -> 0
C95: =C82 | E95: =IFERROR(F95/$F$72,0) -> 0 | F95: =SUM(I95:CN95) -> 0 | G95: $ | I95: =I82*Input!$D$116 -> 0 | J95: =J82*Input!$D$116 -> 0 | K95: =K82*Input!$D$116 -> 0 | L95: =L82*Input!$D$116 -> 0 | M95: =M82*Input!$D$116 -> 0 | N95: =N82*Input!$D$116 -> 0 | O95: =O82*Input!$D$116 -> 0 | P95: =P82*Input!$D$116 -> 0 | ... CN95: =CN82*Input!$D$116 -> 0
C96: =C83 | E96: =IFERROR(F96/$F$72,0) -> 0 | F96: =SUM(I96:CN96) -> 0 | G96: $ | I96: =I83*Input!$D$116 -> 0 | J96: =J83*Input!$D$116 -> 0 | K96: =K83*Input!$D$116 -> 0 | L96: =L83*Input!$D$116 -> 0 | M96: =M83*Input!$D$116 -> 0 | N96: =N83*Input!$D$116 -> 0 | O96: =O83*Input!$D$116 -> 0 | P96: =P83*Input!$D$116 -> 0 | ... CN96: =CN83*Input!$D$116 -> 0
B101: 4 | C101: Taxes
B103: 1. | C103: VAT
C105: Input VAT (Capex) | F105: =SUM(I105:CN105) -> -1161.9048 | G105: $ | I105: =CF!I22/(1+Input!$D$115)*Input!$D$115 -> -238.09524 | J105: =CF!J22/(1+Input!$D$115)*Input!$D$115 -> -238.09524 | K105: =CF!K22/(1+Input!$D$115)*Input!$D$115 -> -238.09524 | L105: =CF!L22/(1+Input!$D$115)*Input!$D$115 -> -238.09524 | M105: =CF!M22/(1+Input!$D$115)*Input!$D$115 -> -209.52381 | N105: =CF!N22/(1+Input!$D$115)*Input!$D$115 -> 0 | O105: =CF!O22/(1+Input!$D$115)*Input!$D$115 -> 0 | P105: =CF!P22/(1+Input!$D$115)*Input!$D$115 -> 0 | ... CN105: =CF!CN22/(1+Input!$D$115)*Input!$D$115 -> 0
C106: Input VAT (Opex) | F106: =SUM(I106:CN106) -> -71045.271 | G106: $ | I106: =(CF!I30+CF!I38+CF!I49)/(1+Input!$D$115)*Input!$D$115 -> -64.285714 | J106: =(CF!J30+CF!J38+CF!J49)/(1+Input!$D$115)*Input!$D$115 -> -64.285714 | K106: =(CF!K30+CF!K38+CF!K49)/(1+Input!$D$115)*Input!$D$115 -> -64.285714 | L106: =(CF!L30+CF!L38+CF!L49)/(1+Input!$D$115)*Input!$D$115 -> -64.285714 | M106: =(CF!M30+CF!M38+CF!M49)/(1+Input!$D$115)*Input!$D$115 -> -64.285714 | N106: =(CF!N30+CF!N38+CF!N49)/(1+Input!$D$115)*Input!$D$115 -> -64.285714 | O106: =(CF!O30+CF!O38+CF!O49)/(1+Input!$D$115)*Input!$D$115 -> -64.285714 | P106: =(CF!P30+CF!P38+CF!P49)/(1+Input!$D$115)*Input!$D$115 -> -64.285714 | ... CN106: =(CF!CN30+CF!CN38+CF!CN49)/(1+Input!$D$115)*Input!$D$115 -> -1088.1751
C107: Output VAT | F107: =SUM(I107:CN107) -> 374377.28 | G107: $ | I107: =CF!I27/(1+Input!$D$115)*Input!$D$115 -> 0 | J107: =CF!J27/(1+Input!$D$115)*Input!$D$115 -> 0 | K107: =CF!K27/(1+Input!$D$115)*Input!$D$115 -> 0 | L107: =CF!L27/(1+Input!$D$115)*Input!$D$115 -> 0 | M107: =CF!M27/(1+Input!$D$115)*Input!$D$115 -> 0 | N107: =CF!N27/(1+Input!$D$115)*Input!$D$115 -> 0 | O107: =CF!O27/(1+Input!$D$115)*Input!$D$115 -> 0 | P107: =CF!P27/(1+Input!$D$115)*Input!$D$115 -> 0 | ... CN107: =CF!CN27/(1+Input!$D$115)*Input!$D$115 -> 5853.8781
C108: Total VAT | F108: =SUM(I108:CN108) -> -302170.1 | G108: $ | I108: =-SUM(I105:I107) -> 302.38095 | J108: =-SUM(J105:J107) -> 302.38095 | K108: =-SUM(K105:K107) -> 302.38095 | L108: =-SUM(L105:L107) -> 302.38095 | M108: =-SUM(M105:M107) -> 273.80952 | N108: =-SUM(N105:N107) -> 64.285714 | O108: =-SUM(O105:O107) -> 64.285714 | P108: =-SUM(P105:P107) -> 64.285714 | ... CN108: =-SUM(CN105:CN107) -> -4765.703
C109: VAT accrued | F109: =SUM(I109:CN109) -> 302170.1 | G109: $ | I109: =-MIN(0,SUM($H108:I108,$H109:H109)) -> 0 | J109: =-MIN(0,SUM($H108:J108,$H109:I109)) -> 0 | K109: =-MIN(0,SUM($H108:K108,$H109:J109)) -> 0 | L109: =-MIN(0,SUM($H108:L108,$H109:K109)) -> 0 | M109: =-MIN(0,SUM($H108:M108,$H109:L109)) -> 0 | N109: =-MIN(0,SUM($H108:N108,$H109:M109)) -> 0 | O109: =-MIN(0,SUM($H108:O108,$H109:N109)) -> 0 | P109: =-MIN(0,SUM($H108:P108,$H109:O109)) -> 0 | ... CN109: =-MIN(0,SUM($H108:CN108,$H109:CM109)) -> 4765.703
C110: VAT movement | F110: =SUM(I110:CN110) -> -302170.1 | G110: $ | I110: =-I109 -> 0 | J110: =-J109 -> 0 | K110: =-K109 -> 0 | L110: =-L109 -> 0 | M110: =-M109 -> 0 | N110: =-N109 -> 0 | O110: =-O109 -> 0 | P110: =-P109 -> 0 | ... CN110: =-CN109 -> -4765.703
C112: Deferred tax assets (VAT) | G112: $ | I112: =IF(ROUND(SUM($H$108:I108)-SUM($H$110:I110),3)=0,0,(SUM($H$108:I108)-SUM($H$110:I110))) -> 302.38095 | J112: =IF(ROUND(SUM($H$108:J108)-SUM($H$110:J110),3)=0,0,(SUM($H$108:J108)-SUM($H$110:J110))) -> 604.7619 | K112: =IF(ROUND(SUM($H$108:K108)-SUM($H$110:K110),3)=0,0,(SUM($H$108:K108)-SUM($H$110:K110))) -> 907.14286 | L112: =IF(ROUND(SUM($H$108:L108)-SUM($H$110:L110),3)=0,0,(SUM($H$108:L108)-SUM($H$110:L110))) -> 1209.5238 | M112: =IF(ROUND(SUM($H$108:M108)-SUM($H$110:M110),3)=0,0,(SUM($H$108:M108)-SUM($H$110:M110))) -> 1483.3333 | N112: =IF(ROUND(SUM($H$108:N108)-SUM($H$110:N110),3)=0,0,(SUM($H$108:N108)-SUM($H$110:N110))) -> 1547.619 | O112: =IF(ROUND(SUM($H$108:O108)-SUM($H$110:O110),3)=0,0,(SUM($H$108:O108)-SUM($H$110:O110))) -> 1611.9048 | P112: =IF(ROUND(SUM($H$108:P108)-SUM($H$110:P110),3)=0,0,(SUM($H$108:P108)-SUM($H$110:P110))) -> 1676.1905 | ... CN112: =IF(ROUND(SUM($H$108:CN108)-SUM($H$110:CN110),3)=0,0,(SUM($H$108:CN108)-SUM($H$110:CN110))) -> 0
B115: 2. | C115: Income tax
B117: 2.1. | C117: General
C118: Accrual | F118: =SUM(I118:CN118) -> -451191.48 | G118: $ | I118: =-PL!I51*Input!$D$114 -> 970.71429 | J118: =-PL!J51*Input!$D$114 -> 970.71429 | K118: =-PL!K51*Input!$D$114 -> 970.71429 | L118: =-PL!L51*Input!$D$114 -> 970.71429 | M118: =-PL!M51*Input!$D$114 -> 970.71429 | N118: =-PL!N51*Input!$D$114 -> 1069.7143 | O118: =-PL!O51*Input!$D$114 -> 1104.5714 | P118: =-PL!P51*Input!$D$114 -> 1104.5714 | ... CN118: =-PL!CN51*Input!$D$114 -> -7299.8141
C119: Payment | F119: =SUM(I119:CN119) -> -451191.48 | G119: $ | I119: =MIN(0,-SUM($H119:H119)+SUM($H118:I118)) -> 0 | J119: =MIN(0,-SUM($H119:I119)+SUM($H118:J118)) -> 0 | K119: =MIN(0,-SUM($H119:J119)+SUM($H118:K118)) -> 0 | L119: =MIN(0,-SUM($H119:K119)+SUM($H118:L118)) -> 0 | M119: =MIN(0,-SUM($H119:L119)+SUM($H118:M118)) -> 0 | N119: =MIN(0,-SUM($H119:M119)+SUM($H118:N118)) -> 0 | O119: =MIN(0,-SUM($H119:N119)+SUM($H118:O118)) -> 0 | P119: =MIN(0,-SUM($H119:O119)+SUM($H118:P118)) -> 0 | ... CN119: =MIN(0,-SUM($H119:CM119)+SUM($H118:CN118)) -> -7299.8141
C121: Deferred tax assets (income taxes) | G121: $ | I121: =IF(ROUND(SUM($H$118:I118)-SUM($H$119:I119),3)=0,0,(SUM($H$118:I118)-SUM($H$119:I119))) -> 970.71429 | J121: =IF(ROUND(SUM($H$118:J118)-SUM($H$119:J119),3)=0,0,(SUM($H$118:J118)-SUM($H$119:J119))) -> 1941.4286 | K121: =IF(ROUND(SUM($H$118:K118)-SUM($H$119:K119),3)=0,0,(SUM($H$118:K118)-SUM($H$119:K119))) -> 2912.1429 | L121: =IF(ROUND(SUM($H$118:L118)-SUM($H$119:L119),3)=0,0,(SUM($H$118:L118)-SUM($H$119:L119))) -> 3882.8571 | M121: =IF(ROUND(SUM($H$118:M118)-SUM($H$119:M119),3)=0,0,(SUM($H$118:M118)-SUM($H$119:M119))) -> 4853.5714 | N121: =IF(ROUND(SUM($H$118:N118)-SUM($H$119:N119),3)=0,0,(SUM($H$118:N118)-SUM($H$119:N119))) -> 5923.2857 | O121: =IF(ROUND(SUM($H$118:O118)-SUM($H$119:O119),3)=0,0,(SUM($H$118:O118)-SUM($H$119:O119))) -> 7027.8571 | P121: =IF(ROUND(SUM($H$118:P118)-SUM($H$119:P119),3)=0,0,(SUM($H$118:P118)-SUM($H$119:P119))) -> 8132.4286 | ... CN121: =IF(ROUND(SUM($H$118:CN118)-SUM($H$119:CN119),3)=0,0,(SUM($H$118:CN118)-SUM($H$119:CN119))) -> 0
B123: 2.2. | C123: No interest on credit or loan
C124: Accrual | F124: =SUM(I124:CN124) -> -451191.48 | G124: $ | I124: =-(PL!I51-PL!I50)*Input!$D$114 -> 970.71429 | J124: =-(PL!J51-PL!J50)*Input!$D$114 -> 970.71429 | K124: =-(PL!K51-PL!K50)*Input!$D$114 -> 970.71429 | L124: =-(PL!L51-PL!L50)*Input!$D$114 -> 970.71429 | M124: =-(PL!M51-PL!M50)*Input!$D$114 -> 970.71429 | N124: =-(PL!N51-PL!N50)*Input!$D$114 -> 1069.7143 | O124: =-(PL!O51-PL!O50)*Input!$D$114 -> 1104.5714 | P124: =-(PL!P51-PL!P50)*Input!$D$114 -> 1104.5714 | ... CN124: =-(PL!CN51-PL!CN50)*Input!$D$114 -> -7299.8141
C125: Payment | F125: =SUM(I125:CN125) -> -451191.48 | G125: $ | I125: =MIN(0,-SUM($H125:H125)+SUM($H124:I124)) -> 0 | J125: =MIN(0,-SUM($H125:I125)+SUM($H124:J124)) -> 0 | K125: =MIN(0,-SUM($H125:J125)+SUM($H124:K124)) -> 0 | L125: =MIN(0,-SUM($H125:K125)+SUM($H124:L124)) -> 0 | M125: =MIN(0,-SUM($H125:L125)+SUM($H124:M124)) -> 0 | N125: =MIN(0,-SUM($H125:M125)+SUM($H124:N124)) -> 0 | O125: =MIN(0,-SUM($H125:N125)+SUM($H124:O124)) -> 0 | P125: =MIN(0,-SUM($H125:O125)+SUM($H124:P124)) -> 0 | ... CN125: =MIN(0,-SUM($H125:CM125)+SUM($H124:CN124)) -> -7299.8141

Sheet Assumptions
A1: Unit Economics Benchmarks for Recruitment Tech SaaS
A3: Conversion Funnel Metrics
B5: 1. Conversion to Registration (C1):
B6: Typical range: 2-5% for cold traffic
B7: Good: 5-10% for targeted campaigns | C7: таргетируем рекламу в ЛИ
B8: Excellent: 10-15% with strong product-market fit | F8: Recommendations:
F9: Focus on Sales-Assisted Model: Recruitment tools typically require demos/onboarding. Target 20-30% demo→paid conversion.
B10: 2. Conversion from Registration to Payment (C2): | F10: Pricing Strategy: Consider $300-800/month for small recruiting teams (3-10 recruiters), scaling with seats or job slots.
B11: Free trial → Paid: 10-25% | C11: даем бесплатные кредиты | F11: Reduce Churn: Focus on usage metrics - customers who use your tool 3+ times/week have <2% churn vs 8%+ for occasional users.
B12: Freemium → Paid: 2-5% | F12: CAC Payback Period: Aim for <12 months; recruitment tech often sees 6-18 month payback.
B13: Demo/Sales-led: 20-40% | C13: делаем кастевы с выходом на продажу | F13: Channel Mix: LinkedIn + content marketing + partnerships with ATS providers tend to work best for recruitment ICP.
B14: For B2B HR/Recruitment tools: 15-30% (typically sales-assisted)
B16: 3. Final Conversion from Click to Purchase (C3):
B17: Overall: 0.5-2% for B2B SaaS | E17: делаем кастевы с выходом на продажу -> даем бесплатные кредиты
B18: Recruitment tech: 1-3% with targeted marketing | E18: кажется у нас тут логика сломана: сделали кастев, дали пользоваться, потом еще раз с человеком созваниваться?
A20: Revenue Metrics
B21: 4. Average Revenue Per Paying Customer (ARPPU): | D21: Customer = company | F21: я больше не буду пессимистом и заложу средние начения по mid маркету
B22: Small teams (1-10 users): $100-500/month | C22: <- | D22: Фриланс рекрутеры | F22: С1 | G22: 0.075 | H22: оставил заявку
B23: Mid-market (10-50 users): $500-2,500/month | C23: <- | D23: Рекрутинговые агенства | F23: C2 | G23: 0.3 | H23: использовал триал
B24: Enterprise (50+ users): $2,500-10,000+/month | F24: C3 | G24: 0.02 | H24: попытался накинуть токенов
B25: Recruitment tech average: $200-1,000/month per customer | F25: ARPPU | G25: 1500 | H25: $
F26: CL | G26: 27 | H26: months
B27: 5. Customer Lifetime (CL): | F27: LTV | G27: =G25*G26 -> 40500 | H27: $
B28: B2B SaaS average: 24-48 months | F28: Churn % | G28: 0.015
B29: HR/Recruitment tech: 18-36 months | D29: поверим в этот диапазон | F29: LI ADS | G29: 12.5 | H29: $
B30: Enterprise customers: 36-60+ months
B32: 6. Lifetime Value (LTV):
B33: Formula: ARPPU × Customer Lifetime | F33: Files / user /month | G33: 200
B34: Small business: $2,400-$6,000
B35: Mid-market: $12,000-$48,000
B36: Enterprise: $60,000-$240,000+
B37: Target LTV:CAC ratio: 3:1 minimum, 4:1-5:1 ideal
K38: SaaS is usually a “winner-takes-all” game, and it is therefore important to grab market share as fast as possible to make sure you are the winner in your space.
B39: 7. Churn Rate:
B40: Monthly churn (SMB): 3-7% | D40: где-то читал что churn rate for AI products нужно считать иначе с большим средним скользящим
B41: Monthly churn (Mid-market): 1-3%
B42: Monthly churn (Enterprise): 0.5-1.5%
B43: Annual churn target: <20% for healthy SaaS
B44: Recruitment tech: 2-5% monthly (higher volatility in hiring cycles)
A46: Acquisition Metrics
B47: 8. Cost of 1 Visit (Click):
B48: Google Ads (B2B HR keywords): $3-15/click
B49: LinkedIn Ads: $5-20/click
B50: Content marketing/SEO: $0.50-3/click (blended)
B51: Retargeting: $1-5/click
B53: 9. Customer Acquisition Cost (CAC):
B54: Target CAC: $500-3,000 for SMB
B55: Mid-market CAC: $3,000-10,000
B56: Enterprise CAC: $10,000-50,000+
B57: Recruitment tech average: $1,500-5,000
B58: Key Benchmarks for Your ICP (Recruiters/TA Teams):
B63: Paid Search (Google Ads)
E64: https://www.forentrepreneurs.com/saas-metrics-2/
B65: High-intent keywords (expensive but convert well):
B66: "applicant tracking system" - $8-25/click
B67: "recruitment software" - $6-18/click
B68: "hiring platform" - $5-15/click
B69: "ATS for recruiters" - $7-20/click
B70: "technical recruiting tool" - $4-12/click | I70: Target | J70: Best-in-Class
I71: 0.05 | J71: 0.1
B72: Mid-funnel keywords (better value): | I72: 0.25 | J72: 0.35
B73: "how to find software engineers" - $3-8/click | I73: 0.015 | J73: 0.03
B74: "tech recruiting tips" - $2-6/click | E74: Clicks for 1 Customer | F74: CAC | G74: LTV ($400 × 24mo) | H74: LTV:CAC | I74: 500 | J74: 1000
B75: "candidate screening tool" - $4-10/click | E75: 2500 | F75: 37500 | G75: 9600 | H75: 0.26:1 | I75: 30 mo | J75: 42 mo
B76: Expected average: $8-15/click for bottom-funnel, $3-7/click blended | E76: 2500 | F76: 30000 | G76: 9600 | H76: 0.32:1 | I76: 15000 | J76: 42000
E77: 2500 | F77: 20000 | G77: 9600 | H77: 0.48:1 | I77: 0.03 | J77: 0.015
B78: LinkedIn Ads (Best for your ICP) | E78: 2500 | F78: 12500 | G78: 9600 | H78: 0.77:1 | I78: 2000 | J78: 1000
I79: 4:1 | J79: 10:1
B80: Targeting recruiters/TA professionals:
B81: Sponsored Content: $8-20/click
B82: Message Ads (InMail): $0.50-2/send (different metric)
B83: Text Ads: $4-12/click
B84: Filters that increase cost:
B86: Job titles: "Technical Recruiter", "Talent Acquisition Manager" - premium
B87: Company size: 50-500 employees - moderate
B88: Industry: Tech/Software - premium
B89: Expected average: $10-18/click
B91: Social Media
B92: Facebook/Instagram: $1-4/click (lower quality for B2B)
B93: Twitter/X: $2-6/click (tech-savvy audience)
... B124: CPC
B125: 15
B126: 12
B127: 8
B128: 5
B129: This shows you need to improve conversions, not just optimize CPC!
B131: Better Scenario (optimized funnel):
B132: With 10% C1 and 30% C2 (sales-assisted):
B134: 333 clicks needed per customer
B135: At $10/click → CAC = $3,330
B136: LTV:CAC = 2.9:1 ✅
B137: Bottom line: For your ICP, plan for $8-15/click initially, but focus more on conversion optimization than CPC reduction.
